Workbook

Sheet Inventario
A1: env | B1: namespace | C1: providerEnv | D1: deployedName | E1: applicationName | F1: configName | G1: microserviceType | H1: image | I1: isFeature | J1: deploymentName | K1: helmChartVersion | L1: ownerEmail | M1: gitUrl | N1: microserviceVersion | O1: configVersion | P1: frameworkVersion | Q1: configUrl
A2: PRO | B2: ns-storage | C2: AWS | D2: ms-storage-ondemand | E2: ms-storage-ondemand | F2: ms-storage-ondemand-micros-app-configs | G2: p4ms | H2: artifactory.apps.devops.aws.bancsabadell.com/p4-virtual/p4des/ms-storage-ondemand:2.1.0 | I2: =FALSE() -> FALSE | J2: ms-storage-ondemand-p4ms | K2: p4ms-1.1.10 | L2: v888087@adgbs.com | M2: https://bitbucket.apps.devops.aws.bancsabadell.com/scm/p4des/ms-storage-ondemand.git | N2: 2.1.0 | O2: 3.0.0 | P2: 3.9.6 | Q2: https://kubernetes-dashboard.apps.pro.aws.bancsabadell.com/#/configmap/pro-ns-storage/ms-storage-ondemand-micros-app-configs?namespace=pro-ns-storage
A3: PRO | B3: ns-ai | C3: AWS | D3: ms-ai-nlp-engine | E3: ms-ai-nlp-engine | F3: ms-ai-nlp-engine-micros-py-configs | G3: p4mspy | H3: artifactory.apps.devops.aws.bancsabadell.com/p4-virtual/ms-ai-nlp-engine:1.0.7 | I3: =FALSE() -> FALSE | J3: ms-ai-nlp-engine-p4mspy | K3: p4mspy-0.0.11 | L3: mariano.carello@quant.global | M3: http://repos.bancsabadell.com/bitbucket/scm/ESSAB_P4_AI/ms-ai-nlp-engine.git | N3: 1.0.7 | O3: 1.0.6 | P3: null | Q3: https://kubernetes-dashboard.apps.pro.aws.bancsabadell.com/#/configmap/pro-ns-ai/ms-ai-nlp-engine-micros-py-configs?namespace=pro-ns-ai
A4: PRO | B4: ns-ai | C4: AWS | D4: ms-ai-audio-transcribe | E4: ms-ai-audio-transcribe | F4: ms-ai-audio-transcribe-micros-app-configs | G4: p4ms | H4: artifactory.apps.devops.aws.bancsabadell.com/p4-virtual/essab_p4_ai/ms-ai-audio-transcribe:4.3.1 | I4: =FALSE() -> FALSE | J4: ms-ai-audio-transcribe-p4ms | K4: p4ms-1.1.8 | L4: cnunez@paradigmadigital.com | M4: http://repos.bancsabadell.com/bitbucket/scm/ESSAB_P4_AI/ms-ai-audio-transcribe.git | N4: 4.3.1 | O4: 4.3.2 | P4: 3.7.0 | Q4: https://kubernetes-dashboard.apps.pro.aws.bancsabadell.com/#/configmap/pro-ns-ai/ms-ai-audio-transcribe-micros-app-configs?namespace=pro-ns-ai
A5: PRO | B5: ns-ai | C5: AWS | D5: ms-ai-derivation | E5: ms-ai-derivation | F5: ms-ai-derivation-micros-py-configs | G5: p4mspy | H5: artifactory.apps.devops.aws.bancsabadell.com/p4-virtual/ms-ai-derivation:1.0.7 | I5: =FALSE() -> FALSE | J5: ms-ai-derivation-p4mspy | K5: p4mspy-0.0.13 | L5: daniel.b.delgado@accenture.com | M5: http://repos.bancsabadell.com/bitbucket/scm/ES/ms-ai-derivation.git | N5: 1.0.7 | O5: 1.0.1 | P5: null | Q5: https://kubernetes-dashboard.apps.pro.aws.bancsabadell.com/#/configmap/pro-ns-ai/ms-ai-derivation-micros-py-configs?namespace=pro-ns-ai
A6: PRO | B6: ns-ai | C6: AWS | D6: ms-ai-subject-1 | E6: ms-ai-subject-1 | F6: ms-ai-subject-1-micros-py-configs | G6: p4mspy | H6: artifactory.apps.devops.aws.bancsabadell.com/p4-virtual/ms-ai-subject-1:1.0.1 | I6: =FALSE() -> FALSE | J6: ms-ai-subject-1-p4mspy | K6: p4mspy-0.0.7 | L6: ignacio.martin@accenture.com | M6: http://repos.bancsabadell.com/bitbucket/scm/ES/ms-ai-subject-1.git | N6: 1.0.1 | O6: 1.0.1 | P6: null | Q6: https://kubernetes-dashboard.apps.pro.aws.bancsabadell.com/#/configmap/pro-ns-ai/ms-ai-subject-1-micros-py-configs?namespace=pro-ns-ai
A7: PRO | B7: ns-ai | C7: AWS | D7: ms-ai-resolution | E7: ms-ai-resolution | F7: ms-ai-resolution-micros-py-configs | G7: p4mspy | H7: artifactory.apps.devops.aws.bancsabadell.com/p4-virtual/ms-ai-resolution:1.0.7 | I7: =FALSE() -> FALSE | J7: ms-ai-resolution-p4mspy | K7: p4mspy-0.0.8 | L7: daniel.b.delgado@accenture.com | M7: http://repos.bancsabadell.com/bitbucket/scm/ES/ms-ai-resolution.git | N7: 1.0.7 | O7: 1.0.1 | P7: null | Q7: https://kubernetes-dashboard.apps.pro.aws.bancsabadell.com/#/configmap/pro-ns-ai/ms-ai-resolution-micros-py-configs?namespace=pro-ns-ai
A8: PRO | B8: ns-ai | C8: AWS | D8: ms-ai-llm-text-engine | E8: ms-ai-llm-text-engine | F8: ms-ai-llm-text-engine-micros-py-configs | G8: p4mspy | H8: artifactory.apps.devops.aws.bancsabadell.com/p4-virtual/ms-ai-llm-text-engine:1.0.7 | I8: =FALSE() -> FALSE | J8: ms-ai-llm-text-engine-p4mspy | K8: p4mspy-0.0.11 | L8: j.e.martin@accenture.com | M8: http://repos.bancsabadell.com/bitbucket/scm/ESSAB_P4_AI/ms-ai-llm-text-engine.git | N8: 1.0.7 | O8: 1.0.6 | P8: null | Q8: https://kubernetes-dashboard.apps.pro.aws.bancsabadell.com/#/configmap/pro-ns-ai/ms-ai-llm-text-engine-micros-py-configs?namespace=pro-ns-ai
A9: PRO | B9: ns-ai | C9: AWS | D9: ms-ai-file-anonymizer | E9: ms-ai-file-anonymizer | F9: ms-ai-file-anonymizer-micros-py-configs | G9: p4mspy | H9: artifactory.apps.devops.aws.bancsabadell.com/p4-virtual/ms-ai-file-anonymizer:2.2.4 | I9: =FALSE() -> FALSE | J9: ms-ai-file-anonymizer-p4mspy | K9: p4mspy-0.0.15 | L9: s482870@adgbs.com | M9: http://repos.bancsabadell.com/bitbucket/scm/VMB/ms-ai-file-anonymizer.git | N9: 2.2.4 | O9: 2.2.4 | P9: null | Q9: https://kubernetes-dashboard.apps.pro.aws.bancsabadell.com/#/configmap/pro-ns-ai/ms-ai-file-anonymizer-micros-py-configs?namespace=pro-ns-ai
A10: PRO | B10: ns-ai | C10: AWS | D10: ms-ai-sentiment | E10: ms-ai-sentiment | F10: ms-ai-sentiment-micros-py-configs | G10: p4mspy | H10: artifactory.apps.devops.aws.bancsabadell.com/p4-virtual/ms-ai-sentiment:1.0.9 | I10: =FALSE() -> FALSE | J10: ms-ai-sentiment-p4mspy | K10: p4mspy-0.0.13 | L10: daniel.b.delgado@accenture.com | M10: http://repos.bancsabadell.com/bitbucket/scm/ES/ms-ai-sentiment.git | N10: 1.0.9 | O10: 1.0.1 | P10: null | Q10: https://kubernetes-dashboard.apps.pro.aws.bancsabadell.com/#/configmap/pro-ns-ai/ms-ai-sentiment-micros-py-configs?namespace=pro-ns-ai
A11: PRO | B11: ns-ai | C11: AWS | D11: ms-ai-conversation-processor | E11: ms-ai-conversation-processor | F11: ms-ai-conversation-processor-micros-py-configs | G11: p4mspy | H11: artifactory.apps.devops.aws.bancsabadell.com/p4-virtual/ms-ai-conversation-processor:2.0.1 | I11: =FALSE() -> FALSE | J11: ms-ai-conversation-processor-p4mspy | K11: p4mspy-0.0.13 | L11: j.e.martin@accenture.com | M11: http://repos.bancsabadell.com/bitbucket/scm/ES/ms-ai-conversation-processor.git | N11: 2.0.1 | O11: 2.0.1 | P11: null | Q11: https://kubernetes-dashboard.apps.pro.aws.bancsabadell.com/#/configmap/pro-ns-ai/ms-ai-conversation-processor-micros-py-configs?namespace=pro-ns-ai
A12: PRO | B12: ns-bff | C12: AWS | D12: ms-domain-selae-redsys | E12: ms-domain-selae-redsys | F12: ms-domain-selae-redsys-micros-app-configs | G12: p4ms | H12: artifactory.apps.devops.aws.bancsabadell.com/p4-virtual/mobi/ms-domain-selae-redsys:0.1.11 | I12: =FALSE() -> FALSE | J12: ms-domain-selae-redsys-p4ms | K12: p4ms-0.9.0 | L12: josep.itarte@gft.com | M12: http://repos.bancsabadell.com/bitbucket/scm/MOBI/ms-domain-selae-redsys.git | N12: 0.1.11 | O12: 0.1.3 | P12: 1.0.0 | Q12: https://kubernetes-dashboard.apps.pro.aws.bancsabadell.com/#/configmap/pro-ns-bff/ms-domain-selae-redsys-micros-app-configs?namespace=pro-ns-bff
A13: PRO | B13: ns-bff | C13: AWS | D13: ms-bff-information-spaces-v1 | E13: ms-bff-information-spaces-v1 | F13: ms-bff-information-spaces-v1-micros-app-configs | G13: p4ms | H13: artifactory.apps.devops.aws.bancsabadell.com/p4-virtual/mobi/ms-bff-information-spaces-v1:1.2.6 | I13: =FALSE() -> FALSE | J13: ms-bff-information-spaces-v1-p4ms | K13: p4ms-1.1.24 | L13: anabel.monserrat@gft.com | M13: http://repos.bancsabadell.com/bitbucket/scm/MOBI/ms-bff-information-spaces-v1.git | N13: 1.2.6 | O13: 1.1.2 | P13: 3.9.5 | Q13: https://kubernetes-dashboard.apps.pro.aws.bancsabadell.com/#/configmap/pro-ns-bff/ms-bff-information-spaces-v1-micros-app-configs?namespace=pro-ns-bff
... A141: PRO | B141: ns-sys | C141: AWS | D141: ms-sys-party-authentication-iam-v1 | E141: ms-sys-party-authentication-iam-v1 | F141: ms-sys-party-authentication-iam-v1-micros-app-configs | G141: p4ms | H141: artifactory.apps.devops.aws.bancsabadell.com/p4-virtual/p4cp/ms-sys-party-authentication-iam-v1:1.0.4 | I141: =FALSE() -> FALSE | J141: ms-sys-party-authentication-iam-v1-p4ms | K141: p4ms-1.1.24 | L141: etika.rastogi@accenture.com | M141: http://repos.bancsabadell.com/bitbucket/scm/p4cp/ms-sys-party-authentication-iam-v1.git | N141: 1.0.4 | O141: 1.0.0 | P141: 3.9.8 | Q141: https://kubernetes-dashboard.apps.pro.aws.bancsabadell.com/#/configmap/pro-ns-sys/ms-sys-party-authentication-iam-v1-micros-app-configs?namespace=pro-ns-sys
A142: PRO | B142: ns-sys | C142: AWS | D142: ms-sys-saml | E142: ms-sys-saml | F142: ms-sys-saml-micros-app-configs | G142: p4ms | H142: artifactory.apps.devops.aws.bancsabadell.com/p4-virtual/p4cp/ms-sys-saml:0.4.2 | I142: =FALSE() -> FALSE | J142: ms-sys-saml-p4ms | K142: p4ms-1.1.6 | L142: raul.castilla@alten.es | M142: http://repos.bancsabadell.com/bitbucket/scm/P4CP/ms-sys-saml.git | N142: 0.4.2 | P142: 1.6.0 | Q142: https://kubernetes-dashboard.apps.pro.aws.bancsabadell.com/#/configmap/pro-ns-sys/ms-sys-saml-micros-app-configs?namespace=pro-ns-sys
A143: PRO | B143: ns-sys | C143: AWS | D143: ms-sys-regulatory-and-legal-authority | E143: ms-sys-regulatory-and-legal-authority | F143: ms-sys-regulatory-and-legal-authority-micros-app-configs | G143: p4ms | H143: artifactory.apps.devops.aws.bancsabadell.com/p4-virtual/poojj/ms-sys-regulatory-and-legal-authority:1.0.13 | I143: =FALSE() -> FALSE | J143: ms-sys-regulatory-and-legal-authority-p4ms | K143: p4ms-1.1.6 | L143: 0901ProjectServiceGFT@bancsabadell.com | M143: http://repos.bancsabadell.com/bitbucket/scm/poojj/ms-sys-regulatory-and-legal-authority.git | N143: 1.0.13 | O143: 1.0.3 | P143: 1.4.1 | Q143: https://kubernetes-dashboard.apps.pro.aws.bancsabadell.com/#/configmap/pro-ns-sys/ms-sys-regulatory-and-legal-authority-micros-app-configs?namespace=pro-ns-sys
A144: PRO | B144: ns-sys | C144: AWS | D144: ms-sys-tasaciones-anonymizer-consumer | E144: ms-sys-tasaciones-anonymizer-consumer | F144: ms-sys-tasaciones-anonymizer-consumer-micros-app-configs | G144: p4ms | H144: artifactory.apps.devops.aws.bancsabadell.com/p4-virtual/p4cp/ms-sys-tasaciones-anonymizer-consumer:1.1.0 | I144: =FALSE() -> FALSE | J144: ms-sys-tasaciones-anonymizer-consumer-p4ms | K144: p4ms-1.1.24 | L144: etika.rastogi@accenture.com | M144: http://repos.bancsabadell.com/bitbucket/scm/P4CP/ms-sys-tasaciones-anonymizer-consumer.git | N144: 1.1.0 | O144: 1.0.7 | P144: 3.9.9 | Q144: https://kubernetes-dashboard.apps.pro.aws.bancsabadell.com/#/configmap/pro-ns-sys/ms-sys-tasaciones-anonymizer-consumer-micros-app-configs?namespace=pro-ns-sys
A145: PRO | B145: ns-sys | C145: AWS | D145: ms-sys-current-account-fp | E145: ms-sys-current-account-fp | F145: ms-sys-current-account-fp-micros-app-configs | G145: p4ms | H145: artifactory.apps.devops.aws.bancsabadell.com/p4-virtual/p4cp/ms-sys-current-account-fp:0.3.4 | I145: =FALSE() -> FALSE | J145: ms-sys-current-account-fp-p4ms | K145: p4ms-1.1.10 | L145: ddcp@gft.com | M145: http://repos.bancsabadell.com/bitbucket/scm/P4CP/ms-sys-current-account-fp.git | N145: 0.3.4 | O145: 1.0.4 | P145: 1.16.3 | Q145: https://kubernetes-dashboard.apps.pro.aws.bancsabadell.com/#/configmap/pro-ns-sys/ms-sys-current-account-fp-micros-app-configs?namespace=pro-ns-sys
A146: PRO | B146: ns-sys | C146: AWS | D146: ms-sys-payment-instruction-ip | E146: ms-sys-payment-instruction-ip | F146: ms-sys-payment-instruction-ip-micros-app-configs | G146: p4ms | H146: artifactory.apps.devops.aws.bancsabadell.com/p4-virtual/p4cp/ms-sys-payment-instruction-ip:2.1.2 | I146: =FALSE() -> FALSE | J146: ms-sys-payment-instruction-ip-p4ms | K146: p4ms-1.1.8 | L146: y.chawla@accenture.com | M146: http://repos.bancsabadell.com/bitbucket/scm/P4CP/ms-sys-payment-instruction-ip.git | N146: 2.1.2 | O146: 0.0.3 | P146: 1.11.0 | Q146: https://kubernetes-dashboard.apps.pro.aws.bancsabadell.com/#/configmap/pro-ns-sys/ms-sys-payment-instruction-ip-micros-app-configs?namespace=pro-ns-sys
A147: PRO | B147: ns-sys | C147: AWS | D147: ms-sys-customer-products-and-services-sp-v1 | E147: ms-sys-customer-products-and-services-sp-v1 | F147: ms-sys-customer-products-and-services-sp-v1-micros-app-configs | G147: p4ms | H147: artifactory.apps.devops.aws.bancsabadell.com/p4-virtual/p4cp/ms-sys-customer-products-and-services-sp-v1:2.0.5 | I147: =FALSE() -> FALSE | J147: ms-sys-customer-products-and-services-sp-v1-p4ms | K147: p4ms-0.15.3 | L147: smorenoe@minsait.com | M147: http://repos.bancsabadell.com/bitbucket/scm/p4cp/ms-sys-customer-products-and-services-sp-v1.git | N147: 2.0.5 | O147: 1.0.2 | P147: 1.7.0 | Q147: https://kubernetes-dashboard.apps.pro.aws.bancsabadell.com/#/configmap/pro-ns-sys/ms-sys-customer-products-and-services-sp-v1-micros-app-configs?namespace=pro-ns-sys
A148: PRO | B148: ns-sys | C148: AWS | D148: ms-sys-cards-dds-v1 | E148: ms-sys-cards-dds-v1 | F148: ms-sys-cards-dds-v1-micros-app-configs | G148: p4ms | H148: artifactory.apps.devops.aws.bancsabadell.com/p4-virtual/mobi/ms-sys-cards-dds-v1:1.1.71 | I148: =FALSE() -> FALSE | J148: ms-sys-cards-dds-v1-p4ms | K148: p4ms-1.1.26 | L148: fjtaboada@minsait.com | M148: http://repos.bancsabadell.com/bitbucket/scm/mobi/ms-sys-cards-dds-v1.git | N148: 1.1.71 | O148: 1.3.19 | P148: 3.9.12 | Q148: https://kubernetes-dashboard.apps.pro.aws.bancsabadell.com/#/configmap/pro-ns-sys/ms-sys-cards-dds-v1-micros-app-configs?namespace=pro-ns-sys
A149: PRO | B149: ns-sys | C149: AWS | D149: ms-sys-party-reference-data-pe-v3 | E149: ms-sys-party-reference-data-pe-v3 | F149: ms-sys-party-reference-data-pe-v3-micros-app-configs | G149: p4ms | H149: artifactory.apps.devops.aws.bancsabadell.com/p4-virtual/mobi/ms-sys-party-reference-data-pe-v3:1.12.4 | I149: =FALSE() -> FALSE | J149: ms-sys-party-reference-data-pe-v3-p4ms | K149: p4ms-1.1.19 | L149: devops@devops.com | M149: http://repos.bancsabadell.com/bitbucket/scm/MOBI/ms-sys-party-reference-data-pe-v3.git | N149: 1.12.4 | O149: 1.10.4 | P149: 1.16.3 | Q149: https://kubernetes-dashboard.apps.pro.aws.bancsabadell.com/#/configmap/pro-ns-sys/ms-sys-party-reference-data-pe-v3-micros-app-configs?namespace=pro-ns-sys
A150: PRO | B150: ns-sys | C150: AWS | D150: ms-sys-factoring-system-fa-v1 | E150: ms-sys-factoring-system-fa-v1 | F150: ms-sys-factoring-system-fa-v1-micros-app-configs | G150: p4ms | H150: artifactory.apps.devops.aws.bancsabadell.com/p4-virtual/p4cp/ms-sys-factoring-system-fa-v1:1.1.0 | I150: =FALSE() -> FALSE | J150: ms-sys-factoring-system-fa-v1-p4ms | K150: p4ms-1.1.10 | L150: aayush.sagar@accenture.com | M150: http://repos.bancsabadell.com/bitbucket/scm/P4cp/ms-sys-factoring-system-fa-v1.git | N150: 1.1.0 | O150: 1.0.6 | P150: 3.7.2 | Q150: https://kubernetes-dashboard.apps.pro.aws.bancsabadell.com/#/configmap/pro-ns-sys/ms-sys-factoring-system-fa-v1-micros-app-configs?namespace=pro-ns-sys
A151: PRO | B151: ns-sys | C151: AWS | D151: ms-sys-adobe-delete-entity | E151: ms-sys-adobe-delete-entity | F151: ms-sys-adobe-delete-entity-micros-app-configs | G151: p4ms | H151: artifactory.apps.devops.aws.bancsabadell.com/p4-virtual/p4cp/ms-sys-adobe-delete-entity:1.0.3 | I151: =FALSE() -> FALSE | J151: ms-sys-adobe-delete-entity-p4ms | K151: p4ms-1.1.19 | L151: Daniel.Gimenez.Verdugo@everis.com | M151: http://repos.bancsabadell.com/bitbucket/scm/p4cp/ms-sys-adobe-delete-entity.git | N151: 1.0.3 | O151: 0.0.1 | P151: 3.9.5 | Q151: https://kubernetes-dashboard.apps.pro.aws.bancsabadell.com/#/configmap/pro-ns-sys/ms-sys-adobe-delete-entity-micros-app-configs?namespace=pro-ns-sys
A152: PRO | B152: ns-sys | C152: AWS | D152: ms-sys-onboarding-process | E152: ms-sys-onboarding-process | F152: ms-sys-onboarding-process-micros-app-configs | G152: p4ms | H152: artifactory.apps.devops.aws.bancsabadell.com/p4-virtual/p4cp/ms-sys-onboarding-process:0.13.0 | I152: =FALSE() -> FALSE | J152: ms-sys-onboarding-process-p4ms | K152: p4ms-0.15.1 | L152: apardoba@everis.com | M152: http://repos.bancsabadell.com/bitbucket/scm/P4CP/ms-sys-onboarding-process.git | N152: 0.13.0 | O152: 0.6.8 | P152: 1.11.0 | Q152: https://kubernetes-dashboard.apps.pro.aws.bancsabadell.com/#/configmap/pro-ns-sys/ms-sys-onboarding-process-micros-app-configs?namespace=pro-ns-sys
A153: PRO | B153: ns-sys | C153: AWS | D153: ms-sys-fraud | E153: ms-sys-fraud | F153: ms-sys-fraud-micros-app-configs | G153: p4ms | H153: artifactory.apps.devops.aws.bancsabadell.com/p4-virtual/p4des/ms-sys-fraud:1.3.1 | I153: =FALSE() -> FALSE | J153: ms-sys-fraud-p4ms | K153: p4ms-1.1.24 | L153: alfredo.miguel.estevez.mendez@nttdata.com | M153: https://bitbucket.apps.devops.aws.bancsabadell.com/scm/P4DES/ms-sys-fraud.git | N153: 1.3.1 | O153: 1.0.14 | P153: 3.9.13 | Q153: https://kubernetes-dashboard.apps.pro.aws.bancsabadell.com/#/configmap/pro-ns-sys/ms-sys-fraud-micros-app-configs?namespace=pro-ns-sys
A154: PRO | B154: ns-sys | C154: AWS | D154: ms-sys-customer-relationship-management-scf | E154: ms-sys-customer-relationship-management-scf | F154: ms-sys-customer-relationship-management-scf-micros-app-configs | G154: p4ms | H154: artifactory.apps.devops.aws.bancsabadell.com/p4-virtual/p4cp/ms-sys-customer-relationship-management-scf:1.0.18 | I154: =FALSE() -> FALSE | J154: ms-sys-customer-relationship-management-scf-p4ms | K154: p4ms-1.1.8 | L154: BancSabadell.JavaFactory@accenture.com | M154: http://repos.bancsabadell.com/bitbucket/scm/p4cp/ms-sys-customer-relationship-management-scf.git | N154: 1.0.18 | O154: 1.0.6 | P154: 1.16.3 | Q154: https://kubernetes-dashboard.apps.pro.aws.bancsabadell.com/#/configmap/pro-ns-sys/ms-sys-customer-relationship-management-scf-micros-app-configs?namespace=pro-ns-sys
... A438: PRO | B438: ns-baas | C438: AWS | D438: ms-baas-ccf-v2 | E438: ms-baas-ccf-v2 | F438: ms-baas-ccf-v2-micros-app-configs | G438: p4ms | H438: artifactory.apps.devops.aws.bancsabadell.com/p4-virtual/p4cp/ms-baas-ccf-v2:1.1.0 | I438: =FALSE() -> FALSE | J438: ms-baas-ccf-v2-p4ms | K438: p4ms-1.1.10 | L438: umesh.kumar.singhal@accenture.com | M438: http://repos.bancsabadell.com/bitbucket/scm/p4cp/ms-baas-ccf-v2.git | N438: 1.1.0 | O438: 1.1.5 | P438: 1.15.0 | Q438: https://kubernetes-dashboard.apps.pro.aws.bancsabadell.com/#/configmap/pro-ns-baas/ms-baas-ccf-v2-micros-app-configs?namespace=pro-ns-baas

Sheet Cruce
A1: Micros | B1: deployed in PRO | C1: version config | D1: repo micro | E1: repo config | F1: branch
A2: ms-baas-consumer-loan-v1 | B2: =ISNUMBER(MATCH(A2,Inventario!D:D, 0)) -> TRUE | C2: =IFERROR(INDEX(Inventario!O:O, MATCH(A2,Inventario!D:D, 0)), "") -> 1.3.3 | D2: =IFERROR(INDEX(Inventario!M:M, MATCH(A2, Inventario!D:D, 0)), "") -> http://repos.bancsabadell.com/bitbucket/scm/P4CP/ms-baas-consumer-loan-v1.git | E2: =SUBSTITUTE(D2, ".git", "-conf/browse") -> http://repos.bancsabadell.com/bitbucket/scm/P4CP/ms-baas-consumer-loan-v1-conf/browse | F2: =CONCATENATE("release/",C2) -> release/1.3.3
A3: ms-batch-sinfonia-processor | B3: =ISNUMBER(MATCH(A3,Inventario!D:D, 0)) -> 1 | C3: =IFERROR(INDEX(Inventario!O:O, MATCH(A3,Inventario!D:D, 0)), "") -> 1.0.7 | D3: =IFERROR(INDEX(Inventario!M:M, MATCH(A3, Inventario!D:D, 0)), "") -> http://repos.bancsabadell.com/bitbucket/scm/p4cp/ms-batch-sinfonia-processor.git | E3: =SUBSTITUTE(D3, ".git", "-conf/browse") -> http://repos.bancsabadell.com/bitbucket/scm/p4cp/ms-batch-sinfonia-processor-conf/browse | F3: =CONCATENATE("release/",C3) -> release/1.0.7
A4: ms-baas-mortgage-loan-v1 | B4: =ISNUMBER(MATCH(A4,Inventario!D:D, 0)) -> 1 | C4: =IFERROR(INDEX(Inventario!O:O, MATCH(A4,Inventario!D:D, 0)), "") -> 1.1.4 | D4: =IFERROR(INDEX(Inventario!M:M, MATCH(A4, Inventario!D:D, 0)), "") -> http://repos.bancsabadell.com/bitbucket/scm/P4CP/ms-baas-mortgage-loan-v1.git | E4: =SUBSTITUTE(D4, ".git", "-conf/browse") -> http://repos.bancsabadell.com/bitbucket/scm/P4CP/ms-baas-mortgage-loan-v1-conf/browse | F4: =CONCATENATE("release/",C4) -> release/1.1.4
A5: ms-baas-special-pricing-conditions | B5: =ISNUMBER(MATCH(A5,Inventario!D:D, 0)) -> 1 | C5: =IFERROR(INDEX(Inventario!O:O, MATCH(A5,Inventario!D:D, 0)), "") -> 0.8.19 | D5: =IFERROR(INDEX(Inventario!M:M, MATCH(A5, Inventario!D:D, 0)), "") -> http://repos.bancsabadell.com/bitbucket/scm/JUST_RAROC/ms-baas-special-pricing-conditions.git | E5: =SUBSTITUTE(D5, ".git", "-conf/browse") -> http://repos.bancsabadell.com/bitbucket/scm/JUST_RAROC/ms-baas-special-pricing-conditions-conf/browse | F5: =CONCATENATE("release/",C5) -> release/0.8.19
A6: ms-baas-credit-facility-online-pr | B6: =ISNUMBER(MATCH(A6,Inventario!D:D, 0)) -> 1 | C6: =IFERROR(INDEX(Inventario!O:O, MATCH(A6,Inventario!D:D, 0)), "") -> 1.0.6 | D6: =IFERROR(INDEX(Inventario!M:M, MATCH(A6, Inventario!D:D, 0)), "") -> http://repos.bancsabadell.com/bitbucket/scm/P4CP/ms-baas-credit-facility-online-pr.git | E6: =SUBSTITUTE(D6, ".git", "-conf/browse") -> http://repos.bancsabadell.com/bitbucket/scm/P4CP/ms-baas-credit-facility-online-pr-conf/browse | F6: =CONCATENATE("release/",C6) -> release/1.0.6
A7: ms-sys-credit-facility-online-pr | B7: =ISNUMBER(MATCH(A7,Inventario!D:D, 0)) -> 1 | C7: =IFERROR(INDEX(Inventario!O:O, MATCH(A7,Inventario!D:D, 0)), "") -> 1.0.2 | D7: =IFERROR(INDEX(Inventario!M:M, MATCH(A7, Inventario!D:D, 0)), "") -> http://repos.bancsabadell.com/bitbucket/scm/P4CP/ms-sys-credit-facility-online-pr.git | E7: =SUBSTITUTE(D7, ".git", "-conf/browse") -> http://repos.bancsabadell.com/bitbucket/scm/P4CP/ms-sys-credit-facility-online-pr-conf/browse | F7: =CONCATENATE("release/",C7) -> release/1.0.2
A8: ms-baas-scf-packaging | B8: =ISNUMBER(MATCH(A8,Inventario!D:D, 0)) -> 1 | C8: =IFERROR(INDEX(Inventario!O:O, MATCH(A8,Inventario!D:D, 0)), "") -> 1.0.6 | D8: =IFERROR(INDEX(Inventario!M:M, MATCH(A8, Inventario!D:D, 0)), "") -> http://repos.bancsabadell.com/bitbucket/scm/p4cp/ms-baas-scf-packaging.git | E8: =SUBSTITUTE(D8, ".git", "-conf/browse") -> http://repos.bancsabadell.com/bitbucket/scm/p4cp/ms-baas-scf-packaging-conf/browse | F8: =CONCATENATE("release/",C8) -> release/1.0.6
A9: ms-sys-card-terminal-operation-ps | B9: =ISNUMBER(MATCH(A9,Inventario!D:D, 0)) -> 1 | C9: =IFERROR(INDEX(Inventario!O:O, MATCH(A9,Inventario!D:D, 0)), "") -> 1.0.2 | D9: =IFERROR(INDEX(Inventario!M:M, MATCH(A9, Inventario!D:D, 0)), "") -> http://repos.bancsabadell.com/bitbucket/scm/P4CP/ms-sys-card-terminal-operation-ps.git | E9: =SUBSTITUTE(D9, ".git", "-conf/browse") -> http://repos.bancsabadell.com/bitbucket/scm/P4CP/ms-sys-card-terminal-operation-ps-conf/browse | F9: =CONCATENATE("release/",C9) -> release/1.0.2
A10: ms-sys-customer-campaign-execution-system-kx | B10: =ISNUMBER(MATCH(A10,Inventario!D:D, 0)) -> 1 | C10: =IFERROR(INDEX(Inventario!O:O, MATCH(A10,Inventario!D:D, 0)), "") -> 1.0.2 | D10: =IFERROR(INDEX(Inventario!M:M, MATCH(A10, Inventario!D:D, 0)), "") -> http://repos.bancsabadell.com/bitbucket/scm/P4CP/ms-sys-customer-campaign-execution-system-kx.git | E10: =SUBSTITUTE(D10, ".git", "-conf/browse") -> http://repos.bancsabadell.com/bitbucket/scm/P4CP/ms-sys-customer-campaign-execution-system-kx-conf/browse | F10: =CONCATENATE("release/",C10) -> release/1.0.2
A11: ms-baas-factoring-v1 | B11: =ISNUMBER(MATCH(A11,Inventario!D:D, 0)) -> 1 | C11: =IFERROR(INDEX(Inventario!O:O, MATCH(A11,Inventario!D:D, 0)), "") -> 1.0.6 | D11: =IFERROR(INDEX(Inventario!M:M, MATCH(A11, Inventario!D:D, 0)), "") -> http://repos.bancsabadell.com/bitbucket/scm/P4cp/ms-baas-factoring-v1.git | E11: =SUBSTITUTE(D11, ".git", "-conf/browse") -> http://repos.bancsabadell.com/bitbucket/scm/P4cp/ms-baas-factoring-v1-conf/browse | F11: =CONCATENATE("release/",C11) -> release/1.0.6
A12: ms-sys-factoring-system-fa-v1 | B12: =ISNUMBER(MATCH(A12,Inventario!D:D, 0)) -> 1 | C12: =IFERROR(INDEX(Inventario!O:O, MATCH(A12,Inventario!D:D, 0)), "") -> 1.0.6 | D12: =IFERROR(INDEX(Inventario!M:M, MATCH(A12, Inventario!D:D, 0)), "") -> http://repos.bancsabadell.com/bitbucket/scm/P4cp/ms-sys-factoring-system-fa-v1.git | E12: =SUBSTITUTE(D12, ".git", "-conf/browse") -> http://repos.bancsabadell.com/bitbucket/scm/P4cp/ms-sys-factoring-system-fa-v1-conf/browse | F12: =CONCATENATE("release/",C12) -> release/1.0.6
A13: ms-baas-confirming-v1 | B13: =ISNUMBER(MATCH(A13,Inventario!D:D, 0)) -> 1 | C13: =IFERROR(INDEX(Inventario!O:O, MATCH(A13,Inventario!D:D, 0)), "") -> 1.0.4 | D13: =IFERROR(INDEX(Inventario!M:M, MATCH(A13, Inventario!D:D, 0)), "") -> http://repos.bancsabadell.com/bitbucket/scm/P4CP/ms-baas-confirming-v1.git | E13: =SUBSTITUTE(D13, ".git", "-conf/browse") -> http://repos.bancsabadell.com/bitbucket/scm/P4CP/ms-baas-confirming-v1-conf/browse | F13: =CONCATENATE("release/",C13) -> release/1.0.4
... A35: ms-baas-position-keeping-extended-v1 | B35: =ISNUMBER(MATCH(A35,Inventario!D:D, 0)) -> 1 | C35: =IFERROR(INDEX(Inventario!O:O, MATCH(A35,Inventario!D:D, 0)), "") -> 2.0.0 | D35: =IFERROR(INDEX(Inventario!M:M, MATCH(A35, Inventario!D:D, 0)), "") -> http://repos.bancsabadell.com/bitbucket/scm/MOBI/ms-baas-position-keeping-extended-v1.git | E35: =SUBSTITUTE(D35, ".git", "-conf/browse") -> http://repos.bancsabadell.com/bitbucket/scm/MOBI/ms-baas-position-keeping-extended-v1-conf/browse | F35: =CONCATENATE("release/",C35) -> release/2.0.0
A36: ms-baas-product-matching-baas-v1 | B36: =ISNUMBER(MATCH(A36,Inventario!D:D, 0)) -> 0 | C36: =IFERROR(INDEX(Inventario!O:O, MATCH(A36,Inventario!D:D, 0)), "") | D36: =IFERROR(INDEX(Inventario!M:M, MATCH(A36, Inventario!D:D, 0)), "") | E36: =SUBSTITUTE(D36, ".git", "-conf")
A37: ms-sys-notifications | B37: =ISNUMBER(MATCH(A37,Inventario!D:D, 0)) -> 1 | C37: =IFERROR(INDEX(Inventario!O:O, MATCH(A37,Inventario!D:D, 0)), "") -> 1.5.5 | D37: =IFERROR(INDEX(Inventario!M:M, MATCH(A37, Inventario!D:D, 0)), "") -> https://bitbucket.apps.devops.aws.bancsabadell.com/scm/p4des/ms-sys-notifications.git | E37: =SUBSTITUTE(D37, ".git", "-conf/browse") -> https://bitbucket.apps.devops.aws.bancsabadell.com/scm/p4des/ms-sys-notifications-conf/browse | F37: =CONCATENATE("release/",C37) -> release/1.5.5
A38: ms-sys-notifications-hub-email-sender | B38: =ISNUMBER(MATCH(A38,Inventario!D:D, 0)) -> 1 | C38: =IFERROR(INDEX(Inventario!O:O, MATCH(A38,Inventario!D:D, 0)), "") -> 1.0.2 | D38: =IFERROR(INDEX(Inventario!M:M, MATCH(A38, Inventario!D:D, 0)), "") -> https://bitbucket.apps.devops.aws.bancsabadell.com/scm/p4des/ms-sys-notifications-hub-email-sender.git | E38: =SUBSTITUTE(D38, ".git", "-conf/browse") -> https://bitbucket.apps.devops.aws.bancsabadell.com/scm/p4des/ms-sys-notifications-hub-email-sender-conf/browse | F38: =CONCATENATE("release/",C38) -> release/1.0.2
A39: ms-baas-correspondence-v2 | B39: =ISNUMBER(MATCH(A39,Inventario!D:D, 0)) -> 1 | C39: =IFERROR(INDEX(Inventario!O:O, MATCH(A39,Inventario!D:D, 0)), "") -> 1.0.6 | D39: =IFERROR(INDEX(Inventario!M:M, MATCH(A39, Inventario!D:D, 0)), "") -> http://repos.bancsabadell.com/bitbucket/scm/p4cp/ms-baas-correspondence-v2.git | E39: =SUBSTITUTE(D39, ".git", "-conf/browse") -> http://repos.bancsabadell.com/bitbucket/scm/p4cp/ms-baas-correspondence-v2-conf/browse | F39: =CONCATENATE("release/",C39) -> release/1.0.6
A40: ms-sys-correspondence-ia | B40: =ISNUMBER(MATCH(A40,Inventario!D:D, 0)) -> 1 | C40: =IFERROR(INDEX(Inventario!O:O, MATCH(A40,Inventario!D:D, 0)), "") -> 1.0.9 | D40: =IFERROR(INDEX(Inventario!M:M, MATCH(A40, Inventario!D:D, 0)), "") -> http://repos.bancsabadell.com/bitbucket/scm/p4cp/ms-sys-correspondence-ia.git | E40: =SUBSTITUTE(D40, ".git", "-conf/browse") -> http://repos.bancsabadell.com/bitbucket/scm/p4cp/ms-sys-correspondence-ia-conf/browse | F40: =CONCATENATE("release/",C40) -> release/1.0.9
A41: ms-baas-correspondence-v3 | B41: =ISNUMBER(MATCH(A41,Inventario!D:D, 0)) -> 1 | C41: =IFERROR(INDEX(Inventario!O:O, MATCH(A41,Inventario!D:D, 0)), "") -> 1.0.7 | D41: =IFERROR(INDEX(Inventario!M:M, MATCH(A41, Inventario!D:D, 0)), "") -> http://repos.bancsabadell.com/bitbucket/scm/p4cp/ms-baas-correspondence-v3.git | E41: =SUBSTITUTE(D41, ".git", "-conf/browse") -> http://repos.bancsabadell.com/bitbucket/scm/p4cp/ms-baas-correspondence-v3-conf/browse | F41: =CONCATENATE("release/",C41) -> release/1.0.7
A42: ms-sys-correspondence-ia-v2 | B42: =ISNUMBER(MATCH(A42,Inventario!D:D, 0)) -> 1 | C42: =IFERROR(INDEX(Inventario!O:O, MATCH(A42,Inventario!D:D, 0)), "") -> 1.0.6 | D42: =IFERROR(INDEX(Inventario!M:M, MATCH(A42, Inventario!D:D, 0)), "") -> http://repos.bancsabadell.com/bitbucket/scm/P4CP/ms-sys-correspondence-ia-v2.git | E42: =SUBSTITUTE(D42, ".git", "-conf/browse") -> http://repos.bancsabadell.com/bitbucket/scm/P4CP/ms-sys-correspondence-ia-v2-conf/browse | F42: =CONCATENATE("release/",C42) -> release/1.0.6
A43: ms-baas-servicing-order-v1 | B43: =ISNUMBER(MATCH(A43,Inventario!D:D, 0)) -> 1 | C43: =IFERROR(INDEX(Inventario!O:O, MATCH(A43,Inventario!D:D, 0)), "") -> 0.1.6 | D43: =IFERROR(INDEX(Inventario!M:M, MATCH(A43, Inventario!D:D, 0)), "") -> http://repos.bancsabadell.com/bitbucket/scm/p4cp/ms-baas-servicing-order-v1.git | E43: =SUBSTITUTE(D43, ".git", "-conf/browse") -> http://repos.bancsabadell.com/bitbucket/scm/p4cp/ms-baas-servicing-order-v1-conf/browse | F43: =CONCATENATE("release/",C43) -> release/0.1.6
A44: ms-sys-servicing-order-gt-v1 | B44: =ISNUMBER(MATCH(A44,Inventario!D:D, 0)) -> 1 | C44: =IFERROR(INDEX(Inventario!O:O, MATCH(A44,Inventario!D:D, 0)), "") -> 0.1.6 | D44: =IFERROR(INDEX(Inventario!M:M, MATCH(A44, Inventario!D:D, 0)), "") -> http://repos.bancsabadell.com/bitbucket/scm/p4cp/ms-sys-servicing-order-gt-v1.git | E44: =SUBSTITUTE(D44, ".git", "-conf/browse") -> http://repos.bancsabadell.com/bitbucket/scm/p4cp/ms-sys-servicing-order-gt-v1-conf/browse | F44: =CONCATENATE("release/",C44) -> release/0.1.6
A45: ms-baas-desktop-notifications | B45: =ISNUMBER(MATCH(A45,Inventario!D:D, 0)) -> 1 | C45: =IFERROR(INDEX(Inventario!O:O, MATCH(A45,Inventario!D:D, 0)), "") -> 1.0.8 | D45: =IFERROR(INDEX(Inventario!M:M, MATCH(A45, Inventario!D:D, 0)), "") -> http://repos.bancsabadell.com/bitbucket/scm/p4notifications/ms-baas-desktop-notifications.git | E45: =SUBSTITUTE(D45, ".git", "-conf/browse") -> http://repos.bancsabadell.com/bitbucket/scm/p4notifications/ms-baas-desktop-notifications-conf/browse | F45: =CONCATENATE("release/",C45) -> release/1.0.8
A46: ms-sys-party-routing-profile-aa | B46: =ISNUMBER(MATCH(A46,Inventario!D:D, 0)) -> 1 | C46: =IFERROR(INDEX(Inventario!O:O, MATCH(A46,Inventario!D:D, 0)), "") -> 0.3.3 | D46: =IFERROR(INDEX(Inventario!M:M, MATCH(A46, Inventario!D:D, 0)), "") -> http://repos.bancsabadell.com/bitbucket/scm/MOBI/ms-sys-party-routing-profile-aa.git | E46: =SUBSTITUTE(D46, ".git", "-conf/browse") -> http://repos.bancsabadell.com/bitbucket/scm/MOBI/ms-sys-party-routing-profile-aa-conf/browse | F46: =CONCATENATE("release/",C46) -> release/0.3.3
A47: ms-bff-tjmovilpinrecovery | B47: =ISNUMBER(MATCH(A47,Inventario!D:D, 0)) -> 1 | C47: =IFERROR(INDEX(Inventario!O:O, MATCH(A47,Inventario!D:D, 0)), "") -> 0.1.6 | D47: =IFERROR(INDEX(Inventario!M:M, MATCH(A47, Inventario!D:D, 0)), "") -> http://repos.bancsabadell.com/bitbucket/scm/P4CP/ms-bff-tjmovilpinrecovery.git | E47: =SUBSTITUTE(D47, ".git", "-conf/browse") -> http://repos.bancsabadell.com/bitbucket/scm/P4CP/ms-bff-tjmovilpinrecovery-conf/browse | F47: =CONCATENATE("release/",C47) -> release/0.1.6
A48: ms-bff-party-reference-data-directory-v2 | B48: =ISNUMBER(MATCH(A48,Inventario!D:D, 0)) -> 1 | C48: =IFERROR(INDEX(Inventario!O:O, MATCH(A48,Inventario!D:D, 0)), "") -> 1.1.2 | D48: =IFERROR(INDEX(Inventario!M:M, MATCH(A48, Inventario!D:D, 0)), "") -> http://repos.bancsabadell.com/bitbucket/scm/MOBI/ms-bff-party-reference-data-directory-v2.git | E48: =SUBSTITUTE(D48, ".git", "-conf/browse") -> http://repos.bancsabadell.com/bitbucket/scm/MOBI/ms-bff-party-reference-data-directory-v2-conf/browse | F48: =CONCATENATE("release/",C48) -> release/1.1.2
... A106: ms-sys-customer-offer-pz | B106: =ISNUMBER(MATCH(A106,Inventario!D:D, 0)) -> 1 | C106: =IFERROR(INDEX(Inventario!O:O, MATCH(A106,Inventario!D:D, 0)), "") -> 1.0.1 | D106: =IFERROR(INDEX(Inventario!M:M, MATCH(A106, Inventario!D:D, 0)), "") -> http://repos.bancsabadell.com/bitbucket/scm/POOJJ/ms-sys-customer-offer-pz.git | E106: =SUBSTITUTE(D106, ".git", "-conf/browse") -> http://repos.bancsabadell.com/bitbucket/scm/POOJJ/ms-sys-customer-offer-pz-conf/browse | F106: =CONCATENATE("release/",C106) -> release/1.0.1
A107: ms-sys-informa-docu-pe | B107: =ISNUMBER(MATCH(A107,Inventario!D:D, 0)) -> 0 | C107: =IFERROR(INDEX(Inventario!O:O, MATCH(A107,Inventario!D:D, 0)), "") | D107: =IFERROR(INDEX(Inventario!M:M, MATCH(A107, Inventario!D:D, 0)), "") | E107: =SUBSTITUTE(D107, ".git", "-conf")
A108: ms-sys-legal-entity-directory-ee-v1 | B108: =ISNUMBER(MATCH(A108,Inventario!D:D, 0)) -> 1 | C108: =IFERROR(INDEX(Inventario!O:O, MATCH(A108,Inventario!D:D, 0)), "") -> 0.0.2 | D108: =IFERROR(INDEX(Inventario!M:M, MATCH(A108, Inventario!D:D, 0)), "") -> http://repos.bancsabadell.com/bitbucket/scm/P4CP/ms-sys-legal-entity-directory-ee-v1.git | E108: =SUBSTITUTE(D108, ".git", "-conf/browse") -> http://repos.bancsabadell.com/bitbucket/scm/P4CP/ms-sys-legal-entity-directory-ee-v1-conf/browse | F108: =CONCATENATE("release/",C108) -> release/0.0.2
A109: ms-sys-legal-entity-directory-pe-v1 | B109: =ISNUMBER(MATCH(A109,Inventario!D:D, 0)) -> 1 | C109: =IFERROR(INDEX(Inventario!O:O, MATCH(A109,Inventario!D:D, 0)), "") -> 1.0.2 | D109: =IFERROR(INDEX(Inventario!M:M, MATCH(A109, Inventario!D:D, 0)), "") -> http://repos.bancsabadell.com/bitbucket/scm/P4CP/ms-sys-legal-entity-directory-pe-v1.git | E109: =SUBSTITUTE(D109, ".git", "-conf/browse") -> http://repos.bancsabadell.com/bitbucket/scm/P4CP/ms-sys-legal-entity-directory-pe-v1-conf/browse | F109: =CONCATENATE("release/",C109) -> release/1.0.2
A110: ms-sys-party-reference-data-pe | B110: =ISNUMBER(MATCH(A110,Inventario!D:D, 0)) -> 1 | C110: =IFERROR(INDEX(Inventario!O:O, MATCH(A110,Inventario!D:D, 0)), "") -> 1.6.2 | D110: =IFERROR(INDEX(Inventario!M:M, MATCH(A110, Inventario!D:D, 0)), "") -> http://repos.bancsabadell.com/bitbucket/scm/P4CP/ms-sys-party-reference-data-pe.git | E110: =SUBSTITUTE(D110, ".git", "-conf/browse") -> http://repos.bancsabadell.com/bitbucket/scm/P4CP/ms-sys-party-reference-data-pe-conf/browse | F110: =CONCATENATE("release/",C110) -> release/1.6.2
A111: ms-sys-party-reference-data-pe-v2 | B111: =ISNUMBER(MATCH(A111,Inventario!D:D, 0)) -> 1 | C111: =IFERROR(INDEX(Inventario!O:O, MATCH(A111,Inventario!D:D, 0)), "") -> 1.0.6 | D111: =IFERROR(INDEX(Inventario!M:M, MATCH(A111, Inventario!D:D, 0)), "") -> http://repos.bancsabadell.com/bitbucket/scm/P4CP/ms-sys-party-reference-data-pe-v2.git | E111: =SUBSTITUTE(D111, ".git", "-conf/browse") -> http://repos.bancsabadell.com/bitbucket/scm/P4CP/ms-sys-party-reference-data-pe-v2-conf/browse | F111: =CONCATENATE("release/",C111) -> release/1.0.6
A112: ms-sys-party-reference-data-pe-v3 | B112: =ISNUMBER(MATCH(A112,Inventario!D:D, 0)) -> 1 | C112: =IFERROR(INDEX(Inventario!O:O, MATCH(A112,Inventario!D:D, 0)), "") -> 1.10.4 | D112: =IFERROR(INDEX(Inventario!M:M, MATCH(A112, Inventario!D:D, 0)), "") -> http://repos.bancsabadell.com/bitbucket/scm/MOBI/ms-sys-party-reference-data-pe-v3.git | E112: =SUBSTITUTE(D112, ".git", "-conf/browse") -> http://repos.bancsabadell.com/bitbucket/scm/MOBI/ms-sys-party-reference-data-pe-v3-conf/browse | F112: =CONCATENATE("release/",C112) -> release/1.10.4
A113: ms-sys-pe-connected-client | B113: =ISNUMBER(MATCH(A113,Inventario!D:D, 0)) -> 1 | C113: =IFERROR(INDEX(Inventario!O:O, MATCH(A113,Inventario!D:D, 0)), "") -> 1.0.0 | D113: =IFERROR(INDEX(Inventario!M:M, MATCH(A113, Inventario!D:D, 0)), "") -> http://repos.bancsabadell.com/bitbucket/scm/ESSABCONNECTEDCLIENT/ms-sys-pe-connected-client.git | E113: =SUBSTITUTE(D113, ".git", "-conf/browse") -> http://repos.bancsabadell.com/bitbucket/scm/ESSABCONNECTEDCLIENT/ms-sys-pe-connected-client-conf/browse | F113: =CONCATENATE("release/",C113) -> release/1.0.0
A114: ms-sys-product-directory-kc | B114: =ISNUMBER(MATCH(A114,Inventario!D:D, 0)) -> 1 | C114: =IFERROR(INDEX(Inventario!O:O, MATCH(A114,Inventario!D:D, 0)), "") -> 1.0.1 | D114: =IFERROR(INDEX(Inventario!M:M, MATCH(A114, Inventario!D:D, 0)), "") -> http://repos.bancsabadell.com/bitbucket/scm/POOJJ/ms-sys-product-directory-kc.git | E114: =SUBSTITUTE(D114, ".git", "-conf/browse") -> http://repos.bancsabadell.com/bitbucket/scm/POOJJ/ms-sys-product-directory-kc-conf/browse | F114: =CONCATENATE("release/",C114) -> release/1.0.1
A115: ms-sys-public-reference-data-management-dv | B115: =ISNUMBER(MATCH(A115,Inventario!D:D, 0)) -> 1 | C115: =IFERROR(INDEX(Inventario!O:O, MATCH(A115,Inventario!D:D, 0)), "") -> 1.0.5 | D115: =IFERROR(INDEX(Inventario!M:M, MATCH(A115, Inventario!D:D, 0)), "") -> http://repos.bancsabadell.com/bitbucket/scm/P4CP/ms-sys-public-reference-data-management-dv.git | E115: =SUBSTITUTE(D115, ".git", "-conf/browse") -> http://repos.bancsabadell.com/bitbucket/scm/P4CP/ms-sys-public-reference-data-management-dv-conf/browse | F115: =CONCATENATE("release/",C115) -> release/1.0.5
A116: ms-baas-legal-entity-directory-pe-v1 | B116: =ISNUMBER(MATCH(A116,Inventario!D:D, 0)) -> 1 | C116: =IFERROR(INDEX(Inventario!O:O, MATCH(A116,Inventario!D:D, 0)), "") -> 0.1.3 | D116: =IFERROR(INDEX(Inventario!M:M, MATCH(A116, Inventario!D:D, 0)), "") -> http://repos.bancsabadell.com/bitbucket/scm/mobi/ms-baas-legal-entity-directory-pe-v1.git | E116: =SUBSTITUTE(D116, ".git", "-conf/browse") -> http://repos.bancsabadell.com/bitbucket/scm/mobi/ms-baas-legal-entity-directory-pe-v1-conf/browse | F116: =CONCATENATE("release/",C116) -> release/0.1.3
A117: ms-batch-connected-client | B117: =ISNUMBER(MATCH(A117,Inventario!D:D, 0)) -> 1 | C117: =IFERROR(INDEX(Inventario!O:O, MATCH(A117,Inventario!D:D, 0)), "") -> 1.0.3 | D117: =IFERROR(INDEX(Inventario!M:M, MATCH(A117, Inventario!D:D, 0)), "") -> http://repos.bancsabadell.com/bitbucket/scm/ESSABCONNECTEDCLIENT/ms-batch-connected-client.git | E117: =SUBSTITUTE(D117, ".git", "-conf/browse") -> http://repos.bancsabadell.com/bitbucket/scm/ESSABCONNECTEDCLIENT/ms-batch-connected-client-conf/browse | F117: =CONCATENATE("release/",C117) -> release/1.0.3
A118: ms-batch-informa-docu-pe | B118: =ISNUMBER(MATCH(A118,Inventario!D:D, 0)) -> 1 | C118: =IFERROR(INDEX(Inventario!O:O, MATCH(A118,Inventario!D:D, 0)), "") -> 2.0.4 | D118: =IFERROR(INDEX(Inventario!M:M, MATCH(A118, Inventario!D:D, 0)), "") -> http://repos.bancsabadell.com/bitbucket/scm/INFO/ms-batch-informa-docu-pe.git | E118: =SUBSTITUTE(D118, ".git", "-conf/browse") -> http://repos.bancsabadell.com/bitbucket/scm/INFO/ms-batch-informa-docu-pe-conf/browse | F118: =CONCATENATE("release/",C118) -> release/2.0.4
A119: ms-baas-pccm | B119: =ISNUMBER(MATCH(A119,Inventario!D:D, 0)) -> 1 | C119: =IFERROR(INDEX(Inventario!O:O, MATCH(A119,Inventario!D:D, 0)), "") -> 1.0.4 | D119: =IFERROR(INDEX(Inventario!M:M, MATCH(A119, Inventario!D:D, 0)), "") -> http://repos.bancsabadell.com/bitbucket/scm/PCCM/ms-baas-pccm.git | E119: =SUBSTITUTE(D119, ".git", "-conf/browse") -> http://repos.bancsabadell.com/bitbucket/scm/PCCM/ms-baas-pccm-conf/browse | F119: =CONCATENATE("release/",C119) -> release/1.0.4
... A163: ms-sys-fraud-diagnosis-system-ih-v1 | B163: =ISNUMBER(MATCH(A163,Inventario!D:D, 0)) -> 1 | C163: =IFERROR(INDEX(Inventario!O:O, MATCH(A163,Inventario!D:D, 0)), "") -> 1.0.6 | D163: =IFERROR(INDEX(Inventario!M:M, MATCH(A163, Inventario!D:D, 0)), "") -> http://repos.bancsabadell.com/bitbucket/scm/P4CP/ms-sys-fraud-diagnosis-system-ih-v1.git | E163: =SUBSTITUTE(D163, ".git", "-conf/browse") -> http://repos.bancsabadell.com/bitbucket/scm/P4CP/ms-sys-fraud-diagnosis-system-ih-v1-conf/browse | F163: =CONCATENATE("release/",C163) -> release/1.0.6
A164: ms-sys-fraud-notification-redsys | B164: =ISNUMBER(MATCH(A164,Inventario!D:D, 0)) -> 0 | C164: =IFERROR(INDEX(Inventario!O:O, MATCH(A164,Inventario!D:D, 0)), "") | D164: =IFERROR(INDEX(Inventario!M:M, MATCH(A164, Inventario!D:D, 0)), "") | E164: =SUBSTITUTE(D164, ".git", "-conf")
A165: ms-baas-c2c-validation | B165: =ISNUMBER(MATCH(A165,Inventario!D:D, 0)) -> 1 | C165: =IFERROR(INDEX(Inventario!O:O, MATCH(A165,Inventario!D:D, 0)), "") -> 0.0.6 | D165: =IFERROR(INDEX(Inventario!M:M, MATCH(A165, Inventario!D:D, 0)), "") -> http://repos.bancsabadell.com/bitbucket/scm/ESTC/ms-baas-c2c-validation.git | E165: =SUBSTITUTE(D165, ".git", "-conf/browse") -> http://repos.bancsabadell.com/bitbucket/scm/ESTC/ms-baas-c2c-validation-conf/browse | F165: =CONCATENATE("release/",C165) -> release/0.0.6
A166: ms-baas-consumo-datos | B166: =ISNUMBER(MATCH(A166,Inventario!D:D, 0)) -> 1 | C166: =IFERROR(INDEX(Inventario!O:O, MATCH(A166,Inventario!D:D, 0)), "") -> 1.0.9 | D166: =IFERROR(INDEX(Inventario!M:M, MATCH(A166, Inventario!D:D, 0)), "") -> http://repos.bancsabadell.com/bitbucket/scm/ESACCESODATO/ms-baas-consumo-datos.git | E166: =SUBSTITUTE(D166, ".git", "-conf/browse") -> http://repos.bancsabadell.com/bitbucket/scm/ESACCESODATO/ms-baas-consumo-datos-conf/browse | F166: =CONCATENATE("release/",C166) -> release/1.0.9
A167: ms-sys-callcenter-data-download | B167: =ISNUMBER(MATCH(A167,Inventario!D:D, 0)) -> 0 | C167: =IFERROR(INDEX(Inventario!O:O, MATCH(A167,Inventario!D:D, 0)), "") | D167: =IFERROR(INDEX(Inventario!M:M, MATCH(A167, Inventario!D:D, 0)), "") | E167: =SUBSTITUTE(D167, ".git", "-conf")
A168: ms-sys-interactive-help-zendesk-v1 | B168: =ISNUMBER(MATCH(A168,Inventario!D:D, 0)) -> 1 | C168: =IFERROR(INDEX(Inventario!O:O, MATCH(A168,Inventario!D:D, 0)), "") -> 1.0.20 | D168: =IFERROR(INDEX(Inventario!M:M, MATCH(A168, Inventario!D:D, 0)), "") -> http://repos.bancsabadell.com/bitbucket/scm/MOBI/ms-sys-interactive-help-zendesk-v1.git | E168: =SUBSTITUTE(D168, ".git", "-conf/browse") -> http://repos.bancsabadell.com/bitbucket/scm/MOBI/ms-sys-interactive-help-zendesk-v1-conf/browse | F168: =CONCATENATE("release/",C168) -> release/1.0.20
E169: =SUBSTITUTE(D169, ".git", "-conf")
E170: =SUBSTITUTE(D170, ".git", "-conf")
E171: =SUBSTITUTE(D171, ".git", "-conf")
E172: =SUBSTITUTE(D172, ".git", "-conf")
E173: =SUBSTITUTE(D173, ".git", "-conf")
E174: =SUBSTITUTE(D174, ".git", "-conf")
E175: =SUBSTITUTE(D175, ".git", "-conf")
E176: =SUBSTITUTE(D176, ".git", "-conf")
E177: =SUBSTITUTE(D177, ".git", "-conf")
E178: =SUBSTITUTE(D178, ".git", "-conf")
E179: =SUBSTITUTE(D179, ".git", "-conf")
E180: =SUBSTITUTE(D180, ".git", "-conf")
... E242: =SUBSTITUTE(D242, ".git", "-conf")

Sheet salidabranches-micros
A1: service | B1: url | C1: http_code | D1: branch | E1: status | F1: property_key | G1: property_value | H1: presente globales sys | I1: value en sys | J1: presente globales baas | K1: value en baas | L1: presente globales bff | M1: value en bff
A2: ms-baas-consumer-loan-v1 | B2: http://repos.bancsabadell.com/bitbucket/rest/api/1.0/projects/P4CP/repos/ms-baas-consumer-loan-v1-conf/browse/pro/configs/application.yaml?at=release/1.3.3 | C2: 404 | D2: release/1.3.3 | E2: 404 | H2: =ISNUMBER(MATCH(F2,'globales-sys'!F:F, 0)) -> FALSE | I2: =IFERROR(INDEX('globales-sys'!G:G, MATCH(F2,'globales-sys'!F:F, 0)), "") | J2: =ISNUMBER(MATCH(F2,'globales-baas'!F:F, 0)) -> FALSE | K2: =IFERROR(INDEX('globales-baas'!G:G, MATCH(F2,'globales-baas'!F:F, 0)), "") | L2: =ISNUMBER(MATCH(F2,'globales-bff'!F:F, 0)) -> FALSE | M2: =IFERROR(INDEX('globales-bff'!G:G, MATCH(F2,'globales-bff'!F:F, 0)), "")
A3: ms-batch-sinfonia-processor | B3: http://repos.bancsabadell.com/bitbucket/rest/api/1.0/projects/p4cp/repos/ms-batch-sinfonia-processor-conf/browse/pro/configs/application.yaml?at=release/1.0.7 | C3: 404 | D3: release/1.0.7 | E3: 404 | H3: =ISNUMBER(MATCH(F3,'globales-sys'!F:F, 0)) -> FALSE | I3: =IFERROR(INDEX('globales-sys'!G:G, MATCH(F3,'globales-sys'!F:F, 0)), "") | J3: =ISNUMBER(MATCH(F3,'globales-baas'!F:F, 0)) -> FALSE | K3: =IFERROR(INDEX('globales-baas'!G:G, MATCH(F3,'globales-baas'!F:F, 0)), "") | L3: =ISNUMBER(MATCH(F3,'globales-bff'!F:F, 0)) -> FALSE | M3: =IFERROR(INDEX('globales-bff'!G:G, MATCH(F3,'globales-bff'!F:F, 0)), "")
A4: ms-baas-special-pricing-conditions | B4: http://repos.bancsabadell.com/bitbucket/rest/api/1.0/projects/JUST_RAROC/repos/ms-baas-special-pricing-conditions-conf/browse/pro/configs/application.yaml?at=release/0.8.19 | C4: 404 | D4: release/0.8.19 | E4: 404 | H4: =ISNUMBER(MATCH(F4,'globales-sys'!F:F, 0)) -> FALSE | I4: =IFERROR(INDEX('globales-sys'!G:G, MATCH(F4,'globales-sys'!F:F, 0)), "") | J4: =ISNUMBER(MATCH(F4,'globales-baas'!F:F, 0)) -> FALSE | K4: =IFERROR(INDEX('globales-baas'!G:G, MATCH(F4,'globales-baas'!F:F, 0)), "") | L4: =ISNUMBER(MATCH(F4,'globales-bff'!F:F, 0)) -> FALSE | M4: =IFERROR(INDEX('globales-bff'!G:G, MATCH(F4,'globales-bff'!F:F, 0)), "")
A5: ms-sys-credit-facility-online-pr | B5: http://repos.bancsabadell.com/bitbucket/rest/api/1.0/projects/P4CP/repos/ms-sys-credit-facility-online-pr-conf/browse/pro/configs/application.yaml?at=release/1.0.2 | C5: 404 | D5: release/1.0.2 | E5: 404 | H5: =ISNUMBER(MATCH(F5,'globales-sys'!F:F, 0)) -> FALSE | I5: =IFERROR(INDEX('globales-sys'!G:G, MATCH(F5,'globales-sys'!F:F, 0)), "") | J5: =ISNUMBER(MATCH(F5,'globales-baas'!F:F, 0)) -> FALSE | K5: =IFERROR(INDEX('globales-baas'!G:G, MATCH(F5,'globales-baas'!F:F, 0)), "") | L5: =ISNUMBER(MATCH(F5,'globales-bff'!F:F, 0)) -> FALSE | M5: =IFERROR(INDEX('globales-bff'!G:G, MATCH(F5,'globales-bff'!F:F, 0)), "")
A6: ms-baas-scf-packaging | B6: http://repos.bancsabadell.com/bitbucket/rest/api/1.0/projects/p4cp/repos/ms-baas-scf-packaging-conf/browse/pro/configs/application.yaml?at=release/1.0.6 | C6: 200 | D6: release/1.0.6 | E6: OK | F6: proteo4.domain-client.services[0].base-url | G6: https://ms-sys-party-reference-data-pe-pro-ns-sys.apps.pro.aws.bancsabadell.com | H6: =ISNUMBER(MATCH(F6,'globales-sys'!F:F, 0)) -> FALSE | I6: =IFERROR(INDEX('globales-sys'!G:G, MATCH(F6,'globales-sys'!F:F, 0)), "") | J6: =ISNUMBER(MATCH(F6,'globales-baas'!F:F, 0)) -> FALSE | K6: =IFERROR(INDEX('globales-baas'!G:G, MATCH(F6,'globales-baas'!F:F, 0)), "") | L6: =ISNUMBER(MATCH(F6,'globales-bff'!F:F, 0)) -> FALSE | M6: =IFERROR(INDEX('globales-bff'!G:G, MATCH(F6,'globales-bff'!F:F, 0)), "")
A7: ms-baas-scf-packaging | B7: http://repos.bancsabadell.com/bitbucket/rest/api/1.0/projects/p4cp/repos/ms-baas-scf-packaging-conf/browse/pro/configs/application.yaml?at=release/1.0.6 | C7: 200 | D7: release/1.0.6 | E7: OK | F7: proteo4.domain-client.services[1].base-url | G7: https://ms-sys-party-reference-data-pe-v2-pro-ns-sys.apps.pro.aws.bancsabadell.com | H7: =ISNUMBER(MATCH(F7,'globales-sys'!F:F, 0)) -> FALSE | I7: =IFERROR(INDEX('globales-sys'!G:G, MATCH(F7,'globales-sys'!F:F, 0)), "") | J7: =ISNUMBER(MATCH(F7,'globales-baas'!F:F, 0)) -> FALSE | K7: =IFERROR(INDEX('globales-baas'!G:G, MATCH(F7,'globales-baas'!F:F, 0)), "") | L7: =ISNUMBER(MATCH(F7,'globales-bff'!F:F, 0)) -> FALSE | M7: =IFERROR(INDEX('globales-bff'!G:G, MATCH(F7,'globales-bff'!F:F, 0)), "")
A8: ms-baas-scf-packaging | B8: http://repos.bancsabadell.com/bitbucket/rest/api/1.0/projects/p4cp/repos/ms-baas-scf-packaging-conf/browse/pro/configs/application.yaml?at=release/1.0.6 | C8: 200 | D8: release/1.0.6 | E8: OK | F8: proteo4.domain-client.services[2].base-url | G8: https://ms-sys-legal-entity-directory-ee-v1-pro-ns-sys.apps.pro.aws.bancsabadell.com | H8: =ISNUMBER(MATCH(F8,'globales-sys'!F:F, 0)) -> FALSE | I8: =IFERROR(INDEX('globales-sys'!G:G, MATCH(F8,'globales-sys'!F:F, 0)), "") | J8: =ISNUMBER(MATCH(F8,'globales-baas'!F:F, 0)) -> FALSE | K8: =IFERROR(INDEX('globales-baas'!G:G, MATCH(F8,'globales-baas'!F:F, 0)), "") | L8: =ISNUMBER(MATCH(F8,'globales-bff'!F:F, 0)) -> FALSE | M8: =IFERROR(INDEX('globales-bff'!G:G, MATCH(F8,'globales-bff'!F:F, 0)), "")
A9: ms-baas-scf-packaging | B9: http://repos.bancsabadell.com/bitbucket/rest/api/1.0/projects/p4cp/repos/ms-baas-scf-packaging-conf/browse/pro/configs/application.yaml?at=release/1.0.6 | C9: 200 | D9: release/1.0.6 | E9: OK | F9: proteo4.domain-client.services[3].base-url | G9: https://ms-sys-consumer-loan-scf-pro-ns-sys.apps.pro.aws.bancsabadell.com | H9: =ISNUMBER(MATCH(F9,'globales-sys'!F:F, 0)) -> FALSE | I9: =IFERROR(INDEX('globales-sys'!G:G, MATCH(F9,'globales-sys'!F:F, 0)), "") | J9: =ISNUMBER(MATCH(F9,'globales-baas'!F:F, 0)) -> FALSE | K9: =IFERROR(INDEX('globales-baas'!G:G, MATCH(F9,'globales-baas'!F:F, 0)), "") | L9: =ISNUMBER(MATCH(F9,'globales-bff'!F:F, 0)) -> FALSE | M9: =IFERROR(INDEX('globales-bff'!G:G, MATCH(F9,'globales-bff'!F:F, 0)), "")
A10: ms-baas-scf-packaging | B10: http://repos.bancsabadell.com/bitbucket/rest/api/1.0/projects/p4cp/repos/ms-baas-scf-packaging-conf/browse/pro/configs/application.yaml?at=release/1.0.6 | C10: 200 | D10: release/1.0.6 | E10: OK | F10: proteo4.domain-client.services[4].base-url | G10: https://ms-sys-customer-relationship-management-scf-pro-ns-sys.apps.pro.aws.bancsabadell.com | H10: =ISNUMBER(MATCH(F10,'globales-sys'!F:F, 0)) -> FALSE | I10: =IFERROR(INDEX('globales-sys'!G:G, MATCH(F10,'globales-sys'!F:F, 0)), "") | J10: =ISNUMBER(MATCH(F10,'globales-baas'!F:F, 0)) -> FALSE | K10: =IFERROR(INDEX('globales-baas'!G:G, MATCH(F10,'globales-baas'!F:F, 0)), "") | L10: =ISNUMBER(MATCH(F10,'globales-bff'!F:F, 0)) -> FALSE | M10: =IFERROR(INDEX('globales-bff'!G:G, MATCH(F10,'globales-bff'!F:F, 0)), "")
A11: ms-baas-scf-packaging | B11: http://repos.bancsabadell.com/bitbucket/rest/api/1.0/projects/p4cp/repos/ms-baas-scf-packaging-conf/browse/pro/configs/application.yaml?at=release/1.0.6 | C11: 200 | D11: release/1.0.6 | E11: OK | F11: proteo4.domain-client.services[5].base-url | G11: https://ms-sys-card-terminal-operation-ps-pro-ns-sys.apps.pro.aws.bancsabadell.com | H11: =ISNUMBER(MATCH(F11,'globales-sys'!F:F, 0)) -> FALSE | I11: =IFERROR(INDEX('globales-sys'!G:G, MATCH(F11,'globales-sys'!F:F, 0)), "") | J11: =ISNUMBER(MATCH(F11,'globales-baas'!F:F, 0)) -> FALSE | K11: =IFERROR(INDEX('globales-baas'!G:G, MATCH(F11,'globales-baas'!F:F, 0)), "") | L11: =ISNUMBER(MATCH(F11,'globales-bff'!F:F, 0)) -> FALSE | M11: =IFERROR(INDEX('globales-bff'!G:G, MATCH(F11,'globales-bff'!F:F, 0)), "")
A12: ms-baas-scf-packaging | B12: http://repos.bancsabadell.com/bitbucket/rest/api/1.0/projects/p4cp/repos/ms-baas-scf-packaging-conf/browse/pro/configs/application.yaml?at=release/1.0.6 | C12: 200 | D12: release/1.0.6 | E12: OK | F12: proteo4.domain-client.services[6].base-url | G12: https://ms-sys-customer-campaign-execution-system-kx-pro-ns-sys.apps.pro.aws.bancsabadell.com | H12: =ISNUMBER(MATCH(F12,'globales-sys'!F:F, 0)) -> FALSE | I12: =IFERROR(INDEX('globales-sys'!G:G, MATCH(F12,'globales-sys'!F:F, 0)), "") | J12: =ISNUMBER(MATCH(F12,'globales-baas'!F:F, 0)) -> FALSE | K12: =IFERROR(INDEX('globales-baas'!G:G, MATCH(F12,'globales-baas'!F:F, 0)), "") | L12: =ISNUMBER(MATCH(F12,'globales-bff'!F:F, 0)) -> FALSE | M12: =IFERROR(INDEX('globales-bff'!G:G, MATCH(F12,'globales-bff'!F:F, 0)), "")
A13: ms-baas-scf-packaging | B13: http://repos.bancsabadell.com/bitbucket/rest/api/1.0/projects/p4cp/repos/ms-baas-scf-packaging-conf/browse/pro/configs/application.yaml?at=release/1.0.6 | C13: 200 | D13: release/1.0.6 | E13: OK | F13: proteo4.domain-client.services[7].base-url | G13: https://ms-sys-legal-entity-directory-pe-v1-pro-ns-sys.apps.pro.aws.bancsabadell.com | H13: =ISNUMBER(MATCH(F13,'globales-sys'!F:F, 0)) -> FALSE | I13: =IFERROR(INDEX('globales-sys'!G:G, MATCH(F13,'globales-sys'!F:F, 0)), "") | J13: =ISNUMBER(MATCH(F13,'globales-baas'!F:F, 0)) -> FALSE | K13: =IFERROR(INDEX('globales-baas'!G:G, MATCH(F13,'globales-baas'!F:F, 0)), "") | L13: =ISNUMBER(MATCH(F13,'globales-bff'!F:F, 0)) -> FALSE | M13: =IFERROR(INDEX('globales-bff'!G:G, MATCH(F13,'globales-bff'!F:F, 0)), "")
A14: ms-baas-scf-packaging | B14: http://repos.bancsabadell.com/bitbucket/rest/api/1.0/projects/p4cp/repos/ms-baas-scf-packaging-conf/browse/pro/configs/application.yaml?at=release/1.0.6 | C14: 200 | D14: release/1.0.6 | E14: OK | F14: proteo4.domain-client.services[8].base-url | G14: https://ms-sys-sales-product-agreement-system-pe-v1-pro-ns-sys.apps.pro.aws.bancsabadell.com | H14: =ISNUMBER(MATCH(F14,'globales-sys'!F:F, 0)) -> FALSE | I14: =IFERROR(INDEX('globales-sys'!G:G, MATCH(F14,'globales-sys'!F:F, 0)), "") | J14: =ISNUMBER(MATCH(F14,'globales-baas'!F:F, 0)) -> FALSE | K14: =IFERROR(INDEX('globales-baas'!G:G, MATCH(F14,'globales-baas'!F:F, 0)), "") | L14: =ISNUMBER(MATCH(F14,'globales-bff'!F:F, 0)) -> FALSE | M14: =IFERROR(INDEX('globales-bff'!G:G, MATCH(F14,'globales-bff'!F:F, 0)), "")
A15: ms-sys-card-terminal-operation-ps | B15: http://repos.bancsabadell.com/bitbucket/rest/api/1.0/projects/P4CP/repos/ms-sys-card-terminal-operation-ps-conf/browse/pro/configs/application.yaml?at=release/1.0.2 | C15: 200 | D15: release/1.0.2 | E15: OK | F15: proteo4.error-literal.baseUrl | G15: https://ms-infra-literal-adapter-pro-ns-inf.apps.pro.aws.bancsabadell.com | H15: =ISNUMBER(MATCH(F15,'globales-sys'!F:F, 0)) -> FALSE | I15: =IFERROR(INDEX('globales-sys'!G:G, MATCH(F15,'globales-sys'!F:F, 0)), "") | J15: =ISNUMBER(MATCH(F15,'globales-baas'!F:F, 0)) -> FALSE | K15: =IFERROR(INDEX('globales-baas'!G:G, MATCH(F15,'globales-baas'!F:F, 0)), "") | L15: =ISNUMBER(MATCH(F15,'globales-bff'!F:F, 0)) -> FALSE | M15: =IFERROR(INDEX('globales-bff'!G:G, MATCH(F15,'globales-bff'!F:F, 0)), "")
A16: ms-sys-card-terminal-operation-ps | B16: http://repos.bancsabadell.com/bitbucket/rest/api/1.0/projects/P4CP/repos/ms-sys-card-terminal-operation-ps-conf/browse/pro/configs/application.yaml?at=release/1.0.2 | C16: 200 | D16: release/1.0.2 | E16: OK | F16: proteo4.mainframe-adapter.base-url | G16: https://ms-infra-mainframe-adapter-pro-ns-inf.apps.pro.aws.bancsabadell.com | H16: =ISNUMBER(MATCH(F16,'globales-sys'!F:F, 0)) -> TRUE | I16: =IFERROR(INDEX('globales-sys'!G:G, MATCH(F16,'globales-sys'!F:F, 0)), "") -> https://ms-infra-mainframe-adapter-pro-ns-inf.${PROVIDER_SUFFIX_URL:apps.pro.aws.bancsabadell.com} | J16: =ISNUMBER(MATCH(F16,'globales-baas'!F:F, 0)) -> FALSE | K16: =IFERROR(INDEX('globales-baas'!G:G, MATCH(F16,'globales-baas'!F:F, 0)), "") | L16: =ISNUMBER(MATCH(F16,'globales-bff'!F:F, 0)) -> FALSE | M16: =IFERROR(INDEX('globales-bff'!G:G, MATCH(F16,'globales-bff'!F:F, 0)), "")
A17: ms-sys-customer-campaign-execution-system-kx | B17: http://repos.bancsabadell.com/bitbucket/rest/api/1.0/projects/P4CP/repos/ms-sys-customer-campaign-execution-system-kx-conf/browse/pro/configs/application.yaml?at=release/1.0.2 | C17: 200 | D17: release/1.0.2 | E17: OK | F17: proteo4.error-literal.baseUrl | G17: https://ms-infra-literal-adapter-pro-ns-inf.apps.pro.aws.bancsabadell.com | H17: =ISNUMBER(MATCH(F17,'globales-sys'!F:F, 0)) -> FALSE | I17: =IFERROR(INDEX('globales-sys'!G:G, MATCH(F17,'globales-sys'!F:F, 0)), "") | J17: =ISNUMBER(MATCH(F17,'globales-baas'!F:F, 0)) -> FALSE | K17: =IFERROR(INDEX('globales-baas'!G:G, MATCH(F17,'globales-baas'!F:F, 0)), "") | L17: =ISNUMBER(MATCH(F17,'globales-bff'!F:F, 0)) -> FALSE | M17: =IFERROR(INDEX('globales-bff'!G:G, MATCH(F17,'globales-bff'!F:F, 0)), "")
A18: ms-sys-customer-campaign-execution-system-kx | B18: http://repos.bancsabadell.com/bitbucket/rest/api/1.0/projects/P4CP/repos/ms-sys-customer-campaign-execution-system-kx-conf/browse/pro/configs/application.yaml?at=release/1.0.2 | C18: 200 | D18: release/1.0.2 | E18: OK | F18: proteo4.mainframe-adapter.base-url | G18: https://ms-infra-mainframe-adapter-pro-ns-inf.apps.pro.aws.bancsabadell.com | H18: =ISNUMBER(MATCH(F18,'globales-sys'!F:F, 0)) -> TRUE | I18: =IFERROR(INDEX('globales-sys'!G:G, MATCH(F18,'globales-sys'!F:F, 0)), "") -> https://ms-infra-mainframe-adapter-pro-ns-inf.${PROVIDER_SUFFIX_URL:apps.pro.aws.bancsabadell.com} | J18: =ISNUMBER(MATCH(F18,'globales-baas'!F:F, 0)) -> FALSE | K18: =IFERROR(INDEX('globales-baas'!G:G, MATCH(F18,'globales-baas'!F:F, 0)), "") | L18: =ISNUMBER(MATCH(F18,'globales-bff'!F:F, 0)) -> FALSE | M18: =IFERROR(INDEX('globales-bff'!G:G, MATCH(F18,'globales-bff'!F:F, 0)), "")
A19: ms-baas-factoring-v1 | B19: http://repos.bancsabadell.com/bitbucket/rest/api/1.0/projects/P4cp/repos/ms-baas-factoring-v1-conf/browse/pro/configs/application.yaml?at=release/1.0.6 | C19: 404 | D19: release/1.0.6 | E19: 404 | H19: =ISNUMBER(MATCH(F19,'globales-sys'!F:F, 0)) -> FALSE | I19: =IFERROR(INDEX('globales-sys'!G:G, MATCH(F19,'globales-sys'!F:F, 0)), "") | J19: =ISNUMBER(MATCH(F19,'globales-baas'!F:F, 0)) -> FALSE | K19: =IFERROR(INDEX('globales-baas'!G:G, MATCH(F19,'globales-baas'!F:F, 0)), "") | L19: =ISNUMBER(MATCH(F19,'globales-bff'!F:F, 0)) -> FALSE | M19: =IFERROR(INDEX('globales-bff'!G:G, MATCH(F19,'globales-bff'!F:F, 0)), "")
A20: ms-sys-factoring-system-fa-v1 | B20: http://repos.bancsabadell.com/bitbucket/rest/api/1.0/projects/P4cp/repos/ms-sys-factoring-system-fa-v1-conf/browse/pro/configs/application.yaml?at=release/1.0.6 | C20: 404 | D20: release/1.0.6 | E20: 404 | H20: =ISNUMBER(MATCH(F20,'globales-sys'!F:F, 0)) -> FALSE | I20: =IFERROR(INDEX('globales-sys'!G:G, MATCH(F20,'globales-sys'!F:F, 0)), "") | J20: =ISNUMBER(MATCH(F20,'globales-baas'!F:F, 0)) -> FALSE | K20: =IFERROR(INDEX('globales-baas'!G:G, MATCH(F20,'globales-baas'!F:F, 0)), "") | L20: =ISNUMBER(MATCH(F20,'globales-bff'!F:F, 0)) -> FALSE | M20: =IFERROR(INDEX('globales-bff'!G:G, MATCH(F20,'globales-bff'!F:F, 0)), "")
A21: ms-sys-confirming-kf-v1 | B21: http://repos.bancsabadell.com/bitbucket/rest/api/1.0/projects/p4cp/repos/ms-sys-confirming-kf-v1-conf/browse/pro/configs/application.yaml?at=release/1.0.8 | C21: 200 | D21: release/1.0.8 | E21: OK | F21: proteo4.file-storage-service-platform.base-url-uploadlink | G21: https://content.pro.aws.bancsabadell.com/private-document-library-storage/v1 | H21: =ISNUMBER(MATCH(F21,'globales-sys'!F:F, 0)) -> FALSE | I21: =IFERROR(INDEX('globales-sys'!G:G, MATCH(F21,'globales-sys'!F:F, 0)), "") | J21: =ISNUMBER(MATCH(F21,'globales-baas'!F:F, 0)) -> FALSE | K21: =IFERROR(INDEX('globales-baas'!G:G, MATCH(F21,'globales-baas'!F:F, 0)), "") | L21: =ISNUMBER(MATCH(F21,'globales-bff'!F:F, 0)) -> FALSE | M21: =IFERROR(INDEX('globales-bff'!G:G, MATCH(F21,'globales-bff'!F:F, 0)), "")
A22: ms-sys-xy-common-data | B22: http://repos.bancsabadell.com/bitbucket/rest/api/1.0/projects/P4CP/repos/ms-sys-xy-common-data-conf/browse/pro/configs/application.yaml?at=release/1.1.0 | C22: 200 | D22: release/1.1.0 | E22: OK | F22: proteo4.mainframe-adapter.base-url | G22: https://ms-infra-mainframe-adapter-pro-ns-inf.apps.pro.aws.bancsabadell.com | H22: =ISNUMBER(MATCH(F22,'globales-sys'!F:F, 0)) -> TRUE | I22: =IFERROR(INDEX('globales-sys'!G:G, MATCH(F22,'globales-sys'!F:F, 0)), "") -> https://ms-infra-mainframe-adapter-pro-ns-inf.${PROVIDER_SUFFIX_URL:apps.pro.aws.bancsabadell.com} | J22: =ISNUMBER(MATCH(F22,'globales-baas'!F:F, 0)) -> FALSE | K22: =IFERROR(INDEX('globales-baas'!G:G, MATCH(F22,'globales-baas'!F:F, 0)), "") | L22: =ISNUMBER(MATCH(F22,'globales-bff'!F:F, 0)) -> FALSE | M22: =IFERROR(INDEX('globales-bff'!G:G, MATCH(F22,'globales-bff'!F:F, 0)), "")
A23: ms-sys-consumer-loan-system-pr | B23: http://repos.bancsabadell.com/bitbucket/rest/api/1.0/projects/P4CP/repos/ms-sys-consumer-loan-system-pr-conf/browse/pro/configs/application.yaml?at=release/1.0.6 | C23: 404 | D23: release/1.0.6 | E23: 404 | H23: =ISNUMBER(MATCH(F23,'globales-sys'!F:F, 0)) -> FALSE | I23: =IFERROR(INDEX('globales-sys'!G:G, MATCH(F23,'globales-sys'!F:F, 0)), "") | J23: =ISNUMBER(MATCH(F23,'globales-baas'!F:F, 0)) -> FALSE | K23: =IFERROR(INDEX('globales-baas'!G:G, MATCH(F23,'globales-baas'!F:F, 0)), "") | L23: =ISNUMBER(MATCH(F23,'globales-bff'!F:F, 0)) -> FALSE | M23: =IFERROR(INDEX('globales-bff'!G:G, MATCH(F23,'globales-bff'!F:F, 0)), "")
A24: ms-sys-factoring-inblock-v1 | B24: http://repos.bancsabadell.com/bitbucket/rest/api/1.0/projects/P4CP/repos/ms-sys-factoring-inblock-v1-conf/browse/pro/configs/application.yaml?at=release/1.2.5 | C24: 200 | D24: release/1.2.5 | E24: OK | F24: proteo4.file-storage-service-platform.base-url | G24: https://ms-storage-api-pro-ns-storage.apps.pro.aws.bancsabadell.com/private-document-library-storage/v1 | H24: =ISNUMBER(MATCH(F24,'globales-sys'!F:F, 0)) -> TRUE | I24: =IFERROR(INDEX('globales-sys'!G:G, MATCH(F24,'globales-sys'!F:F, 0)), "") -> https://ms-storage-api-pro-ns-inf.${PROVIDER_SUFFIX_URL:apps.pro.aws.bancsabadell.com}/private-document-library-storage/v1 | J24: =ISNUMBER(MATCH(F24,'globales-baas'!F:F, 0)) -> FALSE | K24: =IFERROR(INDEX('globales-baas'!G:G, MATCH(F24,'globales-baas'!F:F, 0)), "") | L24: =ISNUMBER(MATCH(F24,'globales-bff'!F:F, 0)) -> FALSE | M24: =IFERROR(INDEX('globales-bff'!G:G, MATCH(F24,'globales-bff'!F:F, 0)), "")
A25: ms-sys-factoring-inblock-v1 | B25: http://repos.bancsabadell.com/bitbucket/rest/api/1.0/projects/P4CP/repos/ms-sys-factoring-inblock-v1-conf/browse/pro/configs/application.yaml?at=release/1.2.5 | C25: 200 | D25: release/1.2.5 | E25: OK | F25: proteo4.file-storage-service-platform.base-url-uploadlink | G25: https://content.pro.aws.bancsabadell.com/private-document-library-storage/v1 | H25: =ISNUMBER(MATCH(F25,'globales-sys'!F:F, 0)) -> FALSE | I25: =IFERROR(INDEX('globales-sys'!G:G, MATCH(F25,'globales-sys'!F:F, 0)), "") | J25: =ISNUMBER(MATCH(F25,'globales-baas'!F:F, 0)) -> FALSE | K25: =IFERROR(INDEX('globales-baas'!G:G, MATCH(F25,'globales-baas'!F:F, 0)), "") | L25: =ISNUMBER(MATCH(F25,'globales-bff'!F:F, 0)) -> FALSE | M25: =IFERROR(INDEX('globales-bff'!G:G, MATCH(F25,'globales-bff'!F:F, 0)), "")
A26: ms-sys-factoring-inblock-v1 | B26: http://repos.bancsabadell.com/bitbucket/rest/api/1.0/projects/P4CP/repos/ms-sys-factoring-inblock-v1-conf/browse/pro/configs/application.yaml?at=release/1.2.5 | C26: 200 | D26: release/1.2.5 | E26: OK | F26: proteo4.netapp.clients[0].s3-settings.client.endpoint | G26: https://otm1.sgrid.es.bs/ | H26: =ISNUMBER(MATCH(F26,'globales-sys'!F:F, 0)) -> FALSE | I26: =IFERROR(INDEX('globales-sys'!G:G, MATCH(F26,'globales-sys'!F:F, 0)), "") | J26: =ISNUMBER(MATCH(F26,'globales-baas'!F:F, 0)) -> FALSE | K26: =IFERROR(INDEX('globales-baas'!G:G, MATCH(F26,'globales-baas'!F:F, 0)), "") | L26: =ISNUMBER(MATCH(F26,'globales-bff'!F:F, 0)) -> FALSE | M26: =IFERROR(INDEX('globales-bff'!G:G, MATCH(F26,'globales-bff'!F:F, 0)), "")
A27: ms-sys-factoring-inblock-v1 | B27: http://repos.bancsabadell.com/bitbucket/rest/api/1.0/projects/P4CP/repos/ms-sys-factoring-inblock-v1-conf/browse/pro/configs/application.yaml?at=release/1.2.5 | C27: 200 | D27: release/1.2.5 | E27: OK | F27: inblock.endpoints.base-url | G27: https://api.inblockaef.com/v1 | H27: =ISNUMBER(MATCH(F27,'globales-sys'!F:F, 0)) -> FALSE | I27: =IFERROR(INDEX('globales-sys'!G:G, MATCH(F27,'globales-sys'!F:F, 0)), "") | J27: =ISNUMBER(MATCH(F27,'globales-baas'!F:F, 0)) -> FALSE | K27: =IFERROR(INDEX('globales-baas'!G:G, MATCH(F27,'globales-baas'!F:F, 0)), "") | L27: =ISNUMBER(MATCH(F27,'globales-bff'!F:F, 0)) -> FALSE | M27: =IFERROR(INDEX('globales-bff'!G:G, MATCH(F27,'globales-bff'!F:F, 0)), "")
A28: ms-batch-inblock-upload | B28: http://repos.bancsabadell.com/bitbucket/rest/api/1.0/projects/P4CP/repos/ms-batch-inblock-upload-conf/browse/pro/configs/application.yaml?at=release/1.0.4 | C28: 200 | D28: release/1.0.4 | E28: OK | F28: proteo4.domain-client.services[0].base-url | G28: https://ms-sys-factoring-inblock-v1-pro-ns-sys.apps.pro.aws.bancsabadell.com | H28: =ISNUMBER(MATCH(F28,'globales-sys'!F:F, 0)) -> FALSE | I28: =IFERROR(INDEX('globales-sys'!G:G, MATCH(F28,'globales-sys'!F:F, 0)), "") | J28: =ISNUMBER(MATCH(F28,'globales-baas'!F:F, 0)) -> FALSE | K28: =IFERROR(INDEX('globales-baas'!G:G, MATCH(F28,'globales-baas'!F:F, 0)), "") | L28: =ISNUMBER(MATCH(F28,'globales-bff'!F:F, 0)) -> FALSE | M28: =IFERROR(INDEX('globales-bff'!G:G, MATCH(F28,'globales-bff'!F:F, 0)), "")
A29: ms-sys-investment-account | B29: http://repos.bancsabadell.com/bitbucket/rest/api/1.0/projects/P4GC/repos/ms-sys-investment-account-conf/browse/pro/configs/application.yaml?at=release/1.3.1 | C29: 200 | D29: release/1.3.1 | E29: OK | F29: downloadDocument | G29: https://content.pro.aws.bancsabadell.com/v1/documents/ | H29: =ISNUMBER(MATCH(F29,'globales-sys'!F:F, 0)) -> FALSE | I29: =IFERROR(INDEX('globales-sys'!G:G, MATCH(F29,'globales-sys'!F:F, 0)), "") | J29: =ISNUMBER(MATCH(F29,'globales-baas'!F:F, 0)) -> FALSE | K29: =IFERROR(INDEX('globales-baas'!G:G, MATCH(F29,'globales-baas'!F:F, 0)), "") | L29: =ISNUMBER(MATCH(F29,'globales-bff'!F:F, 0)) -> FALSE | M29: =IFERROR(INDEX('globales-bff'!G:G, MATCH(F29,'globales-bff'!F:F, 0)), "")
A30: ms-infra-document-manager | B30: https://bitbucket.apps.devops.aws.bancsabadell.com/rest/api/1.0/projects/p4des/repos/ms-infra-document-manager-conf/browse/pro/configs/application.yaml?at=release/1.4.1 | C30: 200 | D30: release/1.4.1 | E30: OK | F30: spring.kafka.properties.schema.registry.url | G30: https://schemaregistry.apps.pro.aws.bancsabadell.com | H30: =ISNUMBER(MATCH(F30,'globales-sys'!F:F, 0)) -> FALSE | I30: =IFERROR(INDEX('globales-sys'!G:G, MATCH(F30,'globales-sys'!F:F, 0)), "") | J30: =ISNUMBER(MATCH(F30,'globales-baas'!F:F, 0)) -> FALSE | K30: =IFERROR(INDEX('globales-baas'!G:G, MATCH(F30,'globales-baas'!F:F, 0)), "") | L30: =ISNUMBER(MATCH(F30,'globales-bff'!F:F, 0)) -> FALSE | M30: =IFERROR(INDEX('globales-bff'!G:G, MATCH(F30,'globales-bff'!F:F, 0)), "")
A31: ms-infra-document-manager | B31: https://bitbucket.apps.devops.aws.bancsabadell.com/rest/api/1.0/projects/p4des/repos/ms-infra-document-manager-conf/browse/pro/configs/application.yaml?at=release/1.4.1 | C31: 200 | D31: release/1.4.1 | E31: OK | F31: proteo4.netapp.clients[0].s3-settings.client.endpoint | G31: http://10.236.105.11:11600 | H31: =ISNUMBER(MATCH(F31,'globales-sys'!F:F, 0)) -> FALSE | I31: =IFERROR(INDEX('globales-sys'!G:G, MATCH(F31,'globales-sys'!F:F, 0)), "") | J31: =ISNUMBER(MATCH(F31,'globales-baas'!F:F, 0)) -> FALSE | K31: =IFERROR(INDEX('globales-baas'!G:G, MATCH(F31,'globales-baas'!F:F, 0)), "") | L31: =ISNUMBER(MATCH(F31,'globales-bff'!F:F, 0)) -> FALSE | M31: =IFERROR(INDEX('globales-bff'!G:G, MATCH(F31,'globales-bff'!F:F, 0)), "")
A32: ms-sys-transaction-authorization | B32: https://bitbucket.apps.devops.aws.bancsabadell.com/rest/api/1.0/projects/P4DES/repos/ms-sys-transaction-authorization-conf/browse/pro/configs/application.yaml?at=release/1.1.0 | C32: 404 | D32: release/1.1.0 | E32: 404 | H32: =ISNUMBER(MATCH(F32,'globales-sys'!F:F, 0)) -> FALSE | I32: =IFERROR(INDEX('globales-sys'!G:G, MATCH(F32,'globales-sys'!F:F, 0)), "") | J32: =ISNUMBER(MATCH(F32,'globales-baas'!F:F, 0)) -> FALSE | K32: =IFERROR(INDEX('globales-baas'!G:G, MATCH(F32,'globales-baas'!F:F, 0)), "") | L32: =ISNUMBER(MATCH(F32,'globales-bff'!F:F, 0)) -> FALSE | M32: =IFERROR(INDEX('globales-bff'!G:G, MATCH(F32,'globales-bff'!F:F, 0)), "")
A33: ms-baas-issued-device-administration | B33: https://bitbucket.apps.devops.aws.bancsabadell.com/rest/api/1.0/projects/P4DES/repos/ms-baas-issued-device-administration-conf/browse/pro/configs/application.yaml?at=release/0.1.0 | C33: 404 | D33: release/0.1.0 | E33: 404 | H33: =ISNUMBER(MATCH(F33,'globales-sys'!F:F, 0)) -> FALSE | I33: =IFERROR(INDEX('globales-sys'!G:G, MATCH(F33,'globales-sys'!F:F, 0)), "") | J33: =ISNUMBER(MATCH(F33,'globales-baas'!F:F, 0)) -> FALSE | K33: =IFERROR(INDEX('globales-baas'!G:G, MATCH(F33,'globales-baas'!F:F, 0)), "") | L33: =ISNUMBER(MATCH(F33,'globales-bff'!F:F, 0)) -> FALSE | M33: =IFERROR(INDEX('globales-bff'!G:G, MATCH(F33,'globales-bff'!F:F, 0)), "")
A34: ms-infra-bot-idp | B34: https://bitbucket.apps.devops.aws.bancsabadell.com/rest/api/1.0/projects/PP4SEC/repos/ms-infra-bot-idp-conf/browse/pro/configs/application.yaml?at=release/1.3.7 | C34: 200 | D34: release/1.3.7 | E34: OK | F34: proteo4.webclient.services[0].base-url | G34: https://bots.apps.pro.aws.bancsabadell.com:443 | H34: =ISNUMBER(MATCH(F34,'globales-sys'!F:F, 0)) -> FALSE | I34: =IFERROR(INDEX('globales-sys'!G:G, MATCH(F34,'globales-sys'!F:F, 0)), "") | J34: =ISNUMBER(MATCH(F34,'globales-baas'!F:F, 0)) -> FALSE | K34: =IFERROR(INDEX('globales-baas'!G:G, MATCH(F34,'globales-baas'!F:F, 0)), "") | L34: =ISNUMBER(MATCH(F34,'globales-bff'!F:F, 0)) -> FALSE | M34: =IFERROR(INDEX('globales-bff'!G:G, MATCH(F34,'globales-bff'!F:F, 0)), "")
A35: ms-infra-bot-idp | B35: https://bitbucket.apps.devops.aws.bancsabadell.com/rest/api/1.0/projects/PP4SEC/repos/ms-infra-bot-idp-conf/browse/pro/configs/application.yaml?at=release/1.3.7 | C35: 200 | D35: release/1.3.7 | E35: OK | F35: ms-infra-bot-idp.jwt.validation.claims.iss[0] | G35: http://ms-infra-security-jwt-pro-ns-inf.bancsabadell.com/ | H35: =ISNUMBER(MATCH(F35,'globales-sys'!F:F, 0)) -> FALSE | I35: =IFERROR(INDEX('globales-sys'!G:G, MATCH(F35,'globales-sys'!F:F, 0)), "") | J35: =ISNUMBER(MATCH(F35,'globales-baas'!F:F, 0)) -> FALSE | K35: =IFERROR(INDEX('globales-baas'!G:G, MATCH(F35,'globales-baas'!F:F, 0)), "") | L35: =ISNUMBER(MATCH(F35,'globales-bff'!F:F, 0)) -> FALSE | M35: =IFERROR(INDEX('globales-bff'!G:G, MATCH(F35,'globales-bff'!F:F, 0)), "")
A36: ms-infra-bot-idp | B36: https://bitbucket.apps.devops.aws.bancsabadell.com/rest/api/1.0/projects/PP4SEC/repos/ms-infra-bot-idp-conf/browse/pro/configs/application.yaml?at=release/1.3.7 | C36: 200 | D36: release/1.3.7 | E36: OK | F36: ms-infra-bot-idp.jwt.validation.claims.iss[1] | G36: http://ms-infra-jwt-partners-pro-ns-inf.bancsabadell.com/ | H36: =ISNUMBER(MATCH(F36,'globales-sys'!F:F, 0)) -> FALSE | I36: =IFERROR(INDEX('globales-sys'!G:G, MATCH(F36,'globales-sys'!F:F, 0)), "") | J36: =ISNUMBER(MATCH(F36,'globales-baas'!F:F, 0)) -> FALSE | K36: =IFERROR(INDEX('globales-baas'!G:G, MATCH(F36,'globales-baas'!F:F, 0)), "") | L36: =ISNUMBER(MATCH(F36,'globales-bff'!F:F, 0)) -> FALSE | M36: =IFERROR(INDEX('globales-bff'!G:G, MATCH(F36,'globales-bff'!F:F, 0)), "")
A37: ms-infra-bot-idp | B37: https://bitbucket.apps.devops.aws.bancsabadell.com/rest/api/1.0/projects/PP4SEC/repos/ms-infra-bot-idp-conf/browse/pro/configs/application.yaml?at=release/1.3.7 | C37: 200 | D37: release/1.3.7 | E37: OK | F37: ms-infra-bot-idp.jwt.validation.claims.iss[2] | G37: http://ms-infra-jwt-employees-pro-ns-inf.bancsabadell.com/ | H37: =ISNUMBER(MATCH(F37,'globales-sys'!F:F, 0)) -> FALSE | I37: =IFERROR(INDEX('globales-sys'!G:G, MATCH(F37,'globales-sys'!F:F, 0)), "") | J37: =ISNUMBER(MATCH(F37,'globales-baas'!F:F, 0)) -> FALSE | K37: =IFERROR(INDEX('globales-baas'!G:G, MATCH(F37,'globales-baas'!F:F, 0)), "") | L37: =ISNUMBER(MATCH(F37,'globales-bff'!F:F, 0)) -> FALSE | M37: =IFERROR(INDEX('globales-bff'!G:G, MATCH(F37,'globales-bff'!F:F, 0)), "")
A38: ms-infra-bot-idp | B38: https://bitbucket.apps.devops.aws.bancsabadell.com/rest/api/1.0/projects/PP4SEC/repos/ms-infra-bot-idp-conf/browse/pro/configs/application.yaml?at=release/1.3.7 | C38: 200 | D38: release/1.3.7 | E38: OK | F38: ms-infra-bot-idp.jwt.validation.claims.iss[3] | G38: https://ms-infra-security-jwt-pro-ns-inf.bancsabadell.com/ | H38: =ISNUMBER(MATCH(F38,'globales-sys'!F:F, 0)) -> FALSE | I38: =IFERROR(INDEX('globales-sys'!G:G, MATCH(F38,'globales-sys'!F:F, 0)), "") | J38: =ISNUMBER(MATCH(F38,'globales-baas'!F:F, 0)) -> FALSE | K38: =IFERROR(INDEX('globales-baas'!G:G, MATCH(F38,'globales-baas'!F:F, 0)), "") | L38: =ISNUMBER(MATCH(F38,'globales-bff'!F:F, 0)) -> FALSE | M38: =IFERROR(INDEX('globales-bff'!G:G, MATCH(F38,'globales-bff'!F:F, 0)), "")
A39: ms-infra-bot-idp | B39: https://bitbucket.apps.devops.aws.bancsabadell.com/rest/api/1.0/projects/PP4SEC/repos/ms-infra-bot-idp-conf/browse/pro/configs/application.yaml?at=release/1.3.7 | C39: 200 | D39: release/1.3.7 | E39: OK | F39: ms-infra-bot-idp.jwt.validation.claims.iss[4] | G39: https://ms-infra-jwt-partners-pro-ns-inf.bancsabadell.com/ | H39: =ISNUMBER(MATCH(F39,'globales-sys'!F:F, 0)) -> FALSE | I39: =IFERROR(INDEX('globales-sys'!G:G, MATCH(F39,'globales-sys'!F:F, 0)), "") | J39: =ISNUMBER(MATCH(F39,'globales-baas'!F:F, 0)) -> FALSE | K39: =IFERROR(INDEX('globales-baas'!G:G, MATCH(F39,'globales-baas'!F:F, 0)), "") | L39: =ISNUMBER(MATCH(F39,'globales-bff'!F:F, 0)) -> FALSE | M39: =IFERROR(INDEX('globales-bff'!G:G, MATCH(F39,'globales-bff'!F:F, 0)), "")
A40: ms-infra-bot-idp | B40: https://bitbucket.apps.devops.aws.bancsabadell.com/rest/api/1.0/projects/PP4SEC/repos/ms-infra-bot-idp-conf/browse/pro/configs/application.yaml?at=release/1.3.7 | C40: 200 | D40: release/1.3.7 | E40: OK | F40: ms-infra-bot-idp.jwt.validation.claims.iss[5] | G40: https://ms-infra-jwt-employees-pro-ns-inf.bancsabadell.com/ | H40: =ISNUMBER(MATCH(F40,'globales-sys'!F:F, 0)) -> FALSE | I40: =IFERROR(INDEX('globales-sys'!G:G, MATCH(F40,'globales-sys'!F:F, 0)), "") | J40: =ISNUMBER(MATCH(F40,'globales-baas'!F:F, 0)) -> FALSE | K40: =IFERROR(INDEX('globales-baas'!G:G, MATCH(F40,'globales-baas'!F:F, 0)), "") | L40: =ISNUMBER(MATCH(F40,'globales-bff'!F:F, 0)) -> FALSE | M40: =IFERROR(INDEX('globales-bff'!G:G, MATCH(F40,'globales-bff'!F:F, 0)), "")
A41: ms-infra-bot-idp | B41: https://bitbucket.apps.devops.aws.bancsabadell.com/rest/api/1.0/projects/PP4SEC/repos/ms-infra-bot-idp-conf/browse/pro/configs/application.yaml?at=release/1.3.7 | C41: 200 | D41: release/1.3.7 | E41: OK | F41: ms-infra-bot-idp.saml.properties.issuer | G41: https://ms-infra-bot-idp-pro-ns-inf.apps.pro.aws.bancsabadell.com | H41: =ISNUMBER(MATCH(F41,'globales-sys'!F:F, 0)) -> FALSE | I41: =IFERROR(INDEX('globales-sys'!G:G, MATCH(F41,'globales-sys'!F:F, 0)), "") | J41: =ISNUMBER(MATCH(F41,'globales-baas'!F:F, 0)) -> FALSE | K41: =IFERROR(INDEX('globales-baas'!G:G, MATCH(F41,'globales-baas'!F:F, 0)), "") | L41: =ISNUMBER(MATCH(F41,'globales-bff'!F:F, 0)) -> FALSE | M41: =IFERROR(INDEX('globales-bff'!G:G, MATCH(F41,'globales-bff'!F:F, 0)), "")
A42: ms-infra-bot-idp | B42: https://bitbucket.apps.devops.aws.bancsabadell.com/rest/api/1.0/projects/PP4SEC/repos/ms-infra-bot-idp-conf/browse/pro/configs/application.yaml?at=release/1.3.7 | C42: 200 | D42: release/1.3.7 | E42: OK | F42: ms-infra-bot-idp.saml.properties.recipient | G42: https://pro-openam-elb.pro.p4es.aws.bancsabadell.com:8443/o/Consumer/metaAlias/P4/sp | H42: =ISNUMBER(MATCH(F42,'globales-sys'!F:F, 0)) -> FALSE | I42: =IFERROR(INDEX('globales-sys'!G:G, MATCH(F42,'globales-sys'!F:F, 0)), "") | J42: =ISNUMBER(MATCH(F42,'globales-baas'!F:F, 0)) -> FALSE | K42: =IFERROR(INDEX('globales-baas'!G:G, MATCH(F42,'globales-baas'!F:F, 0)), "") | L42: =ISNUMBER(MATCH(F42,'globales-bff'!F:F, 0)) -> FALSE | M42: =IFERROR(INDEX('globales-bff'!G:G, MATCH(F42,'globales-bff'!F:F, 0)), "")
A43: ms-infra-bot-idp | B43: https://bitbucket.apps.devops.aws.bancsabadell.com/rest/api/1.0/projects/PP4SEC/repos/ms-infra-bot-idp-conf/browse/pro/configs/application.yaml?at=release/1.3.7 | C43: 200 | D43: release/1.3.7 | E43: OK | F43: ms-infra-bot-idp.saml.properties.audience[0] | G43: https://pro-openam-elb.pro.p4es.aws.bancsabadell.com:8443/o | H43: =ISNUMBER(MATCH(F43,'globales-sys'!F:F, 0)) -> FALSE | I43: =IFERROR(INDEX('globales-sys'!G:G, MATCH(F43,'globales-sys'!F:F, 0)), "") | J43: =ISNUMBER(MATCH(F43,'globales-baas'!F:F, 0)) -> FALSE | K43: =IFERROR(INDEX('globales-baas'!G:G, MATCH(F43,'globales-baas'!F:F, 0)), "") | L43: =ISNUMBER(MATCH(F43,'globales-bff'!F:F, 0)) -> FALSE | M43: =IFERROR(INDEX('globales-bff'!G:G, MATCH(F43,'globales-bff'!F:F, 0)), "")
A44: ms-sys-customer-offer-sv-v1 | B44: http://repos.bancsabadell.com/bitbucket/rest/api/1.0/projects/P4CP/repos/ms-sys-customer-offer-sv-v1-conf/browse/pro/configs/application.yaml?at=release/1.0.1 | C44: 404 | D44: release/1.0.1 | E44: 404 | H44: =ISNUMBER(MATCH(F44,'globales-sys'!F:F, 0)) -> FALSE | I44: =IFERROR(INDEX('globales-sys'!G:G, MATCH(F44,'globales-sys'!F:F, 0)), "") | J44: =ISNUMBER(MATCH(F44,'globales-baas'!F:F, 0)) -> FALSE | K44: =IFERROR(INDEX('globales-baas'!G:G, MATCH(F44,'globales-baas'!F:F, 0)), "") | L44: =ISNUMBER(MATCH(F44,'globales-bff'!F:F, 0)) -> FALSE | M44: =IFERROR(INDEX('globales-bff'!G:G, MATCH(F44,'globales-bff'!F:F, 0)), "")
A45: ms-sys-servicenow-menudesa | B45: http://repos.bancsabadell.com/bitbucket/rest/api/1.0/projects/ENDPOINTSERVICENOWMENUDESA/repos/ms-sys-servicenow-menudesa-conf/browse/pro/configs/application.yaml?at=release/2.1.0 | C45: 404 | D45: release/2.1.0 | E45: 404 | H45: =ISNUMBER(MATCH(F45,'globales-sys'!F:F, 0)) -> FALSE | I45: =IFERROR(INDEX('globales-sys'!G:G, MATCH(F45,'globales-sys'!F:F, 0)), "") | J45: =ISNUMBER(MATCH(F45,'globales-baas'!F:F, 0)) -> FALSE | K45: =IFERROR(INDEX('globales-baas'!G:G, MATCH(F45,'globales-baas'!F:F, 0)), "") | L45: =ISNUMBER(MATCH(F45,'globales-bff'!F:F, 0)) -> FALSE | M45: =IFERROR(INDEX('globales-bff'!G:G, MATCH(F45,'globales-bff'!F:F, 0)), "")
A46: ms-baas-position-keeping | B46: http://repos.bancsabadell.com/bitbucket/rest/api/1.0/projects/DV/repos/ms-baas-position-keeping-conf/browse/pro/configs/application.yaml?at=release/0.1.30 | C46: 401 | D46: release/0.1.30 | E46: 401 | H46: =ISNUMBER(MATCH(F46,'globales-sys'!F:F, 0)) -> FALSE | I46: =IFERROR(INDEX('globales-sys'!G:G, MATCH(F46,'globales-sys'!F:F, 0)), "") | J46: =ISNUMBER(MATCH(F46,'globales-baas'!F:F, 0)) -> FALSE | K46: =IFERROR(INDEX('globales-baas'!G:G, MATCH(F46,'globales-baas'!F:F, 0)), "") | L46: =ISNUMBER(MATCH(F46,'globales-bff'!F:F, 0)) -> FALSE | M46: =IFERROR(INDEX('globales-bff'!G:G, MATCH(F46,'globales-bff'!F:F, 0)), "")
A47: ms-sys-position-keeping-extended-v1 | B47: http://repos.bancsabadell.com/bitbucket/rest/api/1.0/projects/MOBI/repos/ms-sys-position-keeping-extended-v1-conf/browse/pro/configs/application.yaml?at=release/2.0.0 | C47: 200 | D47: release/2.0.0 | E47: OK | F47: spring.kafka.properties.schema.registry.url | G47: https://schemaregistry.apps.pro.aws.bancsabadell.com | H47: =ISNUMBER(MATCH(F47,'globales-sys'!F:F, 0)) -> FALSE | I47: =IFERROR(INDEX('globales-sys'!G:G, MATCH(F47,'globales-sys'!F:F, 0)), "") | J47: =ISNUMBER(MATCH(F47,'globales-baas'!F:F, 0)) -> FALSE | K47: =IFERROR(INDEX('globales-baas'!G:G, MATCH(F47,'globales-baas'!F:F, 0)), "") | L47: =ISNUMBER(MATCH(F47,'globales-bff'!F:F, 0)) -> FALSE | M47: =IFERROR(INDEX('globales-bff'!G:G, MATCH(F47,'globales-bff'!F:F, 0)), "")
A48: ms-baas-position-keeping-extended-v1 | B48: http://repos.bancsabadell.com/bitbucket/rest/api/1.0/projects/MOBI/repos/ms-baas-position-keeping-extended-v1-conf/browse/pro/configs/application.yaml?at=release/2.0.0 | C48: 200 | D48: release/2.0.0 | E48: OK | F48: operational-log-url | G48: https://ms-sys-operational-log-pro-ns-sys.apps.pro.aws.bancsabadell.com/v1/operational-log | H48: =ISNUMBER(MATCH(F48,'globales-sys'!F:F, 0)) -> FALSE | I48: =IFERROR(INDEX('globales-sys'!G:G, MATCH(F48,'globales-sys'!F:F, 0)), "") | J48: =ISNUMBER(MATCH(F48,'globales-baas'!F:F, 0)) -> FALSE | K48: =IFERROR(INDEX('globales-baas'!G:G, MATCH(F48,'globales-baas'!F:F, 0)), "") | L48: =ISNUMBER(MATCH(F48,'globales-bff'!F:F, 0)) -> FALSE | M48: =IFERROR(INDEX('globales-bff'!G:G, MATCH(F48,'globales-bff'!F:F, 0)), "")
A49: ms-sys-notifications | B49: https://bitbucket.apps.devops.aws.bancsabadell.com/rest/api/1.0/projects/p4des/repos/ms-sys-notifications-conf/browse/pro/configs/application.yaml?at=release/1.5.5 | C49: 200 | D49: release/1.5.5 | E49: OK | F49: ms-sys-notifications.messaging.client.base-url | G49: https://cbs.messagingcanals.bancsabadell.com:49543/axis2/services/MessagingService | H49: =ISNUMBER(MATCH(F49,'globales-sys'!F:F, 0)) -> FALSE | I49: =IFERROR(INDEX('globales-sys'!G:G, MATCH(F49,'globales-sys'!F:F, 0)), "") | J49: =ISNUMBER(MATCH(F49,'globales-baas'!F:F, 0)) -> FALSE | K49: =IFERROR(INDEX('globales-baas'!G:G, MATCH(F49,'globales-baas'!F:F, 0)), "") | L49: =ISNUMBER(MATCH(F49,'globales-bff'!F:F, 0)) -> FALSE | M49: =IFERROR(INDEX('globales-bff'!G:G, MATCH(F49,'globales-bff'!F:F, 0)), "")
A50: ms-sys-notifications-hub-email-sender | B50: https://bitbucket.apps.devops.aws.bancsabadell.com/rest/api/1.0/projects/p4des/repos/ms-sys-notifications-hub-email-sender-conf/browse/pro/configs/application.yaml?at=release/1.0.2 | C50: 200 | D50: release/1.0.2 | E50: OK | F50: spring.kafka.properties.schema.registry.url | G50: https://schemaregistry.apps.pro.aws.bancsabadell.com | H50: =ISNUMBER(MATCH(F50,'globales-sys'!F:F, 0)) -> FALSE | I50: =IFERROR(INDEX('globales-sys'!G:G, MATCH(F50,'globales-sys'!F:F, 0)), "") | J50: =ISNUMBER(MATCH(F50,'globales-baas'!F:F, 0)) -> FALSE | K50: =IFERROR(INDEX('globales-baas'!G:G, MATCH(F50,'globales-baas'!F:F, 0)), "") | L50: =ISNUMBER(MATCH(F50,'globales-bff'!F:F, 0)) -> FALSE | M50: =IFERROR(INDEX('globales-bff'!G:G, MATCH(F50,'globales-bff'!F:F, 0)), "")
A51: ms-sys-notifications-hub-email-sender | B51: https://bitbucket.apps.devops.aws.bancsabadell.com/rest/api/1.0/projects/p4des/repos/ms-sys-notifications-hub-email-sender-conf/browse/pro/configs/application.yaml?at=release/1.0.2 | C51: 200 | D51: release/1.0.2 | E51: OK | F51: proteo4.file-storage-service-platform.base-url | G51: https://ms-storage-api-pro-ns-inf.apps.pro.aws.bancsabadell.com/private-document-library-storage/v1 | H51: =ISNUMBER(MATCH(F51,'globales-sys'!F:F, 0)) -> TRUE | I51: =IFERROR(INDEX('globales-sys'!G:G, MATCH(F51,'globales-sys'!F:F, 0)), "") -> https://ms-storage-api-pro-ns-inf.${PROVIDER_SUFFIX_URL:apps.pro.aws.bancsabadell.com}/private-document-library-storage/v1 | J51: =ISNUMBER(MATCH(F51,'globales-baas'!F:F, 0)) -> FALSE | K51: =IFERROR(INDEX('globales-baas'!G:G, MATCH(F51,'globales-baas'!F:F, 0)), "") | L51: =ISNUMBER(MATCH(F51,'globales-bff'!F:F, 0)) -> FALSE | M51: =IFERROR(INDEX('globales-bff'!G:G, MATCH(F51,'globales-bff'!F:F, 0)), "")
A52: ms-sys-notifications-hub-email-sender | B52: https://bitbucket.apps.devops.aws.bancsabadell.com/rest/api/1.0/projects/p4des/repos/ms-sys-notifications-hub-email-sender-conf/browse/pro/configs/application.yaml?at=release/1.0.2 | C52: 200 | D52: release/1.0.2 | E52: OK | F52: ms-sys-notifications-hub-email-sender.messaging.client.base-url | G52: https://cbs.messagingcanals.bancsabadell.com:49543/axis2/services/MessagingService | H52: =ISNUMBER(MATCH(F52,'globales-sys'!F:F, 0)) -> FALSE | I52: =IFERROR(INDEX('globales-sys'!G:G, MATCH(F52,'globales-sys'!F:F, 0)), "") | J52: =ISNUMBER(MATCH(F52,'globales-baas'!F:F, 0)) -> FALSE | K52: =IFERROR(INDEX('globales-baas'!G:G, MATCH(F52,'globales-baas'!F:F, 0)), "") | L52: =ISNUMBER(MATCH(F52,'globales-bff'!F:F, 0)) -> FALSE | M52: =IFERROR(INDEX('globales-bff'!G:G, MATCH(F52,'globales-bff'!F:F, 0)), "")
A53: ms-sys-correspondence-ia | B53: http://repos.bancsabadell.com/bitbucket/rest/api/1.0/projects/p4cp/repos/ms-sys-correspondence-ia-conf/browse/pro/configs/application.yaml?at=release/1.0.9 | C53: 200 | D53: release/1.0.9 | E53: OK | F53: apiUrl | G53: https://api.bancsabadell.com/front/digital/correspondence/v1 | H53: =ISNUMBER(MATCH(F53,'globales-sys'!F:F, 0)) -> FALSE | I53: =IFERROR(INDEX('globales-sys'!G:G, MATCH(F53,'globales-sys'!F:F, 0)), "") | J53: =ISNUMBER(MATCH(F53,'globales-baas'!F:F, 0)) -> FALSE | K53: =IFERROR(INDEX('globales-baas'!G:G, MATCH(F53,'globales-baas'!F:F, 0)), "") | L53: =ISNUMBER(MATCH(F53,'globales-bff'!F:F, 0)) -> FALSE | M53: =IFERROR(INDEX('globales-bff'!G:G, MATCH(F53,'globales-bff'!F:F, 0)), "")
A54: ms-sys-correspondence-ia-v2 | B54: http://repos.bancsabadell.com/bitbucket/rest/api/1.0/projects/P4CP/repos/ms-sys-correspondence-ia-v2-conf/browse/pro/configs/application.yaml?at=release/1.0.6 | C54: 200 | D54: release/1.0.6 | E54: OK | F54: apiUrl | G54: https://api-exp.front.aws.bancsabadell.com/digital/correspondence/v2 | H54: =ISNUMBER(MATCH(F54,'globales-sys'!F:F, 0)) -> FALSE | I54: =IFERROR(INDEX('globales-sys'!G:G, MATCH(F54,'globales-sys'!F:F, 0)), "") | J54: =ISNUMBER(MATCH(F54,'globales-baas'!F:F, 0)) -> FALSE | K54: =IFERROR(INDEX('globales-baas'!G:G, MATCH(F54,'globales-baas'!F:F, 0)), "") | L54: =ISNUMBER(MATCH(F54,'globales-bff'!F:F, 0)) -> FALSE | M54: =IFERROR(INDEX('globales-bff'!G:G, MATCH(F54,'globales-bff'!F:F, 0)), "")
A55: ms-sys-party-routing-profile-aa | B55: http://repos.bancsabadell.com/bitbucket/rest/api/1.0/projects/MOBI/repos/ms-sys-party-routing-profile-aa-conf/browse/pro/configs/application.yaml?at=release/0.3.3 | C55: 404 | D55: release/0.3.3 | E55: 404 | H55: =ISNUMBER(MATCH(F55,'globales-sys'!F:F, 0)) -> FALSE | I55: =IFERROR(INDEX('globales-sys'!G:G, MATCH(F55,'globales-sys'!F:F, 0)), "") | J55: =ISNUMBER(MATCH(F55,'globales-baas'!F:F, 0)) -> FALSE | K55: =IFERROR(INDEX('globales-baas'!G:G, MATCH(F55,'globales-baas'!F:F, 0)), "") | L55: =ISNUMBER(MATCH(F55,'globales-bff'!F:F, 0)) -> FALSE | M55: =IFERROR(INDEX('globales-bff'!G:G, MATCH(F55,'globales-bff'!F:F, 0)), "")
A56: ms-bff-tjmovilpinrecovery | B56: http://repos.bancsabadell.com/bitbucket/rest/api/1.0/projects/P4CP/repos/ms-bff-tjmovilpinrecovery-conf/browse/pro/configs/application.yaml?at=release/0.1.6 | C56: 404 | D56: release/0.1.6 | E56: 404 | H56: =ISNUMBER(MATCH(F56,'globales-sys'!F:F, 0)) -> FALSE | I56: =IFERROR(INDEX('globales-sys'!G:G, MATCH(F56,'globales-sys'!F:F, 0)), "") | J56: =ISNUMBER(MATCH(F56,'globales-baas'!F:F, 0)) -> FALSE | K56: =IFERROR(INDEX('globales-baas'!G:G, MATCH(F56,'globales-baas'!F:F, 0)), "") | L56: =ISNUMBER(MATCH(F56,'globales-bff'!F:F, 0)) -> FALSE | M56: =IFERROR(INDEX('globales-bff'!G:G, MATCH(F56,'globales-bff'!F:F, 0)), "")
A57: ms-bff-party-reference-data-directory-v2 | B57: http://repos.bancsabadell.com/bitbucket/rest/api/1.0/projects/MOBI/repos/ms-bff-party-reference-data-directory-v2-conf/browse/pro/configs/application.yaml?at=release/1.1.2 | C57: 404 | D57: release/1.1.2 | E57: 404 | H57: =ISNUMBER(MATCH(F57,'globales-sys'!F:F, 0)) -> FALSE | I57: =IFERROR(INDEX('globales-sys'!G:G, MATCH(F57,'globales-sys'!F:F, 0)), "") | J57: =ISNUMBER(MATCH(F57,'globales-baas'!F:F, 0)) -> FALSE | K57: =IFERROR(INDEX('globales-baas'!G:G, MATCH(F57,'globales-baas'!F:F, 0)), "") | L57: =ISNUMBER(MATCH(F57,'globales-bff'!F:F, 0)) -> FALSE | M57: =IFERROR(INDEX('globales-bff'!G:G, MATCH(F57,'globales-bff'!F:F, 0)), "")
A58: ms-bff-bs-accounts-aggregation-v1 | B58: http://repos.bancsabadell.com/bitbucket/rest/api/1.0/projects/P4CP/repos/ms-bff-bs-accounts-aggregation-v1-conf/browse/pro/configs/application.yaml?at=release/0.1.3 | C58: 404 | D58: release/0.1.3 | E58: 404 | H58: =ISNUMBER(MATCH(F58,'globales-sys'!F:F, 0)) -> FALSE | I58: =IFERROR(INDEX('globales-sys'!G:G, MATCH(F58,'globales-sys'!F:F, 0)), "") | J58: =ISNUMBER(MATCH(F58,'globales-baas'!F:F, 0)) -> FALSE | K58: =IFERROR(INDEX('globales-baas'!G:G, MATCH(F58,'globales-baas'!F:F, 0)), "") | L58: =ISNUMBER(MATCH(F58,'globales-bff'!F:F, 0)) -> FALSE | M58: =IFERROR(INDEX('globales-bff'!G:G, MATCH(F58,'globales-bff'!F:F, 0)), "")
A59: ms-bff-card-financial-settlement-v1 | B59: http://repos.bancsabadell.com/bitbucket/rest/api/1.0/projects/p4cp/repos/ms-bff-card-financial-settlement-v1-conf/browse/pro/configs/application.yaml?at=release/0.1.12 | C59: 404 | D59: release/0.1.12 | E59: 404 | H59: =ISNUMBER(MATCH(F59,'globales-sys'!F:F, 0)) -> FALSE | I59: =IFERROR(INDEX('globales-sys'!G:G, MATCH(F59,'globales-sys'!F:F, 0)), "") | J59: =ISNUMBER(MATCH(F59,'globales-baas'!F:F, 0)) -> FALSE | K59: =IFERROR(INDEX('globales-baas'!G:G, MATCH(F59,'globales-baas'!F:F, 0)), "") | L59: =ISNUMBER(MATCH(F59,'globales-bff'!F:F, 0)) -> FALSE | M59: =IFERROR(INDEX('globales-bff'!G:G, MATCH(F59,'globales-bff'!F:F, 0)), "")
A60: ms-bff-cards-v1 | B60: http://repos.bancsabadell.com/bitbucket/rest/api/1.0/projects/p4cp/repos/ms-bff-cards-v1-conf/browse/pro/configs/application.yaml?at=release/0.1.4 | C60: 404 | D60: release/0.1.4 | E60: 404 | H60: =ISNUMBER(MATCH(F60,'globales-sys'!F:F, 0)) -> FALSE | I60: =IFERROR(INDEX('globales-sys'!G:G, MATCH(F60,'globales-sys'!F:F, 0)), "") | J60: =ISNUMBER(MATCH(F60,'globales-baas'!F:F, 0)) -> FALSE | K60: =IFERROR(INDEX('globales-baas'!G:G, MATCH(F60,'globales-baas'!F:F, 0)), "") | L60: =ISNUMBER(MATCH(F60,'globales-bff'!F:F, 0)) -> FALSE | M60: =IFERROR(INDEX('globales-bff'!G:G, MATCH(F60,'globales-bff'!F:F, 0)), "")
A61: ms-bff-credit-facility | B61: http://repos.bancsabadell.com/bitbucket/rest/api/1.0/projects/p4cp/repos/ms-bff-credit-facility-conf/browse/pro/configs/application.yaml?at=release/0.1.10 | C61: 404 | D61: release/0.1.10 | E61: 404 | H61: =ISNUMBER(MATCH(F61,'globales-sys'!F:F, 0)) -> FALSE | I61: =IFERROR(INDEX('globales-sys'!G:G, MATCH(F61,'globales-sys'!F:F, 0)), "") | J61: =ISNUMBER(MATCH(F61,'globales-baas'!F:F, 0)) -> FALSE | K61: =IFERROR(INDEX('globales-baas'!G:G, MATCH(F61,'globales-baas'!F:F, 0)), "") | L61: =ISNUMBER(MATCH(F61,'globales-bff'!F:F, 0)) -> FALSE | M61: =IFERROR(INDEX('globales-bff'!G:G, MATCH(F61,'globales-bff'!F:F, 0)), "")
A62: ms-domain-selae-redsys | B62: http://repos.bancsabadell.com/bitbucket/rest/api/1.0/projects/MOBI/repos/ms-domain-selae-redsys-conf/browse/pro/configs/application.yaml?at=release/0.1.3 | C62: 404 | D62: release/0.1.3 | E62: 404 | H62: =ISNUMBER(MATCH(F62,'globales-sys'!F:F, 0)) -> FALSE | I62: =IFERROR(INDEX('globales-sys'!G:G, MATCH(F62,'globales-sys'!F:F, 0)), "") | J62: =ISNUMBER(MATCH(F62,'globales-baas'!F:F, 0)) -> FALSE | K62: =IFERROR(INDEX('globales-baas'!G:G, MATCH(F62,'globales-baas'!F:F, 0)), "") | L62: =ISNUMBER(MATCH(F62,'globales-bff'!F:F, 0)) -> FALSE | M62: =IFERROR(INDEX('globales-bff'!G:G, MATCH(F62,'globales-bff'!F:F, 0)), "")
A63: ms-bff-onfido | B63: http://repos.bancsabadell.com/bitbucket/rest/api/1.0/projects/mobi/repos/ms-bff-onfido-conf/browse/pro/configs/application.yaml?at=release/0.2.2 | C63: 404 | D63: release/0.2.2 | E63: 404 | H63: =ISNUMBER(MATCH(F63,'globales-sys'!F:F, 0)) -> FALSE | I63: =IFERROR(INDEX('globales-sys'!G:G, MATCH(F63,'globales-sys'!F:F, 0)), "") | J63: =ISNUMBER(MATCH(F63,'globales-baas'!F:F, 0)) -> FALSE | K63: =IFERROR(INDEX('globales-baas'!G:G, MATCH(F63,'globales-baas'!F:F, 0)), "") | L63: =ISNUMBER(MATCH(F63,'globales-bff'!F:F, 0)) -> FALSE | M63: =IFERROR(INDEX('globales-bff'!G:G, MATCH(F63,'globales-bff'!F:F, 0)), "")
A64: ms-bff-onfido-webhook | B64: http://repos.bancsabadell.com/bitbucket/rest/api/1.0/projects/MOBI/repos/ms-bff-onfido-webhook-conf/browse/pro/configs/application.yaml?at=release/0.2.2 | C64: 404 | D64: release/0.2.2 | E64: 404 | H64: =ISNUMBER(MATCH(F64,'globales-sys'!F:F, 0)) -> FALSE | I64: =IFERROR(INDEX('globales-sys'!G:G, MATCH(F64,'globales-sys'!F:F, 0)), "") | J64: =ISNUMBER(MATCH(F64,'globales-baas'!F:F, 0)) -> FALSE | K64: =IFERROR(INDEX('globales-baas'!G:G, MATCH(F64,'globales-baas'!F:F, 0)), "") | L64: =ISNUMBER(MATCH(F64,'globales-bff'!F:F, 0)) -> FALSE | M64: =IFERROR(INDEX('globales-bff'!G:G, MATCH(F64,'globales-bff'!F:F, 0)), "")
A65: ms-bff-transaction-authorization-bd | B65: http://repos.bancsabadell.com/bitbucket/rest/api/1.0/projects/P4CP/repos/ms-bff-transaction-authorization-bd-conf/browse/pro/configs/application.yaml?at=release/0.1.5 | C65: 404 | D65: release/0.1.5 | E65: 404 | H65: =ISNUMBER(MATCH(F65,'globales-sys'!F:F, 0)) -> FALSE | I65: =IFERROR(INDEX('globales-sys'!G:G, MATCH(F65,'globales-sys'!F:F, 0)), "") | J65: =ISNUMBER(MATCH(F65,'globales-baas'!F:F, 0)) -> FALSE | K65: =IFERROR(INDEX('globales-baas'!G:G, MATCH(F65,'globales-baas'!F:F, 0)), "") | L65: =ISNUMBER(MATCH(F65,'globales-bff'!F:F, 0)) -> FALSE | M65: =IFERROR(INDEX('globales-bff'!G:G, MATCH(F65,'globales-bff'!F:F, 0)), "")
A66: ms-baas-onboarding | B66: http://repos.bancsabadell.com/bitbucket/rest/api/1.0/projects/P4CP/repos/ms-baas-onboarding-conf/browse/pro/configs/application.yaml?at=release/0.13.1 | C66: 404 | D66: release/0.13.1 | E66: 404 | H66: =ISNUMBER(MATCH(F66,'globales-sys'!F:F, 0)) -> FALSE | I66: =IFERROR(INDEX('globales-sys'!G:G, MATCH(F66,'globales-sys'!F:F, 0)), "") | J66: =ISNUMBER(MATCH(F66,'globales-baas'!F:F, 0)) -> FALSE | K66: =IFERROR(INDEX('globales-baas'!G:G, MATCH(F66,'globales-baas'!F:F, 0)), "") | L66: =ISNUMBER(MATCH(F66,'globales-bff'!F:F, 0)) -> FALSE | M66: =IFERROR(INDEX('globales-bff'!G:G, MATCH(F66,'globales-bff'!F:F, 0)), "")
A67: ms-bff-onboarding | B67: http://repos.bancsabadell.com/bitbucket/rest/api/1.0/projects/P4CP/repos/ms-bff-onboarding-conf/browse/pro/configs/application.yaml?at=release/0.7.0 | C67: 404 | D67: release/0.7.0 | E67: 404 | H67: =ISNUMBER(MATCH(F67,'globales-sys'!F:F, 0)) -> FALSE | I67: =IFERROR(INDEX('globales-sys'!G:G, MATCH(F67,'globales-sys'!F:F, 0)), "") | J67: =ISNUMBER(MATCH(F67,'globales-baas'!F:F, 0)) -> FALSE | K67: =IFERROR(INDEX('globales-baas'!G:G, MATCH(F67,'globales-baas'!F:F, 0)), "") | L67: =ISNUMBER(MATCH(F67,'globales-bff'!F:F, 0)) -> FALSE | M67: =IFERROR(INDEX('globales-bff'!G:G, MATCH(F67,'globales-bff'!F:F, 0)), "")
A68: ms-bff-cards-dds-v1 | B68: http://repos.bancsabadell.com/bitbucket/rest/api/1.0/projects/mobi/repos/ms-bff-cards-dds-v1-conf/browse/pro/configs/application.yaml?at=release/1.1.18 | C68: 200 | D68: release/1.1.18 | E68: OK | F68: proteo4.web-client.services[0].base-url | G68: https://microsapi.es.bs/digital | H68: =ISNUMBER(MATCH(F68,'globales-sys'!F:F, 0)) -> FALSE | I68: =IFERROR(INDEX('globales-sys'!G:G, MATCH(F68,'globales-sys'!F:F, 0)), "") | J68: =ISNUMBER(MATCH(F68,'globales-baas'!F:F, 0)) -> FALSE | K68: =IFERROR(INDEX('globales-baas'!G:G, MATCH(F68,'globales-baas'!F:F, 0)), "") | L68: =ISNUMBER(MATCH(F68,'globales-bff'!F:F, 0)) -> FALSE | M68: =IFERROR(INDEX('globales-bff'!G:G, MATCH(F68,'globales-bff'!F:F, 0)), "")
A69: ms-bff-cards-dds-v1 | B69: http://repos.bancsabadell.com/bitbucket/rest/api/1.0/projects/mobi/repos/ms-bff-cards-dds-v1-conf/browse/pro/configs/application.yaml?at=release/1.1.18 | C69: 200 | D69: release/1.1.18 | E69: OK | F69: proteo4.web-client.services[1].base-url | G69: https://microsapi.es.bs/digital/party-authentication/v3 | H69: =ISNUMBER(MATCH(F69,'globales-sys'!F:F, 0)) -> FALSE | I69: =IFERROR(INDEX('globales-sys'!G:G, MATCH(F69,'globales-sys'!F:F, 0)), "") | J69: =ISNUMBER(MATCH(F69,'globales-baas'!F:F, 0)) -> FALSE | K69: =IFERROR(INDEX('globales-baas'!G:G, MATCH(F69,'globales-baas'!F:F, 0)), "") | L69: =ISNUMBER(MATCH(F69,'globales-bff'!F:F, 0)) -> FALSE | M69: =IFERROR(INDEX('globales-bff'!G:G, MATCH(F69,'globales-bff'!F:F, 0)), "")
A70: ms-bff-cards-dds-v1 | B70: http://repos.bancsabadell.com/bitbucket/rest/api/1.0/projects/mobi/repos/ms-bff-cards-dds-v1-conf/browse/pro/configs/application.yaml?at=release/1.1.18 | C70: 200 | D70: release/1.1.18 | E70: OK | F70: proteo4.web-client.services[2].base-url | G70: https://microsapi.es.bs/digital | H70: =ISNUMBER(MATCH(F70,'globales-sys'!F:F, 0)) -> FALSE | I70: =IFERROR(INDEX('globales-sys'!G:G, MATCH(F70,'globales-sys'!F:F, 0)), "") | J70: =ISNUMBER(MATCH(F70,'globales-baas'!F:F, 0)) -> FALSE | K70: =IFERROR(INDEX('globales-baas'!G:G, MATCH(F70,'globales-baas'!F:F, 0)), "") | L70: =ISNUMBER(MATCH(F70,'globales-bff'!F:F, 0)) -> FALSE | M70: =IFERROR(INDEX('globales-bff'!G:G, MATCH(F70,'globales-bff'!F:F, 0)), "")
A71: ms-bff-cards-dds-v1 | B71: http://repos.bancsabadell.com/bitbucket/rest/api/1.0/projects/mobi/repos/ms-bff-cards-dds-v1-conf/browse/pro/configs/application.yaml?at=release/1.1.18 | C71: 200 | D71: release/1.1.18 | E71: OK | F71: proteo4.web-client.services[3].base-url | G71: https://microsapi.es.bs/digital | H71: =ISNUMBER(MATCH(F71,'globales-sys'!F:F, 0)) -> FALSE | I71: =IFERROR(INDEX('globales-sys'!G:G, MATCH(F71,'globales-sys'!F:F, 0)), "") | J71: =ISNUMBER(MATCH(F71,'globales-baas'!F:F, 0)) -> FALSE | K71: =IFERROR(INDEX('globales-baas'!G:G, MATCH(F71,'globales-baas'!F:F, 0)), "") | L71: =ISNUMBER(MATCH(F71,'globales-bff'!F:F, 0)) -> FALSE | M71: =IFERROR(INDEX('globales-bff'!G:G, MATCH(F71,'globales-bff'!F:F, 0)), "")
A72: ms-bff-cards-dds-v1 | B72: http://repos.bancsabadell.com/bitbucket/rest/api/1.0/projects/mobi/repos/ms-bff-cards-dds-v1-conf/browse/pro/configs/application.yaml?at=release/1.1.18 | C72: 200 | D72: release/1.1.18 | E72: OK | F72: proteo4.web-client.services[4].base-url | G72: https://microsapi.es.bs/digital | H72: =ISNUMBER(MATCH(F72,'globales-sys'!F:F, 0)) -> FALSE | I72: =IFERROR(INDEX('globales-sys'!G:G, MATCH(F72,'globales-sys'!F:F, 0)), "") | J72: =ISNUMBER(MATCH(F72,'globales-baas'!F:F, 0)) -> FALSE | K72: =IFERROR(INDEX('globales-baas'!G:G, MATCH(F72,'globales-baas'!F:F, 0)), "") | L72: =ISNUMBER(MATCH(F72,'globales-bff'!F:F, 0)) -> FALSE | M72: =IFERROR(INDEX('globales-bff'!G:G, MATCH(F72,'globales-bff'!F:F, 0)), "")
A73: ms-bff-cards-dds-v1 | B73: http://repos.bancsabadell.com/bitbucket/rest/api/1.0/projects/mobi/repos/ms-bff-cards-dds-v1-conf/browse/pro/configs/application.yaml?at=release/1.1.18 | C73: 200 | D73: release/1.1.18 | E73: OK | F73: proteo4.web-client.services[5].base-url | G73: https://microsapi.es.bs/digital | H73: =ISNUMBER(MATCH(F73,'globales-sys'!F:F, 0)) -> FALSE | I73: =IFERROR(INDEX('globales-sys'!G:G, MATCH(F73,'globales-sys'!F:F, 0)), "") | J73: =ISNUMBER(MATCH(F73,'globales-baas'!F:F, 0)) -> FALSE | K73: =IFERROR(INDEX('globales-baas'!G:G, MATCH(F73,'globales-baas'!F:F, 0)), "") | L73: =ISNUMBER(MATCH(F73,'globales-bff'!F:F, 0)) -> FALSE | M73: =IFERROR(INDEX('globales-bff'!G:G, MATCH(F73,'globales-bff'!F:F, 0)), "")
A74: ms-bff-cards-dds-v1 | B74: http://repos.bancsabadell.com/bitbucket/rest/api/1.0/projects/mobi/repos/ms-bff-cards-dds-v1-conf/browse/pro/configs/application.yaml?at=release/1.1.18 | C74: 200 | D74: release/1.1.18 | E74: OK | F74: proteo4.web-client.services[6].base-url | G74: https://microsapi.es.bs/digital | H74: =ISNUMBER(MATCH(F74,'globales-sys'!F:F, 0)) -> FALSE | I74: =IFERROR(INDEX('globales-sys'!G:G, MATCH(F74,'globales-sys'!F:F, 0)), "") | J74: =ISNUMBER(MATCH(F74,'globales-baas'!F:F, 0)) -> FALSE | K74: =IFERROR(INDEX('globales-baas'!G:G, MATCH(F74,'globales-baas'!F:F, 0)), "") | L74: =ISNUMBER(MATCH(F74,'globales-bff'!F:F, 0)) -> FALSE | M74: =IFERROR(INDEX('globales-bff'!G:G, MATCH(F74,'globales-bff'!F:F, 0)), "")
A75: ms-bff-correspondence-v3 | B75: http://repos.bancsabadell.com/bitbucket/rest/api/1.0/projects/P4CP/repos/ms-bff-correspondence-v3-conf/browse/pro/configs/application.yaml?at=release/1.1.9 | C75: 404 | D75: release/1.1.9 | E75: 404 | H75: =ISNUMBER(MATCH(F75,'globales-sys'!F:F, 0)) -> FALSE | I75: =IFERROR(INDEX('globales-sys'!G:G, MATCH(F75,'globales-sys'!F:F, 0)), "") | J75: =ISNUMBER(MATCH(F75,'globales-baas'!F:F, 0)) -> FALSE | K75: =IFERROR(INDEX('globales-baas'!G:G, MATCH(F75,'globales-baas'!F:F, 0)), "") | L75: =ISNUMBER(MATCH(F75,'globales-bff'!F:F, 0)) -> FALSE | M75: =IFERROR(INDEX('globales-bff'!G:G, MATCH(F75,'globales-bff'!F:F, 0)), "")
A76: ms-sys-customer-relationship-management-ags | B76: http://repos.bancsabadell.com/bitbucket/rest/api/1.0/projects/P4CP/repos/ms-sys-customer-relationship-management-ags-conf/browse/pro/configs/application.yaml?at=release/1.1.4 | C76: 200 | D76: release/1.1.4 | E76: OK | F76: proteo4.security.access-token.validation.signature.jwks-uri | G76: https://ms-infra-security-jwt-pro-ns-inf.apps.pro.aws.bancsabadell.com/jwt/jwk_uri | H76: =ISNUMBER(MATCH(F76,'globales-sys'!F:F, 0)) -> TRUE | I76: =IFERROR(INDEX('globales-sys'!G:G, MATCH(F76,'globales-sys'!F:F, 0)), "") -> https://ms-infra-security-jwt-pro-ns-inf.${PROVIDER_SUFFIX_URL:apps.pro.aws.bancsabadell.com}/jwt/jwk_uri | J76: =ISNUMBER(MATCH(F76,'globales-baas'!F:F, 0)) -> TRUE | K76: =IFERROR(INDEX('globales-baas'!G:G, MATCH(F76,'globales-baas'!F:F, 0)), "") -> https://ms-infra-security-jwt-pro-ns-inf.${PROVIDER_SUFFIX_URL:apps.pro.aws.bancsabadell.com}/jwt/jwk_uri | L76: =ISNUMBER(MATCH(F76,'globales-bff'!F:F, 0)) -> TRUE | M76: =IFERROR(INDEX('globales-bff'!G:G, MATCH(F76,'globales-bff'!F:F, 0)), "") -> https://ms-infra-security-jwt-pro-ns-inf.${PROVIDER_SUFFIX_URL:apps.pro.aws.bancsabadell.com}/jwt/jwk_uri
A77: ms-sys-customer-relationship-management-ags | B77: http://repos.bancsabadell.com/bitbucket/rest/api/1.0/projects/P4CP/repos/ms-sys-customer-relationship-management-ags-conf/browse/pro/configs/application.yaml?at=release/1.1.4 | C77: 200 | D77: release/1.1.4 | E77: OK | F77: proteo4.error-literal.baseUrl | G77: https://ms-infra-literal-adapter-pro-ns-inf.apps.pro.aws.bancsabadell.com | H77: =ISNUMBER(MATCH(F77,'globales-sys'!F:F, 0)) -> FALSE | I77: =IFERROR(INDEX('globales-sys'!G:G, MATCH(F77,'globales-sys'!F:F, 0)), "") | J77: =ISNUMBER(MATCH(F77,'globales-baas'!F:F, 0)) -> FALSE | K77: =IFERROR(INDEX('globales-baas'!G:G, MATCH(F77,'globales-baas'!F:F, 0)), "") | L77: =ISNUMBER(MATCH(F77,'globales-bff'!F:F, 0)) -> FALSE | M77: =IFERROR(INDEX('globales-bff'!G:G, MATCH(F77,'globales-bff'!F:F, 0)), "")
A78: ms-sys-customer-relationship-management-ags | B78: http://repos.bancsabadell.com/bitbucket/rest/api/1.0/projects/P4CP/repos/ms-sys-customer-relationship-management-ags-conf/browse/pro/configs/application.yaml?at=release/1.1.4 | C78: 200 | D78: release/1.1.4 | E78: OK | F78: proteo4.mainframe-adapter.base-url | G78: https://ms-infra-mainframe-adapter-pro-ns-inf.apps.pro.aws.bancsabadell.com | H78: =ISNUMBER(MATCH(F78,'globales-sys'!F:F, 0)) -> TRUE | I78: =IFERROR(INDEX('globales-sys'!G:G, MATCH(F78,'globales-sys'!F:F, 0)), "") -> https://ms-infra-mainframe-adapter-pro-ns-inf.${PROVIDER_SUFFIX_URL:apps.pro.aws.bancsabadell.com} | J78: =ISNUMBER(MATCH(F78,'globales-baas'!F:F, 0)) -> FALSE | K78: =IFERROR(INDEX('globales-baas'!G:G, MATCH(F78,'globales-baas'!F:F, 0)), "") | L78: =ISNUMBER(MATCH(F78,'globales-bff'!F:F, 0)) -> FALSE | M78: =IFERROR(INDEX('globales-bff'!G:G, MATCH(F78,'globales-bff'!F:F, 0)), "")
A79: ms-sys-customer-relationship-management-ags | B79: http://repos.bancsabadell.com/bitbucket/rest/api/1.0/projects/P4CP/repos/ms-sys-customer-relationship-management-ags-conf/browse/pro/configs/application.yaml?at=release/1.1.4 | C79: 200 | D79: release/1.1.4 | E79: OK | F79: application.loan-centralizacion-service.base-url | G79: http://services.proteo.bancsabadell.com/soa/service/centralizacionenvios/centralizacion/CentralizacionService | H79: =ISNUMBER(MATCH(F79,'globales-sys'!F:F, 0)) -> FALSE | I79: =IFERROR(INDEX('globales-sys'!G:G, MATCH(F79,'globales-sys'!F:F, 0)), "") | J79: =ISNUMBER(MATCH(F79,'globales-baas'!F:F, 0)) -> FALSE | K79: =IFERROR(INDEX('globales-baas'!G:G, MATCH(F79,'globales-baas'!F:F, 0)), "") | L79: =ISNUMBER(MATCH(F79,'globales-bff'!F:F, 0)) -> FALSE | M79: =IFERROR(INDEX('globales-bff'!G:G, MATCH(F79,'globales-bff'!F:F, 0)), "")
A80: ms-sys-merchant-acquiring-facility-system-ta-v1 | B80: http://repos.bancsabadell.com/bitbucket/rest/api/1.0/projects/P4CP/repos/ms-sys-merchant-acquiring-facility-system-ta-v1-conf/browse/pro/configs/application.yaml?at=release/1.0.8 | C80: 200 | D80: release/1.0.8 | E80: OK | F80: snowdrop.uri | G80: https://europe-west2.snowdrop-mrs.com/api/v3/merchant | H80: =ISNUMBER(MATCH(F80,'globales-sys'!F:F, 0)) -> FALSE | I80: =IFERROR(INDEX('globales-sys'!G:G, MATCH(F80,'globales-sys'!F:F, 0)), "") | J80: =ISNUMBER(MATCH(F80,'globales-baas'!F:F, 0)) -> FALSE | K80: =IFERROR(INDEX('globales-baas'!G:G, MATCH(F80,'globales-baas'!F:F, 0)), "") | L80: =ISNUMBER(MATCH(F80,'globales-bff'!F:F, 0)) -> FALSE | M80: =IFERROR(INDEX('globales-bff'!G:G, MATCH(F80,'globales-bff'!F:F, 0)), "")
A81: ms-sys-icaap-irrbb | B81: http://repos.bancsabadell.com/bitbucket/rest/api/1.0/projects/ESSABICAAPIRRBB/repos/ms-sys-icaap-irrbb-conf/browse/pro/configs/application.yaml?at=release/1.0.2 | C81: 200 | D81: release/1.0.2 | E81: OK | F81: proteo4.security-initializer.client-credentials.partners.openam.base-url | G81: https://pro-openam-elb.pro.p4es.aws.bancsabadell.com:8443/o | H81: =ISNUMBER(MATCH(F81,'globales-sys'!F:F, 0)) -> TRUE | I81: =IFERROR(INDEX('globales-sys'!G:G, MATCH(F81,'globales-sys'!F:F, 0)), "") -> https://pro-openam-elb.pro.p4es.aws.bancsabadell.com:8443/o | J81: =ISNUMBER(MATCH(F81,'globales-baas'!F:F, 0)) -> TRUE | K81: =IFERROR(INDEX('globales-baas'!G:G, MATCH(F81,'globales-baas'!F:F, 0)), "") -> https://pro-openam-elb.pro.p4es.aws.bancsabadell.com:8443/o | L81: =ISNUMBER(MATCH(F81,'globales-bff'!F:F, 0)) -> FALSE | M81: =IFERROR(INDEX('globales-bff'!G:G, MATCH(F81,'globales-bff'!F:F, 0)), "")
A82: ms-sys-icaap-irrbb | B82: http://repos.bancsabadell.com/bitbucket/rest/api/1.0/projects/ESSABICAAPIRRBB/repos/ms-sys-icaap-irrbb-conf/browse/pro/configs/application.yaml?at=release/1.0.2 | C82: 200 | D82: release/1.0.2 | E82: OK | F82: proteo4.events.kafka.registry.url | G82: https://schemaregistry.apps.pro.aws.bancsabadell.com | H82: =ISNUMBER(MATCH(F82,'globales-sys'!F:F, 0)) -> FALSE | I82: =IFERROR(INDEX('globales-sys'!G:G, MATCH(F82,'globales-sys'!F:F, 0)), "") | J82: =ISNUMBER(MATCH(F82,'globales-baas'!F:F, 0)) -> FALSE | K82: =IFERROR(INDEX('globales-baas'!G:G, MATCH(F82,'globales-baas'!F:F, 0)), "") | L82: =ISNUMBER(MATCH(F82,'globales-bff'!F:F, 0)) -> FALSE | M82: =IFERROR(INDEX('globales-bff'!G:G, MATCH(F82,'globales-bff'!F:F, 0)), "")
A83: ms-sys-icaap-irrbb | B83: http://repos.bancsabadell.com/bitbucket/rest/api/1.0/projects/ESSABICAAPIRRBB/repos/ms-sys-icaap-irrbb-conf/browse/pro/configs/application.yaml?at=release/1.0.2 | C83: 200 | D83: release/1.0.2 | E83: OK | F83: fss.base-url | G83: https://ms-storage-api-pro-ns-inf.apps.pro.aws.bancsabadell.com/private-document-library-storage/v1 | H83: =ISNUMBER(MATCH(F83,'globales-sys'!F:F, 0)) -> FALSE | I83: =IFERROR(INDEX('globales-sys'!G:G, MATCH(F83,'globales-sys'!F:F, 0)), "") | J83: =ISNUMBER(MATCH(F83,'globales-baas'!F:F, 0)) -> FALSE | K83: =IFERROR(INDEX('globales-baas'!G:G, MATCH(F83,'globales-baas'!F:F, 0)), "") | L83: =ISNUMBER(MATCH(F83,'globales-bff'!F:F, 0)) -> FALSE | M83: =IFERROR(INDEX('globales-bff'!G:G, MATCH(F83,'globales-bff'!F:F, 0)), "")
A84: ms-baas-channel-activity-history | B84: http://repos.bancsabadell.com/bitbucket/rest/api/1.0/projects/P4CP/repos/ms-baas-channel-activity-history-conf/browse/pro/configs/application.yaml?at=release/1.0.1 | C84: 404 | D84: release/1.0.1 | E84: 404 | H84: =ISNUMBER(MATCH(F84,'globales-sys'!F:F, 0)) -> FALSE | I84: =IFERROR(INDEX('globales-sys'!G:G, MATCH(F84,'globales-sys'!F:F, 0)), "") | J84: =ISNUMBER(MATCH(F84,'globales-baas'!F:F, 0)) -> FALSE | K84: =IFERROR(INDEX('globales-baas'!G:G, MATCH(F84,'globales-baas'!F:F, 0)), "") | L84: =ISNUMBER(MATCH(F84,'globales-bff'!F:F, 0)) -> FALSE | M84: =IFERROR(INDEX('globales-bff'!G:G, MATCH(F84,'globales-bff'!F:F, 0)), "")
A85: ms-baas-customer-relationship-management | B85: http://repos.bancsabadell.com/bitbucket/rest/api/1.0/projects/p4cp/repos/ms-baas-customer-relationship-management-conf/browse/pro/configs/application.yaml?at=release/1.0.4 | C85: 404 | D85: release/1.0.4 | E85: 404 | H85: =ISNUMBER(MATCH(F85,'globales-sys'!F:F, 0)) -> FALSE | I85: =IFERROR(INDEX('globales-sys'!G:G, MATCH(F85,'globales-sys'!F:F, 0)), "") | J85: =ISNUMBER(MATCH(F85,'globales-baas'!F:F, 0)) -> FALSE | K85: =IFERROR(INDEX('globales-baas'!G:G, MATCH(F85,'globales-baas'!F:F, 0)), "") | L85: =ISNUMBER(MATCH(F85,'globales-bff'!F:F, 0)) -> FALSE | M85: =IFERROR(INDEX('globales-bff'!G:G, MATCH(F85,'globales-bff'!F:F, 0)), "")
A86: ms-baas-appointment-reference-data | B86: http://repos.bancsabadell.com/bitbucket/rest/api/1.0/projects/P4CP/repos/ms-baas-appointment-reference-data-conf/browse/pro/configs/application.yaml?at=release/1.0.4 | C86: 404 | D86: release/1.0.4 | E86: 404 | H86: =ISNUMBER(MATCH(F86,'globales-sys'!F:F, 0)) -> FALSE | I86: =IFERROR(INDEX('globales-sys'!G:G, MATCH(F86,'globales-sys'!F:F, 0)), "") | J86: =ISNUMBER(MATCH(F86,'globales-baas'!F:F, 0)) -> FALSE | K86: =IFERROR(INDEX('globales-baas'!G:G, MATCH(F86,'globales-baas'!F:F, 0)), "") | L86: =ISNUMBER(MATCH(F86,'globales-bff'!F:F, 0)) -> FALSE | M86: =IFERROR(INDEX('globales-bff'!G:G, MATCH(F86,'globales-bff'!F:F, 0)), "")
A87: ms-sys-customer-relationship-management-app-v1 | B87: http://repos.bancsabadell.com/bitbucket/rest/api/1.0/projects/MOBI/repos/ms-sys-customer-relationship-management-app-v1-conf/browse/pro/configs/application.yaml?at=release/1.2.2 | C87: 200 | D87: release/1.2.2 | E87: OK | F87: external.services[0].base-url | G87: http://gto.pro.onpremise.bancsabadell.com:12928 | H87: =ISNUMBER(MATCH(F87,'globales-sys'!F:F, 0)) -> FALSE | I87: =IFERROR(INDEX('globales-sys'!G:G, MATCH(F87,'globales-sys'!F:F, 0)), "") | J87: =ISNUMBER(MATCH(F87,'globales-baas'!F:F, 0)) -> FALSE | K87: =IFERROR(INDEX('globales-baas'!G:G, MATCH(F87,'globales-baas'!F:F, 0)), "") | L87: =ISNUMBER(MATCH(F87,'globales-bff'!F:F, 0)) -> FALSE | M87: =IFERROR(INDEX('globales-bff'!G:G, MATCH(F87,'globales-bff'!F:F, 0)), "")
A88: ms-baas-outsystems-notifications | B88: http://repos.bancsabadell.com/bitbucket/rest/api/1.0/projects/ESSABPHISHING/repos/ms-baas-outsystems-notifications-conf/browse/pro/configs/application.yaml?at=release/1.4.3 | C88: 200 | D88: release/1.4.3 | E88: OK | F88: endpoints.document-management.url | G88: https://ms-sys-document-manager-pro-ns-sys.apps.pro.aws.bancsabadell.com/ | H88: =ISNUMBER(MATCH(F88,'globales-sys'!F:F, 0)) -> FALSE | I88: =IFERROR(INDEX('globales-sys'!G:G, MATCH(F88,'globales-sys'!F:F, 0)), "") | J88: =ISNUMBER(MATCH(F88,'globales-baas'!F:F, 0)) -> FALSE | K88: =IFERROR(INDEX('globales-baas'!G:G, MATCH(F88,'globales-baas'!F:F, 0)), "") | L88: =ISNUMBER(MATCH(F88,'globales-bff'!F:F, 0)) -> FALSE | M88: =IFERROR(INDEX('globales-bff'!G:G, MATCH(F88,'globales-bff'!F:F, 0)), "")
A89: ms-baas-outsystems-notifications | B89: http://repos.bancsabadell.com/bitbucket/rest/api/1.0/projects/ESSABPHISHING/repos/ms-baas-outsystems-notifications-conf/browse/pro/configs/application.yaml?at=release/1.4.3 | C89: 200 | D89: release/1.4.3 | E89: OK | F89: proteo4.security.access-token.validation.signature.jwks-uri | G89: https://ms-infra-security-jwt-pro-ns-inf.apps.pro.aws.bancsabadell.com/jwt/jwk_uri | H89: =ISNUMBER(MATCH(F89,'globales-sys'!F:F, 0)) -> TRUE | I89: =IFERROR(INDEX('globales-sys'!G:G, MATCH(F89,'globales-sys'!F:F, 0)), "") -> https://ms-infra-security-jwt-pro-ns-inf.${PROVIDER_SUFFIX_URL:apps.pro.aws.bancsabadell.com}/jwt/jwk_uri | J89: =ISNUMBER(MATCH(F89,'globales-baas'!F:F, 0)) -> TRUE | K89: =IFERROR(INDEX('globales-baas'!G:G, MATCH(F89,'globales-baas'!F:F, 0)), "") -> https://ms-infra-security-jwt-pro-ns-inf.${PROVIDER_SUFFIX_URL:apps.pro.aws.bancsabadell.com}/jwt/jwk_uri | L89: =ISNUMBER(MATCH(F89,'globales-bff'!F:F, 0)) -> TRUE | M89: =IFERROR(INDEX('globales-bff'!G:G, MATCH(F89,'globales-bff'!F:F, 0)), "") -> https://ms-infra-security-jwt-pro-ns-inf.${PROVIDER_SUFFIX_URL:apps.pro.aws.bancsabadell.com}/jwt/jwk_uri
A90: ms-baas-outsystems-notifications | B90: http://repos.bancsabadell.com/bitbucket/rest/api/1.0/projects/ESSABPHISHING/repos/ms-baas-outsystems-notifications-conf/browse/pro/configs/application.yaml?at=release/1.4.3 | C90: 200 | D90: release/1.4.3 | E90: OK | F90: proteo4.domain-client.services[0].base-url | G90: https://ms-sys-document-manager-pro-ns-sys.apps.pro.aws.bancsabadell.com | H90: =ISNUMBER(MATCH(F90,'globales-sys'!F:F, 0)) -> FALSE | I90: =IFERROR(INDEX('globales-sys'!G:G, MATCH(F90,'globales-sys'!F:F, 0)), "") | J90: =ISNUMBER(MATCH(F90,'globales-baas'!F:F, 0)) -> FALSE | K90: =IFERROR(INDEX('globales-baas'!G:G, MATCH(F90,'globales-baas'!F:F, 0)), "") | L90: =ISNUMBER(MATCH(F90,'globales-bff'!F:F, 0)) -> FALSE | M90: =IFERROR(INDEX('globales-bff'!G:G, MATCH(F90,'globales-bff'!F:F, 0)), "")
A91: ms-baas-outsystems-notifications | B91: http://repos.bancsabadell.com/bitbucket/rest/api/1.0/projects/ESSABPHISHING/repos/ms-baas-outsystems-notifications-conf/browse/pro/configs/application.yaml?at=release/1.4.3 | C91: 200 | D91: release/1.4.3 | E91: OK | F91: proteo4.domain-client.services[1].base-url | G91: https://ms-sys-notifications-pro-ns-sys.apps.pro.aws.bancsabadell.com | H91: =ISNUMBER(MATCH(F91,'globales-sys'!F:F, 0)) -> FALSE | I91: =IFERROR(INDEX('globales-sys'!G:G, MATCH(F91,'globales-sys'!F:F, 0)), "") | J91: =ISNUMBER(MATCH(F91,'globales-baas'!F:F, 0)) -> FALSE | K91: =IFERROR(INDEX('globales-baas'!G:G, MATCH(F91,'globales-baas'!F:F, 0)), "") | L91: =ISNUMBER(MATCH(F91,'globales-bff'!F:F, 0)) -> FALSE | M91: =IFERROR(INDEX('globales-bff'!G:G, MATCH(F91,'globales-bff'!F:F, 0)), "")
A92: ms-baas-outsystems-notifications | B92: http://repos.bancsabadell.com/bitbucket/rest/api/1.0/projects/ESSABPHISHING/repos/ms-baas-outsystems-notifications-conf/browse/pro/configs/application.yaml?at=release/1.4.3 | C92: 200 | D92: release/1.4.3 | E92: OK | F92: proteo4.domain-client.services[2].base-url | G92: https://ms-sys-corporate-directory-pro-ns-sys.apps.pro.aws.bancsabadell.com | H92: =ISNUMBER(MATCH(F92,'globales-sys'!F:F, 0)) -> FALSE | I92: =IFERROR(INDEX('globales-sys'!G:G, MATCH(F92,'globales-sys'!F:F, 0)), "") | J92: =ISNUMBER(MATCH(F92,'globales-baas'!F:F, 0)) -> FALSE | K92: =IFERROR(INDEX('globales-baas'!G:G, MATCH(F92,'globales-baas'!F:F, 0)), "") | L92: =ISNUMBER(MATCH(F92,'globales-bff'!F:F, 0)) -> FALSE | M92: =IFERROR(INDEX('globales-bff'!G:G, MATCH(F92,'globales-bff'!F:F, 0)), "")
A93: ms-baas-outsystems-notifications | B93: http://repos.bancsabadell.com/bitbucket/rest/api/1.0/projects/ESSABPHISHING/repos/ms-baas-outsystems-notifications-conf/browse/pro/configs/application.yaml?at=release/1.4.3 | C93: 200 | D93: release/1.4.3 | E93: OK | F93: proteo4.domain-client.services[3].base-url | G93: https://ms-sys-er-minorista-ex-pro-ns-sys.apps.pro.aws.bancsabadell.com | H93: =ISNUMBER(MATCH(F93,'globales-sys'!F:F, 0)) -> FALSE | I93: =IFERROR(INDEX('globales-sys'!G:G, MATCH(F93,'globales-sys'!F:F, 0)), "") | J93: =ISNUMBER(MATCH(F93,'globales-baas'!F:F, 0)) -> FALSE | K93: =IFERROR(INDEX('globales-baas'!G:G, MATCH(F93,'globales-baas'!F:F, 0)), "") | L93: =ISNUMBER(MATCH(F93,'globales-bff'!F:F, 0)) -> FALSE | M93: =IFERROR(INDEX('globales-bff'!G:G, MATCH(F93,'globales-bff'!F:F, 0)), "")
A94: ms-baas-outsystems-notifications | B94: http://repos.bancsabadell.com/bitbucket/rest/api/1.0/projects/ESSABPHISHING/repos/ms-baas-outsystems-notifications-conf/browse/pro/configs/application.yaml?at=release/1.4.3 | C94: 200 | D94: release/1.4.3 | E94: OK | F94: proteo4.domain-client.services[4].base-url | G94: https://ms-sys-legal-entity-directory-pe-v1-pro-ns-sys.apps.pro.aws.bancsabadell.com | H94: =ISNUMBER(MATCH(F94,'globales-sys'!F:F, 0)) -> FALSE | I94: =IFERROR(INDEX('globales-sys'!G:G, MATCH(F94,'globales-sys'!F:F, 0)), "") | J94: =ISNUMBER(MATCH(F94,'globales-baas'!F:F, 0)) -> FALSE | K94: =IFERROR(INDEX('globales-baas'!G:G, MATCH(F94,'globales-baas'!F:F, 0)), "") | L94: =ISNUMBER(MATCH(F94,'globales-bff'!F:F, 0)) -> FALSE | M94: =IFERROR(INDEX('globales-bff'!G:G, MATCH(F94,'globales-bff'!F:F, 0)), "")
A95: ms-baas-outsystems-notifications | B95: http://repos.bancsabadell.com/bitbucket/rest/api/1.0/projects/ESSABPHISHING/repos/ms-baas-outsystems-notifications-conf/browse/pro/configs/application.yaml?at=release/1.4.3 | C95: 200 | D95: release/1.4.3 | E95: OK | F95: proteo4.domain-client.services[5].base-url | G95: https://ms-sys-xy-common-data-pro-ns-sys.apps.pro.aws.bancsabadell.com | H95: =ISNUMBER(MATCH(F95,'globales-sys'!F:F, 0)) -> FALSE | I95: =IFERROR(INDEX('globales-sys'!G:G, MATCH(F95,'globales-sys'!F:F, 0)), "") | J95: =ISNUMBER(MATCH(F95,'globales-baas'!F:F, 0)) -> FALSE | K95: =IFERROR(INDEX('globales-baas'!G:G, MATCH(F95,'globales-baas'!F:F, 0)), "") | L95: =ISNUMBER(MATCH(F95,'globales-bff'!F:F, 0)) -> FALSE | M95: =IFERROR(INDEX('globales-bff'!G:G, MATCH(F95,'globales-bff'!F:F, 0)), "")
A96: ms-baas-outsystems-notifications | B96: http://repos.bancsabadell.com/bitbucket/rest/api/1.0/projects/ESSABPHISHING/repos/ms-baas-outsystems-notifications-conf/browse/pro/configs/application.yaml?at=release/1.4.3 | C96: 200 | D96: release/1.4.3 | E96: OK | F96: proteo4.domain-client.services[6].base-url | G96: https://ms-sys-public-reference-data-system-bp-v1-pro-ns-sys.apps.pro.aws.bancsabadell.com | H96: =ISNUMBER(MATCH(F96,'globales-sys'!F:F, 0)) -> FALSE | I96: =IFERROR(INDEX('globales-sys'!G:G, MATCH(F96,'globales-sys'!F:F, 0)), "") | J96: =ISNUMBER(MATCH(F96,'globales-baas'!F:F, 0)) -> FALSE | K96: =IFERROR(INDEX('globales-baas'!G:G, MATCH(F96,'globales-baas'!F:F, 0)), "") | L96: =ISNUMBER(MATCH(F96,'globales-bff'!F:F, 0)) -> FALSE | M96: =IFERROR(INDEX('globales-bff'!G:G, MATCH(F96,'globales-bff'!F:F, 0)), "")
A97: ms-baas-outsystems-notifications | B97: http://repos.bancsabadell.com/bitbucket/rest/api/1.0/projects/ESSABPHISHING/repos/ms-baas-outsystems-notifications-conf/browse/pro/configs/application.yaml?at=release/1.4.3 | C97: 200 | D97: release/1.4.3 | E97: OK | F97: proteo4.domain-client.services[7].base-url | G97: https://ms-sys-doc-generator-pro-ns-sys.apps.pro.aws.bancsabadell.com | H97: =ISNUMBER(MATCH(F97,'globales-sys'!F:F, 0)) -> FALSE | I97: =IFERROR(INDEX('globales-sys'!G:G, MATCH(F97,'globales-sys'!F:F, 0)), "") | J97: =ISNUMBER(MATCH(F97,'globales-baas'!F:F, 0)) -> FALSE | K97: =IFERROR(INDEX('globales-baas'!G:G, MATCH(F97,'globales-baas'!F:F, 0)), "") | L97: =ISNUMBER(MATCH(F97,'globales-bff'!F:F, 0)) -> FALSE | M97: =IFERROR(INDEX('globales-bff'!G:G, MATCH(F97,'globales-bff'!F:F, 0)), "")
A98: ms-baas-outsystems-notifications | B98: http://repos.bancsabadell.com/bitbucket/rest/api/1.0/projects/ESSABPHISHING/repos/ms-baas-outsystems-notifications-conf/browse/pro/configs/application.yaml?at=release/1.4.3 | C98: 200 | D98: release/1.4.3 | E98: OK | F98: proteo4.domain-client.services[8].base-url | G98: https://ms-sys-sales-product-agreement-system-pe-v1-pro-ns-sys.apps.pro.aws.bancsabadell.com | H98: =ISNUMBER(MATCH(F98,'globales-sys'!F:F, 0)) -> FALSE | I98: =IFERROR(INDEX('globales-sys'!G:G, MATCH(F98,'globales-sys'!F:F, 0)), "") | J98: =ISNUMBER(MATCH(F98,'globales-baas'!F:F, 0)) -> FALSE | K98: =IFERROR(INDEX('globales-baas'!G:G, MATCH(F98,'globales-baas'!F:F, 0)), "") | L98: =ISNUMBER(MATCH(F98,'globales-bff'!F:F, 0)) -> FALSE | M98: =IFERROR(INDEX('globales-bff'!G:G, MATCH(F98,'globales-bff'!F:F, 0)), "")
A99: ms-baas-aeat2bs | B99: http://repos.bancsabadell.com/bitbucket/rest/api/1.0/projects/ESIC/repos/ms-baas-aeat2bs-conf/browse/pro/configs/application.yaml?at=release/1.1.2 | C99: 404 | D99: release/1.1.2 | E99: 404 | H99: =ISNUMBER(MATCH(F99,'globales-sys'!F:F, 0)) -> FALSE | I99: =IFERROR(INDEX('globales-sys'!G:G, MATCH(F99,'globales-sys'!F:F, 0)), "") | J99: =ISNUMBER(MATCH(F99,'globales-baas'!F:F, 0)) -> FALSE | K99: =IFERROR(INDEX('globales-baas'!G:G, MATCH(F99,'globales-baas'!F:F, 0)), "") | L99: =ISNUMBER(MATCH(F99,'globales-bff'!F:F, 0)) -> FALSE | M99: =IFERROR(INDEX('globales-bff'!G:G, MATCH(F99,'globales-bff'!F:F, 0)), "")
A100: ms-baas-bs2aeat | B100: http://repos.bancsabadell.com/bitbucket/rest/api/1.0/projects/ESIC/repos/ms-baas-bs2aeat-conf/browse/pro/configs/application.yaml?at=release/2.2.5 | C100: 404 | D100: release/2.2.5 | E100: 404 | H100: =ISNUMBER(MATCH(F100,'globales-sys'!F:F, 0)) -> FALSE | I100: =IFERROR(INDEX('globales-sys'!G:G, MATCH(F100,'globales-sys'!F:F, 0)), "") | J100: =ISNUMBER(MATCH(F100,'globales-baas'!F:F, 0)) -> FALSE | K100: =IFERROR(INDEX('globales-baas'!G:G, MATCH(F100,'globales-baas'!F:F, 0)), "") | L100: =ISNUMBER(MATCH(F100,'globales-bff'!F:F, 0)) -> FALSE | M100: =IFERROR(INDEX('globales-bff'!G:G, MATCH(F100,'globales-bff'!F:F, 0)), "")
...

Sheet globales-sys
A1: service | B1: url | C1: http_code | D1: branch | E1: status | F1: property_key | G1: property_value
A2: ns-sys-global-p4-micros-arch | B2: https://bitbucket.apps.devops.aws.bancsabadell.com/rest/api/1.0/projects/P4DES/repos/ns-sys-global-p4-micros-arch/browse/pro/configs/application.yaml?at=release/1.28.7 | C2: 200 | D2: release/1.28.7 | E2: OK | F2: management.endpoints.web.exposure.include | G2: info,health,prometheus
A3: ns-sys-global-p4-micros-arch | B3: https://bitbucket.apps.devops.aws.bancsabadell.com/rest/api/1.0/projects/P4DES/repos/ns-sys-global-p4-micros-arch/browse/pro/configs/application.yaml?at=release/1.28.7 | C3: 200 | D3: release/1.28.7 | E3: OK | F3: management.server.servlet.context-path | G3: /actuator
A4: ns-sys-global-p4-micros-arch | B4: https://bitbucket.apps.devops.aws.bancsabadell.com/rest/api/1.0/projects/P4DES/repos/ns-sys-global-p4-micros-arch/browse/pro/configs/application.yaml?at=release/1.28.7 | C4: 200 | D4: release/1.28.7 | E4: OK | F4: management.endpoint.health.show-details | G4: always
A5: ns-sys-global-p4-micros-arch | B5: https://bitbucket.apps.devops.aws.bancsabadell.com/rest/api/1.0/projects/P4DES/repos/ns-sys-global-p4-micros-arch/browse/pro/configs/application.yaml?at=release/1.28.7 | C5: 200 | D5: release/1.28.7 | E5: OK | F5: management.endpoint.health.show-components | G5: always
A6: ns-sys-global-p4-micros-arch | B6: https://bitbucket.apps.devops.aws.bancsabadell.com/rest/api/1.0/projects/P4DES/repos/ns-sys-global-p4-micros-arch/browse/pro/configs/application.yaml?at=release/1.28.7 | C6: 200 | D6: release/1.28.7 | E6: OK | F6: management.endpoint.health.group.readiness.include | G6: readinessState,warmup
A7: ns-sys-global-p4-micros-arch | B7: https://bitbucket.apps.devops.aws.bancsabadell.com/rest/api/1.0/projects/P4DES/repos/ns-sys-global-p4-micros-arch/browse/pro/configs/application.yaml?at=release/1.28.7 | C7: 200 | D7: release/1.28.7 | E7: OK | F7: management.health.probes.enabled | G7: True
A8: ns-sys-global-p4-micros-arch | B8: https://bitbucket.apps.devops.aws.bancsabadell.com/rest/api/1.0/projects/P4DES/repos/ns-sys-global-p4-micros-arch/browse/pro/configs/application.yaml?at=release/1.28.7 | C8: 200 | D8: release/1.28.7 | E8: OK | F8: server.port | G8: 8080
A9: ns-sys-global-p4-micros-arch | B9: https://bitbucket.apps.devops.aws.bancsabadell.com/rest/api/1.0/projects/P4DES/repos/ns-sys-global-p4-micros-arch/browse/pro/configs/application.yaml?at=release/1.28.7 | C9: 200 | D9: release/1.28.7 | E9: OK | F9: server.forward-headers-strategy | G9: NONE
A10: ns-sys-global-p4-micros-arch | B10: https://bitbucket.apps.devops.aws.bancsabadell.com/rest/api/1.0/projects/P4DES/repos/ns-sys-global-p4-micros-arch/browse/pro/configs/application.yaml?at=release/1.28.7 | C10: 200 | D10: release/1.28.7 | E10: OK | F10: server.max-http-header-size | G10: 15KB
A11: ns-sys-global-p4-micros-arch | B11: https://bitbucket.apps.devops.aws.bancsabadell.com/rest/api/1.0/projects/P4DES/repos/ns-sys-global-p4-micros-arch/browse/pro/configs/application.yaml?at=release/1.28.7 | C11: 200 | D11: release/1.28.7 | E11: OK | F11: proteo4.web-client.limit-max-in-memory-size | G11: 26214400
A12: ns-sys-global-p4-micros-arch | B12: https://bitbucket.apps.devops.aws.bancsabadell.com/rest/api/1.0/projects/P4DES/repos/ns-sys-global-p4-micros-arch/browse/pro/configs/application.yaml?at=release/1.28.7 | C12: 200 | D12: release/1.28.7 | E12: OK | F12: proteo4.web-client.propagated-headers[0] | G12: Authorization
A13: ns-sys-global-p4-micros-arch | B13: https://bitbucket.apps.devops.aws.bancsabadell.com/rest/api/1.0/projects/P4DES/repos/ns-sys-global-p4-micros-arch/browse/pro/configs/application.yaml?at=release/1.28.7 | C13: 200 | D13: release/1.28.7 | E13: OK | F13: proteo4.web-client.propagated-headers[1] | G13: Accept-Language
A14: ns-sys-global-p4-micros-arch | B14: https://bitbucket.apps.devops.aws.bancsabadell.com/rest/api/1.0/projects/P4DES/repos/ns-sys-global-p4-micros-arch/browse/pro/configs/application.yaml?at=release/1.28.7 | C14: 200 | D14: release/1.28.7 | E14: OK | F14: proteo4.web-client.propagated-headers[2] | G14: Cookie
A15: ns-sys-global-p4-micros-arch | B15: https://bitbucket.apps.devops.aws.bancsabadell.com/rest/api/1.0/projects/P4DES/repos/ns-sys-global-p4-micros-arch/browse/pro/configs/application.yaml?at=release/1.28.7 | C15: 200 | D15: release/1.28.7 | E15: OK | F15: proteo4.web-client.propagated-headers[3] | G15: Content-Language
A16: ns-sys-global-p4-micros-arch | B16: https://bitbucket.apps.devops.aws.bancsabadell.com/rest/api/1.0/projects/P4DES/repos/ns-sys-global-p4-micros-arch/browse/pro/configs/application.yaml?at=release/1.28.7 | C16: 200 | D16: release/1.28.7 | E16: OK | F16: proteo4.web-client.propagated-headers[4] | G16: User-Agent
A17: ns-sys-global-p4-micros-arch | B17: https://bitbucket.apps.devops.aws.bancsabadell.com/rest/api/1.0/projects/P4DES/repos/ns-sys-global-p4-micros-arch/browse/pro/configs/application.yaml?at=release/1.28.7 | C17: 200 | D17: release/1.28.7 | E17: OK | F17: proteo4.web-client.propagated-headers[5] | G17: x-instance-id
A18: ns-sys-global-p4-micros-arch | B18: https://bitbucket.apps.devops.aws.bancsabadell.com/rest/api/1.0/projects/P4DES/repos/ns-sys-global-p4-micros-arch/browse/pro/configs/application.yaml?at=release/1.28.7 | C18: 200 | D18: release/1.28.7 | E18: OK | F18: proteo4.web-client.propagated-headers[6] | G18: X-Forwarded-For
A19: ns-sys-global-p4-micros-arch | B19: https://bitbucket.apps.devops.aws.bancsabadell.com/rest/api/1.0/projects/P4DES/repos/ns-sys-global-p4-micros-arch/browse/pro/configs/application.yaml?at=release/1.28.7 | C19: 200 | D19: release/1.28.7 | E19: OK | F19: proteo4.web-client.propagated-headers[7] | G19: X-Auth
A20: ns-sys-global-p4-micros-arch | B20: https://bitbucket.apps.devops.aws.bancsabadell.com/rest/api/1.0/projects/P4DES/repos/ns-sys-global-p4-micros-arch/browse/pro/configs/application.yaml?at=release/1.28.7 | C20: 200 | D20: release/1.28.7 | E20: OK | F20: proteo4.web-client.propagated-headers[8] | G20: x-dynatrace-application
A21: ns-sys-global-p4-micros-arch | B21: https://bitbucket.apps.devops.aws.bancsabadell.com/rest/api/1.0/projects/P4DES/repos/ns-sys-global-p4-micros-arch/browse/pro/configs/application.yaml?at=release/1.28.7 | C21: 200 | D21: release/1.28.7 | E21: OK | F21: proteo4.web-client.propagated-headers[9] | G21: x-dynatrace-origin-url
A22: ns-sys-global-p4-micros-arch | B22: https://bitbucket.apps.devops.aws.bancsabadell.com/rest/api/1.0/projects/P4DES/repos/ns-sys-global-p4-micros-arch/browse/pro/configs/application.yaml?at=release/1.28.7 | C22: 200 | D22: release/1.28.7 | E22: OK | F22: proteo4.web-client.propagated-headers[10] | G22: x-dynatrace-requeststate
A23: ns-sys-global-p4-micros-arch | B23: https://bitbucket.apps.devops.aws.bancsabadell.com/rest/api/1.0/projects/P4DES/repos/ns-sys-global-p4-micros-arch/browse/pro/configs/application.yaml?at=release/1.28.7 | C23: 200 | D23: release/1.28.7 | E23: OK | F23: proteo4.web-client.propagated-headers[11] | G23: 25df5dad0a39ec8a6a36be8dcb9153806ca9691401dfb28bca8aab9d85fbd876
... A59: ns-sys-global-p4-micros-arch | B59: https://bitbucket.apps.devops.aws.bancsabadell.com/rest/api/1.0/projects/P4DES/repos/ns-sys-global-p4-micros-arch/browse/pro/configs/application.yaml?at=release/1.28.7 | C59: 200 | D59: release/1.28.7 | E59: OK | F59: proteo4.operations-log.appender.sqs.queue.endpoint | G59: https://sqs.eu-west-1.amazonaws.com/913536646623/proteo4-logoperational.fifo
A60: ns-sys-global-p4-micros-arch | B60: https://bitbucket.apps.devops.aws.bancsabadell.com/rest/api/1.0/projects/P4DES/repos/ns-sys-global-p4-micros-arch/browse/pro/configs/application.yaml?at=release/1.28.7 | C60: 200 | D60: release/1.28.7 | E60: OK | F60: proteo4.operations-log.appender.sqs.queue.timeout | G60: 5000
A61: ns-sys-global-p4-micros-arch | B61: https://bitbucket.apps.devops.aws.bancsabadell.com/rest/api/1.0/projects/P4DES/repos/ns-sys-global-p4-micros-arch/browse/pro/configs/application.yaml?at=release/1.28.7 | C61: 200 | D61: release/1.28.7 | E61: OK | F61: proteo4.operations-log.appender.sqs.queue.fifo.groupId | G61: groupIdPRO
A62: ns-sys-global-p4-micros-arch | B62: https://bitbucket.apps.devops.aws.bancsabadell.com/rest/api/1.0/projects/P4DES/repos/ns-sys-global-p4-micros-arch/browse/pro/configs/application.yaml?at=release/1.28.7 | C62: 200 | D62: release/1.28.7 | E62: OK | F62: proteo4.operations-log.appender.sqs.queue.fifo.groupCount | G62: 64000
A63: ns-sys-global-p4-micros-arch | B63: https://bitbucket.apps.devops.aws.bancsabadell.com/rest/api/1.0/projects/P4DES/repos/ns-sys-global-p4-micros-arch/browse/pro/configs/application.yaml?at=release/1.28.7 | C63: 200 | D63: release/1.28.7 | E63: OK | F63: proteo4.operations-log.appender.sqs.proxy.enabled | G63: ${PROVIDER_IS_OCP:false}
A64: ns-sys-global-p4-micros-arch | B64: https://bitbucket.apps.devops.aws.bancsabadell.com/rest/api/1.0/projects/P4DES/repos/ns-sys-global-p4-micros-arch/browse/pro/configs/application.yaml?at=release/1.28.7 | C64: 200 | D64: release/1.28.7 | E64: OK | F64: proteo4.operations-log.appender.sqs.proxy.hostname | G64: proxy.bancsabadell.com
A65: ns-sys-global-p4-micros-arch | B65: https://bitbucket.apps.devops.aws.bancsabadell.com/rest/api/1.0/projects/P4DES/repos/ns-sys-global-p4-micros-arch/browse/pro/configs/application.yaml?at=release/1.28.7 | C65: 200 | D65: release/1.28.7 | E65: OK | F65: proteo4.operations-log.appender.sqs.proxy.port | G65: 8080
A66: ns-sys-global-p4-micros-arch | B66: https://bitbucket.apps.devops.aws.bancsabadell.com/rest/api/1.0/projects/P4DES/repos/ns-sys-global-p4-micros-arch/browse/pro/configs/application.yaml?at=release/1.28.7 | C66: 200 | D66: release/1.28.7 | E66: OK | F66: proteo4.operations-log.appender.sqs.batch.enabled | G66: True
A67: ns-sys-global-p4-micros-arch | B67: https://bitbucket.apps.devops.aws.bancsabadell.com/rest/api/1.0/projects/P4DES/repos/ns-sys-global-p4-micros-arch/browse/pro/configs/application.yaml?at=release/1.28.7 | C67: 200 | D67: release/1.28.7 | E67: OK | F67: proteo4.operations-log.appender.sqs.batch.maxBatchOpenMs | G67: 200
A68: ns-sys-global-p4-micros-arch | B68: https://bitbucket.apps.devops.aws.bancsabadell.com/rest/api/1.0/projects/P4DES/repos/ns-sys-global-p4-micros-arch/browse/pro/configs/application.yaml?at=release/1.28.7 | C68: 200 | D68: release/1.28.7 | E68: OK | F68: proteo4.operations-log.appender.sqs.batch.maxBatchSize | G68: 10
A69: ns-sys-global-p4-micros-arch | B69: https://bitbucket.apps.devops.aws.bancsabadell.com/rest/api/1.0/projects/P4DES/repos/ns-sys-global-p4-micros-arch/browse/pro/configs/application.yaml?at=release/1.28.7 | C69: 200 | D69: release/1.28.7 | E69: OK | F69: proteo4.operations-log.appender.sqs.batch.maxInflightOutboundBatches | G69: 1
A70: ns-sys-global-p4-micros-arch | B70: https://bitbucket.apps.devops.aws.bancsabadell.com/rest/api/1.0/projects/P4DES/repos/ns-sys-global-p4-micros-arch/browse/pro/configs/application.yaml?at=release/1.28.7 | C70: 200 | D70: release/1.28.7 | E70: OK | F70: proteo4.file-storage-service-platform.base-url | G70: https://ms-storage-api-pro-ns-inf.${PROVIDER_SUFFIX_URL:apps.pro.aws.bancsabadell.com}/private-document-library-storage/v1
A71: ns-sys-global-p4-micros-arch | B71: https://bitbucket.apps.devops.aws.bancsabadell.com/rest/api/1.0/projects/P4DES/repos/ns-sys-global-p4-micros-arch/browse/pro/configs/application.yaml?at=release/1.28.7 | C71: 200 | D71: release/1.28.7 | E71: OK | F71: proteo4.file-storage-service-platform.create-upload-link-path | G71: /upload-link/
A72: ns-sys-global-p4-micros-arch | B72: https://bitbucket.apps.devops.aws.bancsabadell.com/rest/api/1.0/projects/P4DES/repos/ns-sys-global-p4-micros-arch/browse/pro/configs/application.yaml?at=release/1.28.7 | C72: 200 | D72: release/1.28.7 | E72: OK | F72: proteo4.file-storage-service-platform.upload-path | G72: /upload/
A73: ns-sys-global-p4-micros-arch | B73: https://bitbucket.apps.devops.aws.bancsabadell.com/rest/api/1.0/projects/P4DES/repos/ns-sys-global-p4-micros-arch/browse/pro/configs/application.yaml?at=release/1.28.7 | C73: 200 | D73: release/1.28.7 | E73: OK | F73: proteo4.file-storage-service-platform.create-download-link-path | G73: /download-link/
A74: ns-sys-global-p4-micros-arch | B74: https://bitbucket.apps.devops.aws.bancsabadell.com/rest/api/1.0/projects/P4DES/repos/ns-sys-global-p4-micros-arch/browse/pro/configs/application.yaml?at=release/1.28.7 | C74: 200 | D74: release/1.28.7 | E74: OK | F74: proteo4.doc-generator.papyrus.base-url | G74: https://ms-infra-doc-generator-pro-ns-inf.${PROVIDER_SUFFIX_URL:apps.pro.aws.bancsabadell.com}
A75: ns-sys-global-p4-micros-arch | B75: https://bitbucket.apps.devops.aws.bancsabadell.com/rest/api/1.0/projects/P4DES/repos/ns-sys-global-p4-micros-arch/browse/pro/configs/application.yaml?at=release/1.28.7 | C75: 200 | D75: release/1.28.7 | E75: OK | F75: proteo4.doc-generator.papyrus.base-url-api | G75: https://ms-sys-generator-api-pro-ns-sys.${PROVIDER_SUFFIX_URL:apps.pro.aws.bancsabadell.com}
A76: ns-sys-global-p4-micros-arch | B76: https://bitbucket.apps.devops.aws.bancsabadell.com/rest/api/1.0/projects/P4DES/repos/ns-sys-global-p4-micros-arch/browse/pro/configs/application.yaml?at=release/1.28.7 | C76: 200 | D76: release/1.28.7 | E76: OK | F76: proteo4.doc-generator.papyrus.path | G76: /v1/private-documents/link
A77: ns-sys-global-p4-micros-arch | B77: https://bitbucket.apps.devops.aws.bancsabadell.com/rest/api/1.0/projects/P4DES/repos/ns-sys-global-p4-micros-arch/browse/pro/configs/application.yaml?at=release/1.28.7 | C77: 200 | D77: release/1.28.7 | E77: OK | F77: proteo4.geolocation.base-url | G77: https://ms-infra-geolocation-pro-ns-inf.${PROVIDER_SUFFIX_URL:apps.pro.aws.bancsabadell.com}
A78: ns-sys-global-p4-micros-arch | B78: https://bitbucket.apps.devops.aws.bancsabadell.com/rest/api/1.0/projects/P4DES/repos/ns-sys-global-p4-micros-arch/browse/pro/configs/application.yaml?at=release/1.28.7 | C78: 200 | D78: release/1.28.7 | E78: OK | F78: proteo4.biocatch-fraud-adapter.base-url | G78: https://ms-infra-biocatch-fraud-adapter-pro-ns-inf.${PROVIDER_SUFFIX_URL:apps.pro.aws.bancsabadell.com}
A79: ns-sys-global-p4-micros-arch | B79: https://bitbucket.apps.devops.aws.bancsabadell.com/rest/api/1.0/projects/P4DES/repos/ns-sys-global-p4-micros-arch/browse/pro/configs/application.yaml?at=release/1.28.7 | C79: 200 | D79: release/1.28.7 | E79: OK | F79: proteo4.biocatch-fraud-adapter.score-path | G79: /biocatch/score
A80: ns-sys-global-p4-micros-arch | B80: https://bitbucket.apps.devops.aws.bancsabadell.com/rest/api/1.0/projects/P4DES/repos/ns-sys-global-p4-micros-arch/browse/pro/configs/application.yaml?at=release/1.28.7 | C80: 200 | D80: release/1.28.7 | E80: OK | F80: proteo4.biocatch-fraud-adapter.score-login-path | G80: /biocatch/scoreLogin
A81: ns-sys-global-p4-micros-arch | B81: https://bitbucket.apps.devops.aws.bancsabadell.com/rest/api/1.0/projects/P4DES/repos/ns-sys-global-p4-micros-arch/browse/pro/configs/application.yaml?at=release/1.28.7 | C81: 200 | D81: release/1.28.7 | E81: OK | F81: proteo4.rsa-fraud-adapter.base-url | G81: https://ms-infra-rsa-fraud-adapter-pro-ns-inf.${PROVIDER_SUFFIX_URL:apps.pro.aws.bancsabadell.com}
... A93: ns-sys-global-p4-micros-arch | B93: https://bitbucket.apps.devops.aws.bancsabadell.com/rest/api/1.0/projects/P4DES/repos/ns-sys-global-p4-micros-arch/browse/pro/configs/application.yaml?at=release/1.28.7 | C93: 200 | D93: release/1.28.7 | E93: OK | F93: proteo4.crypto.kms.keyarn | G93: arn:aws:kms:eu-west-1:913536646623:key/ee6bf63d-cc22-4761-91d4-1
A94: ns-sys-global-p4-micros-arch | B94: https://bitbucket.apps.devops.aws.bancsabadell.com/rest/api/1.0/projects/P4DES/repos/ns-sys-global-p4-micros-arch/browse/pro/configs/application.yaml?at=release/1.28.7 | C94: 200 | D94: release/1.28.7 | E94: OK | F94: proteo4.crypto.cache.cacheCapacity | G94: 100
A95: ns-sys-global-p4-micros-arch | B95: https://bitbucket.apps.devops.aws.bancsabadell.com/rest/api/1.0/projects/P4DES/repos/ns-sys-global-p4-micros-arch/browse/pro/configs/application.yaml?at=release/1.28.7 | C95: 200 | D95: release/1.28.7 | E95: OK | F95: proteo4.crypto.cache.maxEntryMessages | G95: 100
A96: ns-sys-global-p4-micros-arch | B96: https://bitbucket.apps.devops.aws.bancsabadell.com/rest/api/1.0/projects/P4DES/repos/ns-sys-global-p4-micros-arch/browse/pro/configs/application.yaml?at=release/1.28.7 | C96: 200 | D96: release/1.28.7 | E96: OK | F96: proteo4.crypto.cache.maxEntryAge | G96: 1000
A97: ns-sys-global-p4-micros-arch | B97: https://bitbucket.apps.devops.aws.bancsabadell.com/rest/api/1.0/projects/P4DES/repos/ns-sys-global-p4-micros-arch/browse/pro/configs/application.yaml?at=release/1.28.7 | C97: 200 | D97: release/1.28.7 | E97: OK | F97: proteo4.redis.connection-values-eks.database | G97: 0
A98: ns-sys-global-p4-micros-arch | B98: https://bitbucket.apps.devops.aws.bancsabadell.com/rest/api/1.0/projects/P4DES/repos/ns-sys-global-p4-micros-arch/browse/pro/configs/application.yaml?at=release/1.28.7 | C98: 200 | D98: release/1.28.7 | E98: OK | F98: proteo4.redis.connection-values-eks.host | G98: redis-db-pro-headless.bscloud-redis-pro.svc.cluster.local
A99: ns-sys-global-p4-micros-arch | B99: https://bitbucket.apps.devops.aws.bancsabadell.com/rest/api/1.0/projects/P4DES/repos/ns-sys-global-p4-micros-arch/browse/pro/configs/application.yaml?at=release/1.28.7 | C99: 200 | D99: release/1.28.7 | E99: OK | F99: proteo4.redis.connection-values-eks.port | G99: 16379
A100: ns-sys-global-p4-micros-arch | B100: https://bitbucket.apps.devops.aws.bancsabadell.com/rest/api/1.0/projects/P4DES/repos/ns-sys-global-p4-micros-arch/browse/pro/configs/application.yaml?at=release/1.28.7 | C100: 200 | D100: release/1.28.7 | E100: OK | F100: proteo4.redis.connection-values-ocp.database | G100: 0
A101: ns-sys-global-p4-micros-arch | B101: https://bitbucket.apps.devops.aws.bancsabadell.com/rest/api/1.0/projects/P4DES/repos/ns-sys-global-p4-micros-arch/browse/pro/configs/application.yaml?at=release/1.28.7 | C101: 200 | D101: release/1.28.7 | E101: OK | F101: proteo4.redis.connection-values-ocp.host | G101: redis-db-pro-headless.bscloud-redis-pro.svc.cluster.local
A102: ns-sys-global-p4-micros-arch | B102: https://bitbucket.apps.devops.aws.bancsabadell.com/rest/api/1.0/projects/P4DES/repos/ns-sys-global-p4-micros-arch/browse/pro/configs/application.yaml?at=release/1.28.7 | C102: 200 | D102: release/1.28.7 | E102: OK | F102: proteo4.redis.connection-values-ocp.port | G102: 17140
A103: ns-sys-global-p4-micros-arch | B103: https://bitbucket.apps.devops.aws.bancsabadell.com/rest/api/1.0/projects/P4DES/repos/ns-sys-global-p4-micros-arch/browse/pro/configs/application.yaml?at=release/1.28.7 | C103: 200 | D103: release/1.28.7 | E103: OK | F103: proteo4.redis.encrypt-config.password | G103: ${REDIS_ENCRYPT_PASS}
A104: ns-sys-global-p4-micros-arch | B104: https://bitbucket.apps.devops.aws.bancsabadell.com/rest/api/1.0/projects/P4DES/repos/ns-sys-global-p4-micros-arch/browse/pro/configs/application.yaml?at=release/1.28.7 | C104: 200 | D104: release/1.28.7 | E104: OK | F104: proteo4.redis.pool-config.max-total | G104: 10
A105: ns-sys-global-p4-micros-arch | B105: https://bitbucket.apps.devops.aws.bancsabadell.com/rest/api/1.0/projects/P4DES/repos/ns-sys-global-p4-micros-arch/browse/pro/configs/application.yaml?at=release/1.28.7 | C105: 200 | D105: release/1.28.7 | E105: OK | F105: proteo4.redis.pool-config.max-idle | G105: 10
A106: ns-sys-global-p4-micros-arch | B106: https://bitbucket.apps.devops.aws.bancsabadell.com/rest/api/1.0/projects/P4DES/repos/ns-sys-global-p4-micros-arch/browse/pro/configs/application.yaml?at=release/1.28.7 | C106: 200 | D106: release/1.28.7 | E106: OK | F106: proteo4.redis.pool-config.min-idle | G106: 5
A107: ns-sys-global-p4-micros-arch | B107: https://bitbucket.apps.devops.aws.bancsabadell.com/rest/api/1.0/projects/P4DES/repos/ns-sys-global-p4-micros-arch/browse/pro/configs/application.yaml?at=release/1.28.7 | C107: 200 | D107: release/1.28.7 | E107: OK | F107: spring.sleuth.log.slf4j.enabled | G107: False
A108: ns-sys-global-p4-micros-arch | B108: https://bitbucket.apps.devops.aws.bancsabadell.com/rest/api/1.0/projects/P4DES/repos/ns-sys-global-p4-micros-arch/browse/pro/configs/application.yaml?at=release/1.28.7 | C108: 200 | D108: release/1.28.7 | E108: OK | F108: spring.sleuth.enabled | G108: True
A109: ns-sys-global-p4-micros-arch | B109: https://bitbucket.apps.devops.aws.bancsabadell.com/rest/api/1.0/projects/P4DES/repos/ns-sys-global-p4-micros-arch/browse/pro/configs/application.yaml?at=release/1.28.7 | C109: 200 | D109: release/1.28.7 | E109: OK | F109: spring.sleuth.trace-id128 | G109: True
A110: ns-sys-global-p4-micros-arch | B110: https://bitbucket.apps.devops.aws.bancsabadell.com/rest/api/1.0/projects/P4DES/repos/ns-sys-global-p4-micros-arch/browse/pro/configs/application.yaml?at=release/1.28.7 | C110: 200 | D110: release/1.28.7 | E110: OK | F110: spring.sleuth.baggage.correlation-fields | G110: x-request-id
A111: ns-sys-global-p4-micros-arch | B111: https://bitbucket.apps.devops.aws.bancsabadell.com/rest/api/1.0/projects/P4DES/repos/ns-sys-global-p4-micros-arch/browse/pro/configs/application.yaml?at=release/1.28.7 | C111: 200 | D111: release/1.28.7 | E111: OK | F111: spring.sleuth.baggage.remote-fields | G111: x-request-id
A112: ns-sys-global-p4-micros-arch | B112: https://bitbucket.apps.devops.aws.bancsabadell.com/rest/api/1.0/projects/P4DES/repos/ns-sys-global-p4-micros-arch/browse/pro/configs/application.yaml?at=release/1.28.7 | C112: 200 | D112: release/1.28.7 | E112: OK | F112: spring.cloud.discovery.client.composite-indicator.enabled | G112: False
A1048499: service | B1048499: url | C1048499: http_code | D1048499: branch | E1048499: status | F1048499: property_key | G1048499: property_value
A1048500: ns-sys-global-p4-micros-arch | B1048500: https://bitbucket.apps.devops.aws.bancsabadell.com/rest/api/1.0/projects/P4DES/repos/ns-sys-global-p4-micros-arch/browse/pro/configs/application.yaml?at=release/1.28.7 | C1048500: 200 | D1048500: release/1.28.7 | E1048500: OK | F1048500: management.endpoints.web.exposure.include | G1048500: info,health,prometheus
A1048501: ns-sys-global-p4-micros-arch | B1048501: https://bitbucket.apps.devops.aws.bancsabadell.com/rest/api/1.0/projects/P4DES/repos/ns-sys-global-p4-micros-arch/browse/pro/configs/application.yaml?at=release/1.28.7 | C1048501: 200 | D1048501: release/1.28.7 | E1048501: OK | F1048501: management.server.servlet.context-path | G1048501: /actuator
A1048502: ns-sys-global-p4-micros-arch | B1048502: https://bitbucket.apps.devops.aws.bancsabadell.com/rest/api/1.0/projects/P4DES/repos/ns-sys-global-p4-micros-arch/browse/pro/configs/application.yaml?at=release/1.28.7 | C1048502: 200 | D1048502: release/1.28.7 | E1048502: OK | F1048502: management.endpoint.health.show-details | G1048502: always
A1048503: ns-sys-global-p4-micros-arch | B1048503: https://bitbucket.apps.devops.aws.bancsabadell.com/rest/api/1.0/projects/P4DES/repos/ns-sys-global-p4-micros-arch/browse/pro/configs/application.yaml?at=release/1.28.7 | C1048503: 200 | D1048503: release/1.28.7 | E1048503: OK | F1048503: management.endpoint.health.show-components | G1048503: always
A1048504: ns-sys-global-p4-micros-arch | B1048504: https://bitbucket.apps.devops.aws.bancsabadell.com/rest/api/1.0/projects/P4DES/repos/ns-sys-global-p4-micros-arch/browse/pro/configs/application.yaml?at=release/1.28.7 | C1048504: 200 | D1048504: release/1.28.7 | E1048504: OK | F1048504: management.endpoint.health.group.readiness.include | G1048504: readinessState,warmup
A1048505: ns-sys-global-p4-micros-arch | B1048505: https://bitbucket.apps.devops.aws.bancsabadell.com/rest/api/1.0/projects/P4DES/repos/ns-sys-global-p4-micros-arch/browse/pro/configs/application.yaml?at=release/1.28.7 | C1048505: 200 | D1048505: release/1.28.7 | E1048505: OK | F1048505: management.health.probes.enabled | G1048505: True
A1048506: ns-sys-global-p4-micros-arch | B1048506: https://bitbucket.apps.devops.aws.bancsabadell.com/rest/api/1.0/projects/P4DES/repos/ns-sys-global-p4-micros-arch/browse/pro/configs/application.yaml?at=release/1.28.7 | C1048506: 200 | D1048506: release/1.28.7 | E1048506: OK | F1048506: server.port | G1048506: 8080
A1048507: ns-sys-global-p4-micros-arch | B1048507: https://bitbucket.apps.devops.aws.bancsabadell.com/rest/api/1.0/projects/P4DES/repos/ns-sys-global-p4-micros-arch/browse/pro/configs/application.yaml?at=release/1.28.7 | C1048507: 200 | D1048507: release/1.28.7 | E1048507: OK | F1048507: server.forward-headers-strategy | G1048507: NONE
A1048508: ns-sys-global-p4-micros-arch | B1048508: https://bitbucket.apps.devops.aws.bancsabadell.com/rest/api/1.0/projects/P4DES/repos/ns-sys-global-p4-micros-arch/browse/pro/configs/application.yaml?at=release/1.28.7 | C1048508: 200 | D1048508: release/1.28.7 | E1048508: OK | F1048508: server.max-http-header-size | G1048508: 15KB
A1048509: ns-sys-global-p4-micros-arch | B1048509: https://bitbucket.apps.devops.aws.bancsabadell.com/rest/api/1.0/projects/P4DES/repos/ns-sys-global-p4-micros-arch/browse/pro/configs/application.yaml?at=release/1.28.7 | C1048509: 200 | D1048509: release/1.28.7 | E1048509: OK | F1048509: proteo4.web-client.limit-max-in-memory-size | G1048509: 26214400
A1048510: ns-sys-global-p4-micros-arch | B1048510: https://bitbucket.apps.devops.aws.bancsabadell.com/rest/api/1.0/projects/P4DES/repos/ns-sys-global-p4-micros-arch/browse/pro/configs/application.yaml?at=release/1.28.7 | C1048510: 200 | D1048510: release/1.28.7 | E1048510: OK | F1048510: proteo4.web-client.propagated-headers[0] | G1048510: Authorization
A1048511: ns-sys-global-p4-micros-arch | B1048511: https://bitbucket.apps.devops.aws.bancsabadell.com/rest/api/1.0/projects/P4DES/repos/ns-sys-global-p4-micros-arch/browse/pro/configs/application.yaml?at=release/1.28.7 | C1048511: 200 | D1048511: release/1.28.7 | E1048511: OK | F1048511: proteo4.web-client.propagated-headers[1] | G1048511: Accept-Language
A1048512: ns-sys-global-p4-micros-arch | B1048512: https://bitbucket.apps.devops.aws.bancsabadell.com/rest/api/1.0/projects/P4DES/repos/ns-sys-global-p4-micros-arch/browse/pro/configs/application.yaml?at=release/1.28.7 | C1048512: 200 | D1048512: release/1.28.7 | E1048512: OK | F1048512: proteo4.web-client.propagated-headers[2] | G1048512: Cookie
A1048513: ns-sys-global-p4-micros-arch | B1048513: https://bitbucket.apps.devops.aws.bancsabadell.com/rest/api/1.0/projects/P4DES/repos/ns-sys-global-p4-micros-arch/browse/pro/configs/application.yaml?at=release/1.28.7 | C1048513: 200 | D1048513: release/1.28.7 | E1048513: OK | F1048513: proteo4.web-client.propagated-headers[3] | G1048513: Content-Language
A1048514: ns-sys-global-p4-micros-arch | B1048514: https://bitbucket.apps.devops.aws.bancsabadell.com/rest/api/1.0/projects/P4DES/repos/ns-sys-global-p4-micros-arch/browse/pro/configs/application.yaml?at=release/1.28.7 | C1048514: 200 | D1048514: release/1.28.7 | E1048514: OK | F1048514: proteo4.web-client.propagated-headers[4] | G1048514: User-Agent
A1048515: ns-sys-global-p4-micros-arch | B1048515: https://bitbucket.apps.devops.aws.bancsabadell.com/rest/api/1.0/projects/P4DES/repos/ns-sys-global-p4-micros-arch/browse/pro/configs/application.yaml?at=release/1.28.7 | C1048515: 200 | D1048515: release/1.28.7 | E1048515: OK | F1048515: proteo4.web-client.propagated-headers[5] | G1048515: x-instance-id
A1048516: ns-sys-global-p4-micros-arch | B1048516: https://bitbucket.apps.devops.aws.bancsabadell.com/rest/api/1.0/projects/P4DES/repos/ns-sys-global-p4-micros-arch/browse/pro/configs/application.yaml?at=release/1.28.7 | C1048516: 200 | D1048516: release/1.28.7 | E1048516: OK | F1048516: proteo4.web-client.propagated-headers[6] | G1048516: X-Forwarded-For
A1048517: ns-sys-global-p4-micros-arch | B1048517: https://bitbucket.apps.devops.aws.bancsabadell.com/rest/api/1.0/projects/P4DES/repos/ns-sys-global-p4-micros-arch/browse/pro/configs/application.yaml?at=release/1.28.7 | C1048517: 200 | D1048517: release/1.28.7 | E1048517: OK | F1048517: proteo4.web-client.propagated-headers[7] | G1048517: X-Auth
A1048518: ns-sys-global-p4-micros-arch | B1048518: https://bitbucket.apps.devops.aws.bancsabadell.com/rest/api/1.0/projects/P4DES/repos/ns-sys-global-p4-micros-arch/browse/pro/configs/application.yaml?at=release/1.28.7 | C1048518: 200 | D1048518: release/1.28.7 | E1048518: OK | F1048518: proteo4.web-client.propagated-headers[8] | G1048518: x-dynatrace-application
A1048519: ns-sys-global-p4-micros-arch | B1048519: https://bitbucket.apps.devops.aws.bancsabadell.com/rest/api/1.0/projects/P4DES/repos/ns-sys-global-p4-micros-arch/browse/pro/configs/application.yaml?at=release/1.28.7 | C1048519: 200 | D1048519: release/1.28.7 | E1048519: OK | F1048519: proteo4.web-client.propagated-headers[9] | G1048519: x-dynatrace-origin-url
A1048520: ns-sys-global-p4-micros-arch | B1048520: https://bitbucket.apps.devops.aws.bancsabadell.com/rest/api/1.0/projects/P4DES/repos/ns-sys-global-p4-micros-arch/browse/pro/configs/application.yaml?at=release/1.28.7 | C1048520: 200 | D1048520: release/1.28.7 | E1048520: OK | F1048520: proteo4.web-client.propagated-headers[10] | G1048520: x-dynatrace-requeststate
A1048521: ns-sys-global-p4-micros-arch | B1048521: https://bitbucket.apps.devops.aws.bancsabadell.com/rest/api/1.0/projects/P4DES/repos/ns-sys-global-p4-micros-arch/browse/pro/configs/application.yaml?at=release/1.28.7 | C1048521: 200 | D1048521: release/1.28.7 | E1048521: OK | F1048521: proteo4.web-client.propagated-headers[11] | G1048521: 25df5dad0a39ec8a6a36be8dcb9153806ca9691401dfb28bca8aab9d85fbd876
... A1048557: ns-sys-global-p4-micros-arch | B1048557: https://bitbucket.apps.devops.aws.bancsabadell.com/rest/api/1.0/projects/P4DES/repos/ns-sys-global-p4-micros-arch/browse/pro/configs/application.yaml?at=release/1.28.7 | C1048557: 200 | D1048557: release/1.28.7 | E1048557: OK | F1048557: proteo4.operations-log.appender.sqs.queue.endpoint | G1048557: https://sqs.eu-west-1.amazonaws.com/913536646623/proteo4-logoperational.fifo
A1048558: ns-sys-global-p4-micros-arch | B1048558: https://bitbucket.apps.devops.aws.bancsabadell.com/rest/api/1.0/projects/P4DES/repos/ns-sys-global-p4-micros-arch/browse/pro/configs/application.yaml?at=release/1.28.7 | C1048558: 200 | D1048558: release/1.28.7 | E1048558: OK | F1048558: proteo4.operations-log.appender.sqs.queue.timeout | G1048558: 5000
A1048559: ns-sys-global-p4-micros-arch | B1048559: https://bitbucket.apps.devops.aws.bancsabadell.com/rest/api/1.0/projects/P4DES/repos/ns-sys-global-p4-micros-arch/browse/pro/configs/application.yaml?at=release/1.28.7 | C1048559: 200 | D1048559: release/1.28.7 | E1048559: OK | F1048559: proteo4.operations-log.appender.sqs.queue.fifo.groupId | G1048559: groupIdPRO
A1048560: ns-sys-global-p4-micros-arch | B1048560: https://bitbucket.apps.devops.aws.bancsabadell.com/rest/api/1.0/projects/P4DES/repos/ns-sys-global-p4-micros-arch/browse/pro/configs/application.yaml?at=release/1.28.7 | C1048560: 200 | D1048560: release/1.28.7 | E1048560: OK | F1048560: proteo4.operations-log.appender.sqs.queue.fifo.groupCount | G1048560: 64000
A1048561: ns-sys-global-p4-micros-arch | B1048561: https://bitbucket.apps.devops.aws.bancsabadell.com/rest/api/1.0/projects/P4DES/repos/ns-sys-global-p4-micros-arch/browse/pro/configs/application.yaml?at=release/1.28.7 | C1048561: 200 | D1048561: release/1.28.7 | E1048561: OK | F1048561: proteo4.operations-log.appender.sqs.proxy.enabled | G1048561: ${PROVIDER_IS_OCP:false}
A1048562: ns-sys-global-p4-micros-arch | B1048562: https://bitbucket.apps.devops.aws.bancsabadell.com/rest/api/1.0/projects/P4DES/repos/ns-sys-global-p4-micros-arch/browse/pro/configs/application.yaml?at=release/1.28.7 | C1048562: 200 | D1048562: release/1.28.7 | E1048562: OK | F1048562: proteo4.operations-log.appender.sqs.proxy.hostname | G1048562: proxy.bancsabadell.com
A1048563: ns-sys-global-p4-micros-arch | B1048563: https://bitbucket.apps.devops.aws.bancsabadell.com/rest/api/1.0/projects/P4DES/repos/ns-sys-global-p4-micros-arch/browse/pro/configs/application.yaml?at=release/1.28.7 | C1048563: 200 | D1048563: release/1.28.7 | E1048563: OK | F1048563: proteo4.operations-log.appender.sqs.proxy.port | G1048563: 8080
A1048564: ns-sys-global-p4-micros-arch | B1048564: https://bitbucket.apps.devops.aws.bancsabadell.com/rest/api/1.0/projects/P4DES/repos/ns-sys-global-p4-micros-arch/browse/pro/configs/application.yaml?at=release/1.28.7 | C1048564: 200 | D1048564: release/1.28.7 | E1048564: OK | F1048564: proteo4.operations-log.appender.sqs.batch.enabled | G1048564: True
A1048565: ns-sys-global-p4-micros-arch | B1048565: https://bitbucket.apps.devops.aws.bancsabadell.com/rest/api/1.0/projects/P4DES/repos/ns-sys-global-p4-micros-arch/browse/pro/configs/application.yaml?at=release/1.28.7 | C1048565: 200 | D1048565: release/1.28.7 | E1048565: OK | F1048565: proteo4.operations-log.appender.sqs.batch.maxBatchOpenMs | G1048565: 200
A1048566: ns-sys-global-p4-micros-arch | B1048566: https://bitbucket.apps.devops.aws.bancsabadell.com/rest/api/1.0/projects/P4DES/repos/ns-sys-global-p4-micros-arch/browse/pro/configs/application.yaml?at=release/1.28.7 | C1048566: 200 | D1048566: release/1.28.7 | E1048566: OK | F1048566: proteo4.operations-log.appender.sqs.batch.maxBatchSize | G1048566: 10
A1048567: ns-sys-global-p4-micros-arch | B1048567: https://bitbucket.apps.devops.aws.bancsabadell.com/rest/api/1.0/projects/P4DES/repos/ns-sys-global-p4-micros-arch/browse/pro/configs/application.yaml?at=release/1.28.7 | C1048567: 200 | D1048567: release/1.28.7 | E1048567: OK | F1048567: proteo4.operations-log.appender.sqs.batch.maxInflightOutboundBatches | G1048567: 1
...

Sheet globales-baas
A1: service | B1: url | C1: http_code | D1: branch | E1: status | F1: property_key | G1: property_value
A2: ns-baas-global-p4-micros-arch | B2: https://bitbucket.apps.devops.aws.bancsabadell.com/rest/api/1.0/projects/P4DES/repos/ns-baas-global-p4-micros-arch/browse/pro/configs/application.yaml?at=release/1.7.9 | C2: 200 | D2: release/1.7.9 | E2: OK | F2: management.endpoints.web.exposure.include | G2: info,health,prometheus
A3: ns-baas-global-p4-micros-arch | B3: https://bitbucket.apps.devops.aws.bancsabadell.com/rest/api/1.0/projects/P4DES/repos/ns-baas-global-p4-micros-arch/browse/pro/configs/application.yaml?at=release/1.7.9 | C3: 200 | D3: release/1.7.9 | E3: OK | F3: management.server.servlet.context-path | G3: /actuator
A4: ns-baas-global-p4-micros-arch | B4: https://bitbucket.apps.devops.aws.bancsabadell.com/rest/api/1.0/projects/P4DES/repos/ns-baas-global-p4-micros-arch/browse/pro/configs/application.yaml?at=release/1.7.9 | C4: 200 | D4: release/1.7.9 | E4: OK | F4: management.endpoint.health.show-details | G4: always
A5: ns-baas-global-p4-micros-arch | B5: https://bitbucket.apps.devops.aws.bancsabadell.com/rest/api/1.0/projects/P4DES/repos/ns-baas-global-p4-micros-arch/browse/pro/configs/application.yaml?at=release/1.7.9 | C5: 200 | D5: release/1.7.9 | E5: OK | F5: management.endpoint.health.show-components | G5: always
A6: ns-baas-global-p4-micros-arch | B6: https://bitbucket.apps.devops.aws.bancsabadell.com/rest/api/1.0/projects/P4DES/repos/ns-baas-global-p4-micros-arch/browse/pro/configs/application.yaml?at=release/1.7.9 | C6: 200 | D6: release/1.7.9 | E6: OK | F6: management.endpoint.health.group.readiness.include | G6: readinessState,warmup
A7: ns-baas-global-p4-micros-arch | B7: https://bitbucket.apps.devops.aws.bancsabadell.com/rest/api/1.0/projects/P4DES/repos/ns-baas-global-p4-micros-arch/browse/pro/configs/application.yaml?at=release/1.7.9 | C7: 200 | D7: release/1.7.9 | E7: OK | F7: management.health.probes.enabled | G7: True
A8: ns-baas-global-p4-micros-arch | B8: https://bitbucket.apps.devops.aws.bancsabadell.com/rest/api/1.0/projects/P4DES/repos/ns-baas-global-p4-micros-arch/browse/pro/configs/application.yaml?at=release/1.7.9 | C8: 200 | D8: release/1.7.9 | E8: OK | F8: server.port | G8: 8080
A9: ns-baas-global-p4-micros-arch | B9: https://bitbucket.apps.devops.aws.bancsabadell.com/rest/api/1.0/projects/P4DES/repos/ns-baas-global-p4-micros-arch/browse/pro/configs/application.yaml?at=release/1.7.9 | C9: 200 | D9: release/1.7.9 | E9: OK | F9: server.forward-headers-strategy | G9: NONE
A10: ns-baas-global-p4-micros-arch | B10: https://bitbucket.apps.devops.aws.bancsabadell.com/rest/api/1.0/projects/P4DES/repos/ns-baas-global-p4-micros-arch/browse/pro/configs/application.yaml?at=release/1.7.9 | C10: 200 | D10: release/1.7.9 | E10: OK | F10: server.max-http-header-size | G10: 15KB
A11: ns-baas-global-p4-micros-arch | B11: https://bitbucket.apps.devops.aws.bancsabadell.com/rest/api/1.0/projects/P4DES/repos/ns-baas-global-p4-micros-arch/browse/pro/configs/application.yaml?at=release/1.7.9 | C11: 200 | D11: release/1.7.9 | E11: OK | F11: proteo4.web-client.limit-max-in-memory-size | G11: 500000
A12: ns-baas-global-p4-micros-arch | B12: https://bitbucket.apps.devops.aws.bancsabadell.com/rest/api/1.0/projects/P4DES/repos/ns-baas-global-p4-micros-arch/browse/pro/configs/application.yaml?at=release/1.7.9 | C12: 200 | D12: release/1.7.9 | E12: OK | F12: proteo4.web-client.propagated-headers[0] | G12: Authorization
A13: ns-baas-global-p4-micros-arch | B13: https://bitbucket.apps.devops.aws.bancsabadell.com/rest/api/1.0/projects/P4DES/repos/ns-baas-global-p4-micros-arch/browse/pro/configs/application.yaml?at=release/1.7.9 | C13: 200 | D13: release/1.7.9 | E13: OK | F13: proteo4.web-client.propagated-headers[1] | G13: Accept-Language
A14: ns-baas-global-p4-micros-arch | B14: https://bitbucket.apps.devops.aws.bancsabadell.com/rest/api/1.0/projects/P4DES/repos/ns-baas-global-p4-micros-arch/browse/pro/configs/application.yaml?at=release/1.7.9 | C14: 200 | D14: release/1.7.9 | E14: OK | F14: proteo4.web-client.propagated-headers[2] | G14: Cookie
A15: ns-baas-global-p4-micros-arch | B15: https://bitbucket.apps.devops.aws.bancsabadell.com/rest/api/1.0/projects/P4DES/repos/ns-baas-global-p4-micros-arch/browse/pro/configs/application.yaml?at=release/1.7.9 | C15: 200 | D15: release/1.7.9 | E15: OK | F15: proteo4.web-client.propagated-headers[3] | G15: Content-Language
A16: ns-baas-global-p4-micros-arch | B16: https://bitbucket.apps.devops.aws.bancsabadell.com/rest/api/1.0/projects/P4DES/repos/ns-baas-global-p4-micros-arch/browse/pro/configs/application.yaml?at=release/1.7.9 | C16: 200 | D16: release/1.7.9 | E16: OK | F16: proteo4.web-client.propagated-headers[4] | G16: User-Agent
A17: ns-baas-global-p4-micros-arch | B17: https://bitbucket.apps.devops.aws.bancsabadell.com/rest/api/1.0/projects/P4DES/repos/ns-baas-global-p4-micros-arch/browse/pro/configs/application.yaml?at=release/1.7.9 | C17: 200 | D17: release/1.7.9 | E17: OK | F17: proteo4.web-client.propagated-headers[5] | G17: x-instance-id
A18: ns-baas-global-p4-micros-arch | B18: https://bitbucket.apps.devops.aws.bancsabadell.com/rest/api/1.0/projects/P4DES/repos/ns-baas-global-p4-micros-arch/browse/pro/configs/application.yaml?at=release/1.7.9 | C18: 200 | D18: release/1.7.9 | E18: OK | F18: proteo4.web-client.propagated-headers[6] | G18: X-Forwarded-For
A19: ns-baas-global-p4-micros-arch | B19: https://bitbucket.apps.devops.aws.bancsabadell.com/rest/api/1.0/projects/P4DES/repos/ns-baas-global-p4-micros-arch/browse/pro/configs/application.yaml?at=release/1.7.9 | C19: 200 | D19: release/1.7.9 | E19: OK | F19: proteo4.web-client.propagated-headers[7] | G19: X-Auth
A20: ns-baas-global-p4-micros-arch | B20: https://bitbucket.apps.devops.aws.bancsabadell.com/rest/api/1.0/projects/P4DES/repos/ns-baas-global-p4-micros-arch/browse/pro/configs/application.yaml?at=release/1.7.9 | C20: 200 | D20: release/1.7.9 | E20: OK | F20: proteo4.web-client.propagated-headers[8] | G20: x-dynatrace-application
A21: ns-baas-global-p4-micros-arch | B21: https://bitbucket.apps.devops.aws.bancsabadell.com/rest/api/1.0/projects/P4DES/repos/ns-baas-global-p4-micros-arch/browse/pro/configs/application.yaml?at=release/1.7.9 | C21: 200 | D21: release/1.7.9 | E21: OK | F21: proteo4.web-client.propagated-headers[9] | G21: x-dynatrace-origin-url
A22: ns-baas-global-p4-micros-arch | B22: https://bitbucket.apps.devops.aws.bancsabadell.com/rest/api/1.0/projects/P4DES/repos/ns-baas-global-p4-micros-arch/browse/pro/configs/application.yaml?at=release/1.7.9 | C22: 200 | D22: release/1.7.9 | E22: OK | F22: proteo4.web-client.propagated-headers[10] | G22: x-dynatrace-requeststate
A23: ns-baas-global-p4-micros-arch | B23: https://bitbucket.apps.devops.aws.bancsabadell.com/rest/api/1.0/projects/P4DES/repos/ns-baas-global-p4-micros-arch/browse/pro/configs/application.yaml?at=release/1.7.9 | C23: 200 | D23: release/1.7.9 | E23: OK | F23: proteo4.web-client.propagated-headers[11] | G23: 25df5dad0a39ec8a6a36be8dcb9153806ca9691401dfb28bca8aab9d85fbd876
... A47: ns-baas-global-p4-micros-arch | B47: https://bitbucket.apps.devops.aws.bancsabadell.com/rest/api/1.0/projects/P4DES/repos/ns-baas-global-p4-micros-arch/browse/pro/configs/application.yaml?at=release/1.7.9 | C47: 200 | D47: release/1.7.9 | E47: OK | F47: proteo4.operations-log.appender.sqs.queue.endpoint | G47: https://sqs.eu-west-1.amazonaws.com/913536646623/proteo4-logoperational.fifo
A48: ns-baas-global-p4-micros-arch | B48: https://bitbucket.apps.devops.aws.bancsabadell.com/rest/api/1.0/projects/P4DES/repos/ns-baas-global-p4-micros-arch/browse/pro/configs/application.yaml?at=release/1.7.9 | C48: 200 | D48: release/1.7.9 | E48: OK | F48: proteo4.operations-log.appender.sqs.queue.timeout | G48: 5000
A49: ns-baas-global-p4-micros-arch | B49: https://bitbucket.apps.devops.aws.bancsabadell.com/rest/api/1.0/projects/P4DES/repos/ns-baas-global-p4-micros-arch/browse/pro/configs/application.yaml?at=release/1.7.9 | C49: 200 | D49: release/1.7.9 | E49: OK | F49: proteo4.operations-log.appender.sqs.queue.fifo.groupId | G49: groupIdPRO
A50: ns-baas-global-p4-micros-arch | B50: https://bitbucket.apps.devops.aws.bancsabadell.com/rest/api/1.0/projects/P4DES/repos/ns-baas-global-p4-micros-arch/browse/pro/configs/application.yaml?at=release/1.7.9 | C50: 200 | D50: release/1.7.9 | E50: OK | F50: proteo4.operations-log.appender.sqs.queue.fifo.groupCount | G50: 64000
A51: ns-baas-global-p4-micros-arch | B51: https://bitbucket.apps.devops.aws.bancsabadell.com/rest/api/1.0/projects/P4DES/repos/ns-baas-global-p4-micros-arch/browse/pro/configs/application.yaml?at=release/1.7.9 | C51: 200 | D51: release/1.7.9 | E51: OK | F51: proteo4.operations-log.appender.sqs.proxy.enabled | G51: ${PROVIDER_IS_OCP:false}
A52: ns-baas-global-p4-micros-arch | B52: https://bitbucket.apps.devops.aws.bancsabadell.com/rest/api/1.0/projects/P4DES/repos/ns-baas-global-p4-micros-arch/browse/pro/configs/application.yaml?at=release/1.7.9 | C52: 200 | D52: release/1.7.9 | E52: OK | F52: proteo4.operations-log.appender.sqs.proxy.hostname | G52: proxy.bancsabadell.com
A53: ns-baas-global-p4-micros-arch | B53: https://bitbucket.apps.devops.aws.bancsabadell.com/rest/api/1.0/projects/P4DES/repos/ns-baas-global-p4-micros-arch/browse/pro/configs/application.yaml?at=release/1.7.9 | C53: 200 | D53: release/1.7.9 | E53: OK | F53: proteo4.operations-log.appender.sqs.proxy.port | G53: 8080
A54: ns-baas-global-p4-micros-arch | B54: https://bitbucket.apps.devops.aws.bancsabadell.com/rest/api/1.0/projects/P4DES/repos/ns-baas-global-p4-micros-arch/browse/pro/configs/application.yaml?at=release/1.7.9 | C54: 200 | D54: release/1.7.9 | E54: OK | F54: proteo4.operations-log.appender.sqs.batch.enabled | G54: True
A55: ns-baas-global-p4-micros-arch | B55: https://bitbucket.apps.devops.aws.bancsabadell.com/rest/api/1.0/projects/P4DES/repos/ns-baas-global-p4-micros-arch/browse/pro/configs/application.yaml?at=release/1.7.9 | C55: 200 | D55: release/1.7.9 | E55: OK | F55: proteo4.operations-log.appender.sqs.batch.maxBatchOpenMs | G55: 200
A56: ns-baas-global-p4-micros-arch | B56: https://bitbucket.apps.devops.aws.bancsabadell.com/rest/api/1.0/projects/P4DES/repos/ns-baas-global-p4-micros-arch/browse/pro/configs/application.yaml?at=release/1.7.9 | C56: 200 | D56: release/1.7.9 | E56: OK | F56: proteo4.operations-log.appender.sqs.batch.maxBatchSize | G56: 10
A57: ns-baas-global-p4-micros-arch | B57: https://bitbucket.apps.devops.aws.bancsabadell.com/rest/api/1.0/projects/P4DES/repos/ns-baas-global-p4-micros-arch/browse/pro/configs/application.yaml?at=release/1.7.9 | C57: 200 | D57: release/1.7.9 | E57: OK | F57: proteo4.operations-log.appender.sqs.batch.maxInflightOutboundBatches | G57: 1
A58: ns-baas-global-p4-micros-arch | B58: https://bitbucket.apps.devops.aws.bancsabadell.com/rest/api/1.0/projects/P4DES/repos/ns-baas-global-p4-micros-arch/browse/pro/configs/application.yaml?at=release/1.7.9 | C58: 200 | D58: release/1.7.9 | E58: OK | F58: proteo4.security-initializer.client-credentials.clients.openam.base-url | G58: https://pro-openam-elb.pro.p4es.aws.bancsabadell.com:8443/o
A59: ns-baas-global-p4-micros-arch | B59: https://bitbucket.apps.devops.aws.bancsabadell.com/rest/api/1.0/projects/P4DES/repos/ns-baas-global-p4-micros-arch/browse/pro/configs/application.yaml?at=release/1.7.9 | C59: 200 | D59: release/1.7.9 | E59: OK | F59: proteo4.security-initializer.client-credentials.clients.openam.endpoints.accessToken | G59: /oauth2/realms/root/realms/P4/access_token
A60: ns-baas-global-p4-micros-arch | B60: https://bitbucket.apps.devops.aws.bancsabadell.com/rest/api/1.0/projects/P4DES/repos/ns-baas-global-p4-micros-arch/browse/pro/configs/application.yaml?at=release/1.7.9 | C60: 200 | D60: release/1.7.9 | E60: OK | F60: proteo4.security-initializer.client-credentials.clients.jwt.base-url | G60: https://ms-infra-security-jwt-pro-ns-inf.${PROVIDER_SUFFIX_URL:apps.pro.aws.bancsabadell.com}/
A61: ns-baas-global-p4-micros-arch | B61: https://bitbucket.apps.devops.aws.bancsabadell.com/rest/api/1.0/projects/P4DES/repos/ns-baas-global-p4-micros-arch/browse/pro/configs/application.yaml?at=release/1.7.9 | C61: 200 | D61: release/1.7.9 | E61: OK | F61: proteo4.security-initializer.client-credentials.employees.openam.base-url | G61: https://forgerockam-pro.apps.pro.aws.bancsabadell.com/am
A62: ns-baas-global-p4-micros-arch | B62: https://bitbucket.apps.devops.aws.bancsabadell.com/rest/api/1.0/projects/P4DES/repos/ns-baas-global-p4-micros-arch/browse/pro/configs/application.yaml?at=release/1.7.9 | C62: 200 | D62: release/1.7.9 | E62: OK | F62: proteo4.security-initializer.client-credentials.employees.openam.endpoints.accessToken | G62: /oauth2/realms/root/realms/employees/access_token
A63: ns-baas-global-p4-micros-arch | B63: https://bitbucket.apps.devops.aws.bancsabadell.com/rest/api/1.0/projects/P4DES/repos/ns-baas-global-p4-micros-arch/browse/pro/configs/application.yaml?at=release/1.7.9 | C63: 200 | D63: release/1.7.9 | E63: OK | F63: proteo4.security-initializer.client-credentials.employees.jwt.base-url | G63: https://ms-infra-jwt-employees-pro-ns-inf.${PROVIDER_SUFFIX_URL:apps.pro.aws.bancsabadell.com}/
A64: ns-baas-global-p4-micros-arch | B64: https://bitbucket.apps.devops.aws.bancsabadell.com/rest/api/1.0/projects/P4DES/repos/ns-baas-global-p4-micros-arch/browse/pro/configs/application.yaml?at=release/1.7.9 | C64: 200 | D64: release/1.7.9 | E64: OK | F64: proteo4.security-initializer.client-credentials.partners.openam.base-url | G64: https://pro-openam-elb.pro.p4es.aws.bancsabadell.com:8443/o
A65: ns-baas-global-p4-micros-arch | B65: https://bitbucket.apps.devops.aws.bancsabadell.com/rest/api/1.0/projects/P4DES/repos/ns-baas-global-p4-micros-arch/browse/pro/configs/application.yaml?at=release/1.7.9 | C65: 200 | D65: release/1.7.9 | E65: OK | F65: proteo4.security-initializer.client-credentials.partners.openam.endpoints.accessToken | G65: /oauth2/realms/root/realms/partners/access_token
A66: ns-baas-global-p4-micros-arch | B66: https://bitbucket.apps.devops.aws.bancsabadell.com/rest/api/1.0/projects/P4DES/repos/ns-baas-global-p4-micros-arch/browse/pro/configs/application.yaml?at=release/1.7.9 | C66: 200 | D66: release/1.7.9 | E66: OK | F66: proteo4.security-initializer.client-credentials.partners.jwt.base-url | G66: https://ms-infra-jwt-partners-pro-ns-inf.${PROVIDER_SUFFIX_URL:apps.pro.aws.bancsabadell.com}/
A67: ns-baas-global-p4-micros-arch | B67: https://bitbucket.apps.devops.aws.bancsabadell.com/rest/api/1.0/projects/P4DES/repos/ns-baas-global-p4-micros-arch/browse/pro/configs/application.yaml?at=release/1.7.9 | C67: 200 | D67: release/1.7.9 | E67: OK | F67: proteo4.crypto.kms.uri | G67: https://vpce-0a2d1d35df31199c9-d7i889qk.kms.eu-west-1.vpce.amazonaws.com:443
A68: ns-baas-global-p4-micros-arch | B68: https://bitbucket.apps.devops.aws.bancsabadell.com/rest/api/1.0/projects/P4DES/repos/ns-baas-global-p4-micros-arch/browse/pro/configs/application.yaml?at=release/1.7.9 | C68: 200 | D68: release/1.7.9 | E68: OK | F68: proteo4.crypto.kms.region | G68: eu-west-1
A69: ns-baas-global-p4-micros-arch | B69: https://bitbucket.apps.devops.aws.bancsabadell.com/rest/api/1.0/projects/P4DES/repos/ns-baas-global-p4-micros-arch/browse/pro/configs/application.yaml?at=release/1.7.9 | C69: 200 | D69: release/1.7.9 | E69: OK | F69: proteo4.crypto.kms.keyarn | G69: arn:aws:kms:eu-west-1:913536646623:key/ee6bf63d-cc22-4761-91d4-1
A70: ns-baas-global-p4-micros-arch | B70: https://bitbucket.apps.devops.aws.bancsabadell.com/rest/api/1.0/projects/P4DES/repos/ns-baas-global-p4-micros-arch/browse/pro/configs/application.yaml?at=release/1.7.9 | C70: 200 | D70: release/1.7.9 | E70: OK | F70: proteo4.crypto.cache.cacheCapacity | G70: 100
A71: ns-baas-global-p4-micros-arch | B71: https://bitbucket.apps.devops.aws.bancsabadell.com/rest/api/1.0/projects/P4DES/repos/ns-baas-global-p4-micros-arch/browse/pro/configs/application.yaml?at=release/1.7.9 | C71: 200 | D71: release/1.7.9 | E71: OK | F71: proteo4.crypto.cache.maxEntryMessages | G71: 100
A72: ns-baas-global-p4-micros-arch | B72: https://bitbucket.apps.devops.aws.bancsabadell.com/rest/api/1.0/projects/P4DES/repos/ns-baas-global-p4-micros-arch/browse/pro/configs/application.yaml?at=release/1.7.9 | C72: 200 | D72: release/1.7.9 | E72: OK | F72: proteo4.crypto.cache.maxEntryAge | G72: 1000
A73: ns-baas-global-p4-micros-arch | B73: https://bitbucket.apps.devops.aws.bancsabadell.com/rest/api/1.0/projects/P4DES/repos/ns-baas-global-p4-micros-arch/browse/pro/configs/application.yaml?at=release/1.7.9 | C73: 200 | D73: release/1.7.9 | E73: OK | F73: proteo4.api-url.micros | G73: https://microsapi.es.bs
A74: ns-baas-global-p4-micros-arch | B74: https://bitbucket.apps.devops.aws.bancsabadell.com/rest/api/1.0/projects/P4DES/repos/ns-baas-global-p4-micros-arch/browse/pro/configs/application.yaml?at=release/1.7.9 | C74: 200 | D74: release/1.7.9 | E74: OK | F74: spring.sleuth.log.slf4j.enabled | G74: False
A75: ns-baas-global-p4-micros-arch | B75: https://bitbucket.apps.devops.aws.bancsabadell.com/rest/api/1.0/projects/P4DES/repos/ns-baas-global-p4-micros-arch/browse/pro/configs/application.yaml?at=release/1.7.9 | C75: 200 | D75: release/1.7.9 | E75: OK | F75: spring.sleuth.enabled | G75: True
A76: ns-baas-global-p4-micros-arch | B76: https://bitbucket.apps.devops.aws.bancsabadell.com/rest/api/1.0/projects/P4DES/repos/ns-baas-global-p4-micros-arch/browse/pro/configs/application.yaml?at=release/1.7.9 | C76: 200 | D76: release/1.7.9 | E76: OK | F76: spring.sleuth.trace-id128 | G76: True
A77: ns-baas-global-p4-micros-arch | B77: https://bitbucket.apps.devops.aws.bancsabadell.com/rest/api/1.0/projects/P4DES/repos/ns-baas-global-p4-micros-arch/browse/pro/configs/application.yaml?at=release/1.7.9 | C77: 200 | D77: release/1.7.9 | E77: OK | F77: spring.sleuth.baggage.correlation-fields | G77: x-request-id
A78: ns-baas-global-p4-micros-arch | B78: https://bitbucket.apps.devops.aws.bancsabadell.com/rest/api/1.0/projects/P4DES/repos/ns-baas-global-p4-micros-arch/browse/pro/configs/application.yaml?at=release/1.7.9 | C78: 200 | D78: release/1.7.9 | E78: OK | F78: spring.sleuth.baggage.remote-fields | G78: x-request-id
A79: ns-baas-global-p4-micros-arch | B79: https://bitbucket.apps.devops.aws.bancsabadell.com/rest/api/1.0/projects/P4DES/repos/ns-baas-global-p4-micros-arch/browse/pro/configs/application.yaml?at=release/1.7.9 | C79: 200 | D79: release/1.7.9 | E79: OK | F79: spring.cloud.discovery.client.composite-indicator.enabled | G79: False
A1048466: service | B1048466: url | C1048466: http_code | D1048466: branch | E1048466: status | F1048466: property_key | G1048466: property_value
A1048467: ns-baas-global-p4-micros-arch | B1048467: https://bitbucket.apps.devops.aws.bancsabadell.com/rest/api/1.0/projects/P4DES/repos/ns-baas-global-p4-micros-arch/browse/pro/configs/application.yaml?at=release/1.7.9 | C1048467: 200 | D1048467: release/1.7.9 | E1048467: OK | F1048467: management.endpoints.web.exposure.include | G1048467: info,health,prometheus
A1048468: ns-baas-global-p4-micros-arch | B1048468: https://bitbucket.apps.devops.aws.bancsabadell.com/rest/api/1.0/projects/P4DES/repos/ns-baas-global-p4-micros-arch/browse/pro/configs/application.yaml?at=release/1.7.9 | C1048468: 200 | D1048468: release/1.7.9 | E1048468: OK | F1048468: management.server.servlet.context-path | G1048468: /actuator
A1048469: ns-baas-global-p4-micros-arch | B1048469: https://bitbucket.apps.devops.aws.bancsabadell.com/rest/api/1.0/projects/P4DES/repos/ns-baas-global-p4-micros-arch/browse/pro/configs/application.yaml?at=release/1.7.9 | C1048469: 200 | D1048469: release/1.7.9 | E1048469: OK | F1048469: management.endpoint.health.show-details | G1048469: always
A1048470: ns-baas-global-p4-micros-arch | B1048470: https://bitbucket.apps.devops.aws.bancsabadell.com/rest/api/1.0/projects/P4DES/repos/ns-baas-global-p4-micros-arch/browse/pro/configs/application.yaml?at=release/1.7.9 | C1048470: 200 | D1048470: release/1.7.9 | E1048470: OK | F1048470: management.endpoint.health.show-components | G1048470: always
A1048471: ns-baas-global-p4-micros-arch | B1048471: https://bitbucket.apps.devops.aws.bancsabadell.com/rest/api/1.0/projects/P4DES/repos/ns-baas-global-p4-micros-arch/browse/pro/configs/application.yaml?at=release/1.7.9 | C1048471: 200 | D1048471: release/1.7.9 | E1048471: OK | F1048471: management.endpoint.health.group.readiness.include | G1048471: readinessState,warmup
A1048472: ns-baas-global-p4-micros-arch | B1048472: https://bitbucket.apps.devops.aws.bancsabadell.com/rest/api/1.0/projects/P4DES/repos/ns-baas-global-p4-micros-arch/browse/pro/configs/application.yaml?at=release/1.7.9 | C1048472: 200 | D1048472: release/1.7.9 | E1048472: OK | F1048472: management.health.probes.enabled | G1048472: True
A1048473: ns-baas-global-p4-micros-arch | B1048473: https://bitbucket.apps.devops.aws.bancsabadell.com/rest/api/1.0/projects/P4DES/repos/ns-baas-global-p4-micros-arch/browse/pro/configs/application.yaml?at=release/1.7.9 | C1048473: 200 | D1048473: release/1.7.9 | E1048473: OK | F1048473: server.port | G1048473: 8080
A1048474: ns-baas-global-p4-micros-arch | B1048474: https://bitbucket.apps.devops.aws.bancsabadell.com/rest/api/1.0/projects/P4DES/repos/ns-baas-global-p4-micros-arch/browse/pro/configs/application.yaml?at=release/1.7.9 | C1048474: 200 | D1048474: release/1.7.9 | E1048474: OK | F1048474: server.forward-headers-strategy | G1048474: NONE
A1048475: ns-baas-global-p4-micros-arch | B1048475: https://bitbucket.apps.devops.aws.bancsabadell.com/rest/api/1.0/projects/P4DES/repos/ns-baas-global-p4-micros-arch/browse/pro/configs/application.yaml?at=release/1.7.9 | C1048475: 200 | D1048475: release/1.7.9 | E1048475: OK | F1048475: server.max-http-header-size | G1048475: 15KB
A1048476: ns-baas-global-p4-micros-arch | B1048476: https://bitbucket.apps.devops.aws.bancsabadell.com/rest/api/1.0/projects/P4DES/repos/ns-baas-global-p4-micros-arch/browse/pro/configs/application.yaml?at=release/1.7.9 | C1048476: 200 | D1048476: release/1.7.9 | E1048476: OK | F1048476: proteo4.web-client.limit-max-in-memory-size | G1048476: 500000
A1048477: ns-baas-global-p4-micros-arch | B1048477: https://bitbucket.apps.devops.aws.bancsabadell.com/rest/api/1.0/projects/P4DES/repos/ns-baas-global-p4-micros-arch/browse/pro/configs/application.yaml?at=release/1.7.9 | C1048477: 200 | D1048477: release/1.7.9 | E1048477: OK | F1048477: proteo4.web-client.propagated-headers[0] | G1048477: Authorization
A1048478: ns-baas-global-p4-micros-arch | B1048478: https://bitbucket.apps.devops.aws.bancsabadell.com/rest/api/1.0/projects/P4DES/repos/ns-baas-global-p4-micros-arch/browse/pro/configs/application.yaml?at=release/1.7.9 | C1048478: 200 | D1048478: release/1.7.9 | E1048478: OK | F1048478: proteo4.web-client.propagated-headers[1] | G1048478: Accept-Language
A1048479: ns-baas-global-p4-micros-arch | B1048479: https://bitbucket.apps.devops.aws.bancsabadell.com/rest/api/1.0/projects/P4DES/repos/ns-baas-global-p4-micros-arch/browse/pro/configs/application.yaml?at=release/1.7.9 | C1048479: 200 | D1048479: release/1.7.9 | E1048479: OK | F1048479: proteo4.web-client.propagated-headers[2] | G1048479: Cookie
A1048480: ns-baas-global-p4-micros-arch | B1048480: https://bitbucket.apps.devops.aws.bancsabadell.com/rest/api/1.0/projects/P4DES/repos/ns-baas-global-p4-micros-arch/browse/pro/configs/application.yaml?at=release/1.7.9 | C1048480: 200 | D1048480: release/1.7.9 | E1048480: OK | F1048480: proteo4.web-client.propagated-headers[3] | G1048480: Content-Language
A1048481: ns-baas-global-p4-micros-arch | B1048481: https://bitbucket.apps.devops.aws.bancsabadell.com/rest/api/1.0/projects/P4DES/repos/ns-baas-global-p4-micros-arch/browse/pro/configs/application.yaml?at=release/1.7.9 | C1048481: 200 | D1048481: release/1.7.9 | E1048481: OK | F1048481: proteo4.web-client.propagated-headers[4] | G1048481: User-Agent
A1048482: ns-baas-global-p4-micros-arch | B1048482: https://bitbucket.apps.devops.aws.bancsabadell.com/rest/api/1.0/projects/P4DES/repos/ns-baas-global-p4-micros-arch/browse/pro/configs/application.yaml?at=release/1.7.9 | C1048482: 200 | D1048482: release/1.7.9 | E1048482: OK | F1048482: proteo4.web-client.propagated-headers[5] | G1048482: x-instance-id
A1048483: ns-baas-global-p4-micros-arch | B1048483: https://bitbucket.apps.devops.aws.bancsabadell.com/rest/api/1.0/projects/P4DES/repos/ns-baas-global-p4-micros-arch/browse/pro/configs/application.yaml?at=release/1.7.9 | C1048483: 200 | D1048483: release/1.7.9 | E1048483: OK | F1048483: proteo4.web-client.propagated-headers[6] | G1048483: X-Forwarded-For
A1048484: ns-baas-global-p4-micros-arch | B1048484: https://bitbucket.apps.devops.aws.bancsabadell.com/rest/api/1.0/projects/P4DES/repos/ns-baas-global-p4-micros-arch/browse/pro/configs/application.yaml?at=release/1.7.9 | C1048484: 200 | D1048484: release/1.7.9 | E1048484: OK | F1048484: proteo4.web-client.propagated-headers[7] | G1048484: X-Auth
A1048485: ns-baas-global-p4-micros-arch | B1048485: https://bitbucket.apps.devops.aws.bancsabadell.com/rest/api/1.0/projects/P4DES/repos/ns-baas-global-p4-micros-arch/browse/pro/configs/application.yaml?at=release/1.7.9 | C1048485: 200 | D1048485: release/1.7.9 | E1048485: OK | F1048485: proteo4.web-client.propagated-headers[8] | G1048485: x-dynatrace-application
A1048486: ns-baas-global-p4-micros-arch | B1048486: https://bitbucket.apps.devops.aws.bancsabadell.com/rest/api/1.0/projects/P4DES/repos/ns-baas-global-p4-micros-arch/browse/pro/configs/application.yaml?at=release/1.7.9 | C1048486: 200 | D1048486: release/1.7.9 | E1048486: OK | F1048486: proteo4.web-client.propagated-headers[9] | G1048486: x-dynatrace-origin-url
A1048487: ns-baas-global-p4-micros-arch | B1048487: https://bitbucket.apps.devops.aws.bancsabadell.com/rest/api/1.0/projects/P4DES/repos/ns-baas-global-p4-micros-arch/browse/pro/configs/application.yaml?at=release/1.7.9 | C1048487: 200 | D1048487: release/1.7.9 | E1048487: OK | F1048487: proteo4.web-client.propagated-headers[10] | G1048487: x-dynatrace-requeststate
A1048488: ns-baas-global-p4-micros-arch | B1048488: https://bitbucket.apps.devops.aws.bancsabadell.com/rest/api/1.0/projects/P4DES/repos/ns-baas-global-p4-micros-arch/browse/pro/configs/application.yaml?at=release/1.7.9 | C1048488: 200 | D1048488: release/1.7.9 | E1048488: OK | F1048488: proteo4.web-client.propagated-headers[11] | G1048488: 25df5dad0a39ec8a6a36be8dcb9153806ca9691401dfb28bca8aab9d85fbd876
... A1048512: ns-baas-global-p4-micros-arch | B1048512: https://bitbucket.apps.devops.aws.bancsabadell.com/rest/api/1.0/projects/P4DES/repos/ns-baas-global-p4-micros-arch/browse/pro/configs/application.yaml?at=release/1.7.9 | C1048512: 200 | D1048512: release/1.7.9 | E1048512: OK | F1048512: proteo4.operations-log.appender.sqs.queue.endpoint | G1048512: https://sqs.eu-west-1.amazonaws.com/913536646623/proteo4-logoperational.fifo
A1048513: ns-baas-global-p4-micros-arch | B1048513: https://bitbucket.apps.devops.aws.bancsabadell.com/rest/api/1.0/projects/P4DES/repos/ns-baas-global-p4-micros-arch/browse/pro/configs/application.yaml?at=release/1.7.9 | C1048513: 200 | D1048513: release/1.7.9 | E1048513: OK | F1048513: proteo4.operations-log.appender.sqs.queue.timeout | G1048513: 5000
A1048514: ns-baas-global-p4-micros-arch | B1048514: https://bitbucket.apps.devops.aws.bancsabadell.com/rest/api/1.0/projects/P4DES/repos/ns-baas-global-p4-micros-arch/browse/pro/configs/application.yaml?at=release/1.7.9 | C1048514: 200 | D1048514: release/1.7.9 | E1048514: OK | F1048514: proteo4.operations-log.appender.sqs.queue.fifo.groupId | G1048514: groupIdPRO
A1048515: ns-baas-global-p4-micros-arch | B1048515: https://bitbucket.apps.devops.aws.bancsabadell.com/rest/api/1.0/projects/P4DES/repos/ns-baas-global-p4-micros-arch/browse/pro/configs/application.yaml?at=release/1.7.9 | C1048515: 200 | D1048515: release/1.7.9 | E1048515: OK | F1048515: proteo4.operations-log.appender.sqs.queue.fifo.groupCount | G1048515: 64000
A1048516: ns-baas-global-p4-micros-arch | B1048516: https://bitbucket.apps.devops.aws.bancsabadell.com/rest/api/1.0/projects/P4DES/repos/ns-baas-global-p4-micros-arch/browse/pro/configs/application.yaml?at=release/1.7.9 | C1048516: 200 | D1048516: release/1.7.9 | E1048516: OK | F1048516: proteo4.operations-log.appender.sqs.proxy.enabled | G1048516: ${PROVIDER_IS_OCP:false}
A1048517: ns-baas-global-p4-micros-arch | B1048517: https://bitbucket.apps.devops.aws.bancsabadell.com/rest/api/1.0/projects/P4DES/repos/ns-baas-global-p4-micros-arch/browse/pro/configs/application.yaml?at=release/1.7.9 | C1048517: 200 | D1048517: release/1.7.9 | E1048517: OK | F1048517: proteo4.operations-log.appender.sqs.proxy.hostname | G1048517: proxy.bancsabadell.com
A1048518: ns-baas-global-p4-micros-arch | B1048518: https://bitbucket.apps.devops.aws.bancsabadell.com/rest/api/1.0/projects/P4DES/repos/ns-baas-global-p4-micros-arch/browse/pro/configs/application.yaml?at=release/1.7.9 | C1048518: 200 | D1048518: release/1.7.9 | E1048518: OK | F1048518: proteo4.operations-log.appender.sqs.proxy.port | G1048518: 8080
A1048519: ns-baas-global-p4-micros-arch | B1048519: https://bitbucket.apps.devops.aws.bancsabadell.com/rest/api/1.0/projects/P4DES/repos/ns-baas-global-p4-micros-arch/browse/pro/configs/application.yaml?at=release/1.7.9 | C1048519: 200 | D1048519: release/1.7.9 | E1048519: OK | F1048519: proteo4.operations-log.appender.sqs.batch.enabled | G1048519: True
A1048520: ns-baas-global-p4-micros-arch | B1048520: https://bitbucket.apps.devops.aws.bancsabadell.com/rest/api/1.0/projects/P4DES/repos/ns-baas-global-p4-micros-arch/browse/pro/configs/application.yaml?at=release/1.7.9 | C1048520: 200 | D1048520: release/1.7.9 | E1048520: OK | F1048520: proteo4.operations-log.appender.sqs.batch.maxBatchOpenMs | G1048520: 200
A1048521: ns-baas-global-p4-micros-arch | B1048521: https://bitbucket.apps.devops.aws.bancsabadell.com/rest/api/1.0/projects/P4DES/repos/ns-baas-global-p4-micros-arch/browse/pro/configs/application.yaml?at=release/1.7.9 | C1048521: 200 | D1048521: release/1.7.9 | E1048521: OK | F1048521: proteo4.operations-log.appender.sqs.batch.maxBatchSize | G1048521: 10
A1048522: ns-baas-global-p4-micros-arch | B1048522: https://bitbucket.apps.devops.aws.bancsabadell.com/rest/api/1.0/projects/P4DES/repos/ns-baas-global-p4-micros-arch/browse/pro/configs/application.yaml?at=release/1.7.9 | C1048522: 200 | D1048522: release/1.7.9 | E1048522: OK | F1048522: proteo4.operations-log.appender.sqs.batch.maxInflightOutboundBatches | G1048522: 1
A1048523: ns-baas-global-p4-micros-arch | B1048523: https://bitbucket.apps.devops.aws.bancsabadell.com/rest/api/1.0/projects/P4DES/repos/ns-baas-global-p4-micros-arch/browse/pro/configs/application.yaml?at=release/1.7.9 | C1048523: 200 | D1048523: release/1.7.9 | E1048523: OK | F1048523: proteo4.security-initializer.client-credentials.clients.openam.base-url | G1048523: https://pro-openam-elb.pro.p4es.aws.bancsabadell.com:8443/o
A1048524: ns-baas-global-p4-micros-arch | B1048524: https://bitbucket.apps.devops.aws.bancsabadell.com/rest/api/1.0/projects/P4DES/repos/ns-baas-global-p4-micros-arch/browse/pro/configs/application.yaml?at=release/1.7.9 | C1048524: 200 | D1048524: release/1.7.9 | E1048524: OK | F1048524: proteo4.security-initializer.client-credentials.clients.openam.endpoints.accessToken | G1048524: /oauth2/realms/root/realms/P4/access_token
A1048525: ns-baas-global-p4-micros-arch | B1048525: https://bitbucket.apps.devops.aws.bancsabadell.com/rest/api/1.0/projects/P4DES/repos/ns-baas-global-p4-micros-arch/browse/pro/configs/application.yaml?at=release/1.7.9 | C1048525: 200 | D1048525: release/1.7.9 | E1048525: OK | F1048525: proteo4.security-initializer.client-credentials.clients.jwt.base-url | G1048525: https://ms-infra-security-jwt-pro-ns-inf.${PROVIDER_SUFFIX_URL:apps.pro.aws.bancsabadell.com}/
A1048526: ns-baas-global-p4-micros-arch | B1048526: https://bitbucket.apps.devops.aws.bancsabadell.com/rest/api/1.0/projects/P4DES/repos/ns-baas-global-p4-micros-arch/browse/pro/configs/application.yaml?at=release/1.7.9 | C1048526: 200 | D1048526: release/1.7.9 | E1048526: OK | F1048526: proteo4.security-initializer.client-credentials.employees.openam.base-url | G1048526: https://forgerockam-pro.apps.pro.aws.bancsabadell.com/am
A1048527: ns-baas-global-p4-micros-arch | B1048527: https://bitbucket.apps.devops.aws.bancsabadell.com/rest/api/1.0/projects/P4DES/repos/ns-baas-global-p4-micros-arch/browse/pro/configs/application.yaml?at=release/1.7.9 | C1048527: 200 | D1048527: release/1.7.9 | E1048527: OK | F1048527: proteo4.security-initializer.client-credentials.employees.openam.endpoints.accessToken | G1048527: /oauth2/realms/root/realms/employees/access_token
A1048528: ns-baas-global-p4-micros-arch | B1048528: https://bitbucket.apps.devops.aws.bancsabadell.com/rest/api/1.0/projects/P4DES/repos/ns-baas-global-p4-micros-arch/browse/pro/configs/application.yaml?at=release/1.7.9 | C1048528: 200 | D1048528: release/1.7.9 | E1048528: OK | F1048528: proteo4.security-initializer.client-credentials.employees.jwt.base-url | G1048528: https://ms-infra-jwt-employees-pro-ns-inf.${PROVIDER_SUFFIX_URL:apps.pro.aws.bancsabadell.com}/
A1048529: ns-baas-global-p4-micros-arch | B1048529: https://bitbucket.apps.devops.aws.bancsabadell.com/rest/api/1.0/projects/P4DES/repos/ns-baas-global-p4-micros-arch/browse/pro/configs/application.yaml?at=release/1.7.9 | C1048529: 200 | D1048529: release/1.7.9 | E1048529: OK | F1048529: proteo4.security-initializer.client-credentials.partners.openam.base-url | G1048529: https://pro-openam-elb.pro.p4es.aws.bancsabadell.com:8443/o
A1048530: ns-baas-global-p4-micros-arch | B1048530: https://bitbucket.apps.devops.aws.bancsabadell.com/rest/api/1.0/projects/P4DES/repos/ns-baas-global-p4-micros-arch/browse/pro/configs/application.yaml?at=release/1.7.9 | C1048530: 200 | D1048530: release/1.7.9 | E1048530: OK | F1048530: proteo4.security-initializer.client-credentials.partners.openam.endpoints.accessToken | G1048530: /oauth2/realms/root/realms/partners/access_token
A1048531: ns-baas-global-p4-micros-arch | B1048531: https://bitbucket.apps.devops.aws.bancsabadell.com/rest/api/1.0/projects/P4DES/repos/ns-baas-global-p4-micros-arch/browse/pro/configs/application.yaml?at=release/1.7.9 | C1048531: 200 | D1048531: release/1.7.9 | E1048531: OK | F1048531: proteo4.security-initializer.client-credentials.partners.jwt.base-url | G1048531: https://ms-infra-jwt-partners-pro-ns-inf.${PROVIDER_SUFFIX_URL:apps.pro.aws.bancsabadell.com}/
A1048532: ns-baas-global-p4-micros-arch | B1048532: https://bitbucket.apps.devops.aws.bancsabadell.com/rest/api/1.0/projects/P4DES/repos/ns-baas-global-p4-micros-arch/browse/pro/configs/application.yaml?at=release/1.7.9 | C1048532: 200 | D1048532: release/1.7.9 | E1048532: OK | F1048532: proteo4.crypto.kms.uri | G1048532: https://vpce-0a2d1d35df31199c9-d7i889qk.kms.eu-west-1.vpce.amazonaws.com:443
...

Sheet globales-bff
A1: service | B1: url | C1: http_code | D1: branch | E1: status | F1: property_key | G1: property_value
A2: ns-bff-global-p4-micros-arch | B2: https://bitbucket.apps.devops.aws.bancsabadell.com/rest/api/1.0/projects/P4DES/repos/ns-bff-global-p4-micros-arch/browse/pro/configs/application.yaml?at=release/1.8.8 | C2: 200 | D2: release/1.8.8 | E2: OK | F2: management.endpoints.web.exposure.include | G2: info,health,prometheus
A3: ns-bff-global-p4-micros-arch | B3: https://bitbucket.apps.devops.aws.bancsabadell.com/rest/api/1.0/projects/P4DES/repos/ns-bff-global-p4-micros-arch/browse/pro/configs/application.yaml?at=release/1.8.8 | C3: 200 | D3: release/1.8.8 | E3: OK | F3: management.server.servlet.context-path | G3: /actuator
A4: ns-bff-global-p4-micros-arch | B4: https://bitbucket.apps.devops.aws.bancsabadell.com/rest/api/1.0/projects/P4DES/repos/ns-bff-global-p4-micros-arch/browse/pro/configs/application.yaml?at=release/1.8.8 | C4: 200 | D4: release/1.8.8 | E4: OK | F4: management.endpoint.health.show-details | G4: always
A5: ns-bff-global-p4-micros-arch | B5: https://bitbucket.apps.devops.aws.bancsabadell.com/rest/api/1.0/projects/P4DES/repos/ns-bff-global-p4-micros-arch/browse/pro/configs/application.yaml?at=release/1.8.8 | C5: 200 | D5: release/1.8.8 | E5: OK | F5: management.endpoint.health.show-components | G5: always
A6: ns-bff-global-p4-micros-arch | B6: https://bitbucket.apps.devops.aws.bancsabadell.com/rest/api/1.0/projects/P4DES/repos/ns-bff-global-p4-micros-arch/browse/pro/configs/application.yaml?at=release/1.8.8 | C6: 200 | D6: release/1.8.8 | E6: OK | F6: management.endpoint.health.group.readiness.include | G6: readinessState,warmup
A7: ns-bff-global-p4-micros-arch | B7: https://bitbucket.apps.devops.aws.bancsabadell.com/rest/api/1.0/projects/P4DES/repos/ns-bff-global-p4-micros-arch/browse/pro/configs/application.yaml?at=release/1.8.8 | C7: 200 | D7: release/1.8.8 | E7: OK | F7: management.health.probes.enabled | G7: True
A8: ns-bff-global-p4-micros-arch | B8: https://bitbucket.apps.devops.aws.bancsabadell.com/rest/api/1.0/projects/P4DES/repos/ns-bff-global-p4-micros-arch/browse/pro/configs/application.yaml?at=release/1.8.8 | C8: 200 | D8: release/1.8.8 | E8: OK | F8: server.port | G8: 8080
A9: ns-bff-global-p4-micros-arch | B9: https://bitbucket.apps.devops.aws.bancsabadell.com/rest/api/1.0/projects/P4DES/repos/ns-bff-global-p4-micros-arch/browse/pro/configs/application.yaml?at=release/1.8.8 | C9: 200 | D9: release/1.8.8 | E9: OK | F9: server.forward-headers-strategy | G9: NONE
A10: ns-bff-global-p4-micros-arch | B10: https://bitbucket.apps.devops.aws.bancsabadell.com/rest/api/1.0/projects/P4DES/repos/ns-bff-global-p4-micros-arch/browse/pro/configs/application.yaml?at=release/1.8.8 | C10: 200 | D10: release/1.8.8 | E10: OK | F10: server.max-http-header-size | G10: 15KB
A11: ns-bff-global-p4-micros-arch | B11: https://bitbucket.apps.devops.aws.bancsabadell.com/rest/api/1.0/projects/P4DES/repos/ns-bff-global-p4-micros-arch/browse/pro/configs/application.yaml?at=release/1.8.8 | C11: 200 | D11: release/1.8.8 | E11: OK | F11: proteo4.web-client.limit-max-in-memory-size | G11: 500000
A12: ns-bff-global-p4-micros-arch | B12: https://bitbucket.apps.devops.aws.bancsabadell.com/rest/api/1.0/projects/P4DES/repos/ns-bff-global-p4-micros-arch/browse/pro/configs/application.yaml?at=release/1.8.8 | C12: 200 | D12: release/1.8.8 | E12: OK | F12: proteo4.web-client.propagated-headers[0] | G12: Authorization
A13: ns-bff-global-p4-micros-arch | B13: https://bitbucket.apps.devops.aws.bancsabadell.com/rest/api/1.0/projects/P4DES/repos/ns-bff-global-p4-micros-arch/browse/pro/configs/application.yaml?at=release/1.8.8 | C13: 200 | D13: release/1.8.8 | E13: OK | F13: proteo4.web-client.propagated-headers[1] | G13: Accept-Language
A14: ns-bff-global-p4-micros-arch | B14: https://bitbucket.apps.devops.aws.bancsabadell.com/rest/api/1.0/projects/P4DES/repos/ns-bff-global-p4-micros-arch/browse/pro/configs/application.yaml?at=release/1.8.8 | C14: 200 | D14: release/1.8.8 | E14: OK | F14: proteo4.web-client.propagated-headers[2] | G14: Cookie
A15: ns-bff-global-p4-micros-arch | B15: https://bitbucket.apps.devops.aws.bancsabadell.com/rest/api/1.0/projects/P4DES/repos/ns-bff-global-p4-micros-arch/browse/pro/configs/application.yaml?at=release/1.8.8 | C15: 200 | D15: release/1.8.8 | E15: OK | F15: proteo4.web-client.propagated-headers[3] | G15: Content-Language
A16: ns-bff-global-p4-micros-arch | B16: https://bitbucket.apps.devops.aws.bancsabadell.com/rest/api/1.0/projects/P4DES/repos/ns-bff-global-p4-micros-arch/browse/pro/configs/application.yaml?at=release/1.8.8 | C16: 200 | D16: release/1.8.8 | E16: OK | F16: proteo4.web-client.propagated-headers[4] | G16: User-Agent
A17: ns-bff-global-p4-micros-arch | B17: https://bitbucket.apps.devops.aws.bancsabadell.com/rest/api/1.0/projects/P4DES/repos/ns-bff-global-p4-micros-arch/browse/pro/configs/application.yaml?at=release/1.8.8 | C17: 200 | D17: release/1.8.8 | E17: OK | F17: proteo4.web-client.propagated-headers[5] | G17: x-instance-id
A18: ns-bff-global-p4-micros-arch | B18: https://bitbucket.apps.devops.aws.bancsabadell.com/rest/api/1.0/projects/P4DES/repos/ns-bff-global-p4-micros-arch/browse/pro/configs/application.yaml?at=release/1.8.8 | C18: 200 | D18: release/1.8.8 | E18: OK | F18: proteo4.web-client.propagated-headers[6] | G18: X-Forwarded-For
A19: ns-bff-global-p4-micros-arch | B19: https://bitbucket.apps.devops.aws.bancsabadell.com/rest/api/1.0/projects/P4DES/repos/ns-bff-global-p4-micros-arch/browse/pro/configs/application.yaml?at=release/1.8.8 | C19: 200 | D19: release/1.8.8 | E19: OK | F19: proteo4.web-client.propagated-headers[7] | G19: X-Auth
A20: ns-bff-global-p4-micros-arch | B20: https://bitbucket.apps.devops.aws.bancsabadell.com/rest/api/1.0/projects/P4DES/repos/ns-bff-global-p4-micros-arch/browse/pro/configs/application.yaml?at=release/1.8.8 | C20: 200 | D20: release/1.8.8 | E20: OK | F20: proteo4.web-client.propagated-headers[8] | G20: x-dynatrace-application
A21: ns-bff-global-p4-micros-arch | B21: https://bitbucket.apps.devops.aws.bancsabadell.com/rest/api/1.0/projects/P4DES/repos/ns-bff-global-p4-micros-arch/browse/pro/configs/application.yaml?at=release/1.8.8 | C21: 200 | D21: release/1.8.8 | E21: OK | F21: proteo4.web-client.propagated-headers[9] | G21: x-dynatrace-origin-url
A22: ns-bff-global-p4-micros-arch | B22: https://bitbucket.apps.devops.aws.bancsabadell.com/rest/api/1.0/projects/P4DES/repos/ns-bff-global-p4-micros-arch/browse/pro/configs/application.yaml?at=release/1.8.8 | C22: 200 | D22: release/1.8.8 | E22: OK | F22: proteo4.web-client.propagated-headers[10] | G22: x-dynatrace-requeststate
A23: ns-bff-global-p4-micros-arch | B23: https://bitbucket.apps.devops.aws.bancsabadell.com/rest/api/1.0/projects/P4DES/repos/ns-bff-global-p4-micros-arch/browse/pro/configs/application.yaml?at=release/1.8.8 | C23: 200 | D23: release/1.8.8 | E23: OK | F23: proteo4.web-client.propagated-headers[11] | G23: 25df5dad0a39ec8a6a36be8dcb9153806ca9691401dfb28bca8aab9d85fbd876
... A53: ns-bff-global-p4-micros-arch | B53: https://bitbucket.apps.devops.aws.bancsabadell.com/rest/api/1.0/projects/P4DES/repos/ns-bff-global-p4-micros-arch/browse/pro/configs/application.yaml?at=release/1.8.8 | C53: 200 | D53: release/1.8.8 | E53: OK | F53: proteo4.operations-log.appender.sqs.queue.endpoint | G53: https://sqs.eu-west-1.amazonaws.com/913536646623/proteo4-logoperational.fifo
A54: ns-bff-global-p4-micros-arch | B54: https://bitbucket.apps.devops.aws.bancsabadell.com/rest/api/1.0/projects/P4DES/repos/ns-bff-global-p4-micros-arch/browse/pro/configs/application.yaml?at=release/1.8.8 | C54: 200 | D54: release/1.8.8 | E54: OK | F54: proteo4.operations-log.appender.sqs.queue.timeout | G54: 5000
A55: ns-bff-global-p4-micros-arch | B55: https://bitbucket.apps.devops.aws.bancsabadell.com/rest/api/1.0/projects/P4DES/repos/ns-bff-global-p4-micros-arch/browse/pro/configs/application.yaml?at=release/1.8.8 | C55: 200 | D55: release/1.8.8 | E55: OK | F55: proteo4.operations-log.appender.sqs.queue.fifo.groupId | G55: groupIdPRO
A56: ns-bff-global-p4-micros-arch | B56: https://bitbucket.apps.devops.aws.bancsabadell.com/rest/api/1.0/projects/P4DES/repos/ns-bff-global-p4-micros-arch/browse/pro/configs/application.yaml?at=release/1.8.8 | C56: 200 | D56: release/1.8.8 | E56: OK | F56: proteo4.operations-log.appender.sqs.queue.fifo.groupCount | G56: 64000
A57: ns-bff-global-p4-micros-arch | B57: https://bitbucket.apps.devops.aws.bancsabadell.com/rest/api/1.0/projects/P4DES/repos/ns-bff-global-p4-micros-arch/browse/pro/configs/application.yaml?at=release/1.8.8 | C57: 200 | D57: release/1.8.8 | E57: OK | F57: proteo4.operations-log.appender.sqs.proxy.enabled | G57: ${PROVIDER_IS_OCP:false}
A58: ns-bff-global-p4-micros-arch | B58: https://bitbucket.apps.devops.aws.bancsabadell.com/rest/api/1.0/projects/P4DES/repos/ns-bff-global-p4-micros-arch/browse/pro/configs/application.yaml?at=release/1.8.8 | C58: 200 | D58: release/1.8.8 | E58: OK | F58: proteo4.operations-log.appender.sqs.proxy.hostname | G58: proxy.bancsabadell.com
A59: ns-bff-global-p4-micros-arch | B59: https://bitbucket.apps.devops.aws.bancsabadell.com/rest/api/1.0/projects/P4DES/repos/ns-bff-global-p4-micros-arch/browse/pro/configs/application.yaml?at=release/1.8.8 | C59: 200 | D59: release/1.8.8 | E59: OK | F59: proteo4.operations-log.appender.sqs.proxy.port | G59: 8080
A60: ns-bff-global-p4-micros-arch | B60: https://bitbucket.apps.devops.aws.bancsabadell.com/rest/api/1.0/projects/P4DES/repos/ns-bff-global-p4-micros-arch/browse/pro/configs/application.yaml?at=release/1.8.8 | C60: 200 | D60: release/1.8.8 | E60: OK | F60: proteo4.operations-log.appender.sqs.batch.enabled | G60: True
A61: ns-bff-global-p4-micros-arch | B61: https://bitbucket.apps.devops.aws.bancsabadell.com/rest/api/1.0/projects/P4DES/repos/ns-bff-global-p4-micros-arch/browse/pro/configs/application.yaml?at=release/1.8.8 | C61: 200 | D61: release/1.8.8 | E61: OK | F61: proteo4.operations-log.appender.sqs.batch.maxBatchOpenMs | G61: 200
A62: ns-bff-global-p4-micros-arch | B62: https://bitbucket.apps.devops.aws.bancsabadell.com/rest/api/1.0/projects/P4DES/repos/ns-bff-global-p4-micros-arch/browse/pro/configs/application.yaml?at=release/1.8.8 | C62: 200 | D62: release/1.8.8 | E62: OK | F62: proteo4.operations-log.appender.sqs.batch.maxBatchSize | G62: 10
A63: ns-bff-global-p4-micros-arch | B63: https://bitbucket.apps.devops.aws.bancsabadell.com/rest/api/1.0/projects/P4DES/repos/ns-bff-global-p4-micros-arch/browse/pro/configs/application.yaml?at=release/1.8.8 | C63: 200 | D63: release/1.8.8 | E63: OK | F63: proteo4.operations-log.appender.sqs.batch.maxInflightOutboundBatches | G63: 1
A64: ns-bff-global-p4-micros-arch | B64: https://bitbucket.apps.devops.aws.bancsabadell.com/rest/api/1.0/projects/P4DES/repos/ns-bff-global-p4-micros-arch/browse/pro/configs/application.yaml?at=release/1.8.8 | C64: 200 | D64: release/1.8.8 | E64: OK | F64: proteo4.crypto.kms.uri | G64: https://vpce-0f3f45908cdf57e70-9kv2zs29.kms.eu-west-1.vpce.amazonaws.com:443
A65: ns-bff-global-p4-micros-arch | B65: https://bitbucket.apps.devops.aws.bancsabadell.com/rest/api/1.0/projects/P4DES/repos/ns-bff-global-p4-micros-arch/browse/pro/configs/application.yaml?at=release/1.8.8 | C65: 200 | D65: release/1.8.8 | E65: OK | F65: proteo4.crypto.kms.region | G65: eu-west-1
A66: ns-bff-global-p4-micros-arch | B66: https://bitbucket.apps.devops.aws.bancsabadell.com/rest/api/1.0/projects/P4DES/repos/ns-bff-global-p4-micros-arch/browse/pro/configs/application.yaml?at=release/1.8.8 | C66: 200 | D66: release/1.8.8 | E66: OK | F66: proteo4.crypto.kms.keyarn | G66: arn:aws:kms:eu-west-1:913536646623:key/ee6bf63d-cc22-4761-91d4-1
A67: ns-bff-global-p4-micros-arch | B67: https://bitbucket.apps.devops.aws.bancsabadell.com/rest/api/1.0/projects/P4DES/repos/ns-bff-global-p4-micros-arch/browse/pro/configs/application.yaml?at=release/1.8.8 | C67: 200 | D67: release/1.8.8 | E67: OK | F67: proteo4.crypto.cache.cacheCapacity | G67: 100
A68: ns-bff-global-p4-micros-arch | B68: https://bitbucket.apps.devops.aws.bancsabadell.com/rest/api/1.0/projects/P4DES/repos/ns-bff-global-p4-micros-arch/browse/pro/configs/application.yaml?at=release/1.8.8 | C68: 200 | D68: release/1.8.8 | E68: OK | F68: proteo4.crypto.cache.maxEntryMessages | G68: 100
A69: ns-bff-global-p4-micros-arch | B69: https://bitbucket.apps.devops.aws.bancsabadell.com/rest/api/1.0/projects/P4DES/repos/ns-bff-global-p4-micros-arch/browse/pro/configs/application.yaml?at=release/1.8.8 | C69: 200 | D69: release/1.8.8 | E69: OK | F69: proteo4.crypto.cache.maxEntryAge | G69: 1000
